Workbook
Name Categories: #REF!
Name Fiscalyear: #REF!
Name Investment_Purpose: #REF!

Sheet LISTED COMPANIES
A1: SN | B1: SYMBOL | C1: Company Name | D1: SYMBOL2 | E1: Sector | F1: SYMBOL3 | G1: Instrument
A2: 1 | B2: NABIL | C2: Nabil Bank Limited | D2: NABIL | E2: Commercial Banks | F2: NABIL | G2: Equity
A3: 2 | B3: NIMB | C3: Nepal Investment Mega Bank Limited | D3: NIMB | E3: Commercial Banks | F3: NIMB | G3: Equity
A4: 3 | B4: SCB | C4: Standard Chartered Bank Limited | D4: SCB | E4: Commercial Banks | F4: SCB | G4: Equity
A5: 4 | B5: HBL | C5: Himalayan Bank Limited | D5: HBL | E5: Commercial Banks | F5: HBL | G5: Equity
A6: 5 | B6: SBI | C6: Nepal SBI Bank Limited | D6: SBI | E6: Commercial Banks | F6: SBI | G6: Equity
A7: 6 | B7: EBL | C7: Everest Bank Limited | D7: EBL | E7: Commercial Banks | F7: EBL | G7: Equity
A8: 7 | B8: NICA | C8: NIC Asia Bank Ltd. | D8: NICA | E8: Commercial Banks | F8: NICA | G8: Equity
A9: 8 | B9: MBL | C9: Machhapuchhre Bank Limited | D9: MBL | E9: Commercial Banks | F9: MBL | G9: Equity
A10: 9 | B10: LSL | C10: Laxmi Sunrise Bank Limited | D10: LSL | E10: Commercial Banks | F10: LSL | G10: Equity
A11: 10 | B11: KBL | C11: Kumari Bank Limited | D11: KBL | E11: Commercial Banks | F11: KBL | G11: Equity
A12: 11 | B12: SBL | C12: Siddhartha Bank Limited | D12: SBL | E12: Commercial Banks | F12: SBL | G12: Equity
A13: 12 | B13: SHL | C13: Soaltee Hotel Limited | D13: SHL | E13: Hotels And Tourism | F13: SHL | G13: Equity
... A362: 361 | B362: HIDCLP | C362: Hydroelectricity Investment & Development Company Limited | D362: HIDCLP | E362: Investment | F362: HIDCLP | G362: Equity

Sheet VALIDATION
A1: TRANSACTION TYPE | C1: FISCAL YEAR | E1: INVESTMENT APPROACH | G1: SECTOR | H1: STOP LOSS CEILING(%)
A2: Purchase | C2: 80-81 | E2: Held for Trading | G2: Commercial Banks | H2: 12
A3: Opening | C3: 81-82 | E3: Available for Sale | G3: Hotels And Tourism | H3: 15
A4: Sale | E4: Held to Maturity | G4: Hydro Power | H4: 22
A5: Bonus Share | G5: Tradings | H5: 18
A6: Right Share | G6: Microfinance | H6: 20
A7: Reedemption | G7: Development Banks | H7: 15
G8: Non Life Insurance | H8: 18
G9: Life Insurance | H9: 18
G10: Finance | H10: 20
G11: MFG & Processing | H11: 20
G12: Investment | H12: 18
G13: Others | H13: 15
G14: Mutual Fund | H14: 15
G15: Corporate Debenture | H15: 15

Sheet Monthly Summary
A2: 1. Shrawan | M2: Purchase | Q2: Sales | T2: Capital Gain Tax | W2: TC AP TAX | X2: WACC AP TAX | Y2: P/L AP TAX
A3: S.No | B3: SYMBOL | C3: Sector | D3: Purchase QTY | E3: Total Purchase Amount | F3: Sales Qty | G3: Sales Amt | H3: TC AP NFRS | I3: Closing Unit | J3: WACC AP NFRS | K3: P/L AP NFRS | M3: Purchase Commission | N3: DP Charges | O3: Total Commission on Purchase | P3: Investment Cost (Including Comission) | Q3: Sales Commission | R3: DP Charges | S3: Total Commission on Sales
A4: 1 | B4: =SHL!B11 -> SHL | C4: =VLOOKUP(Table242830891013141516232425323334353637[[#This Row],[SYMBOL]],Table2[[SYMBOL2]:[Sector ]],2,) -> Hotels And Tourism | D4: =SHL!F11 -> 500 | E4: =SHL!H11 -> 282500 | F4: =SHL!I11 -> 0 | G4: =SHL!K11 -> 0 | H4: =SHL!M11 -> 282500 | I4: =SHL!N11 -> 500 | J4: =SHL!O11 -> 565 | K4: =SHL!P11 -> 0 | M4: =SHL!R11 -> 974.63 | N4: =SHL!S11 -> 25 | O4: =SHL!T11 -> 999.63 | P4: =SHL!U11 -> 283499.63 | Q4: =SHL!V11 -> 0 | R4: =SHL!W11 -> 0 | S4: =SHL!X11 -> 0 | T4: =SHL!Y11 -> 0 | ... Y4: =SHL!AD11 -> 0
A5: 2 | B5: SBI | C5: =VLOOKUP(Table242830891013141516232425323334353637[[#This Row],[SYMBOL]],Table2[[SYMBOL2]:[Sector ]],2,) -> Commercial Banks | D5: =SBI!F17 -> 10924 | E5: =SBI!H17 -> 4806341.5 | F5: =SBI!I17 -> 3444 | G5: =SBI!K17 -> 1537024 | H5: =SBI!M17 -> 3291050.4 | I5: =SBI!N17 -> 7480 | J5: =SBI!O17 -> 439.98 | K5: =SBI!P17 -> 21732.88 | M5: =SBI!R17 -> 0 | N5: =SBI!S17 -> 0 | O5: =SBI!T17 -> 0 | P5: =SBI!U17 -> 4812786.7 | Q5: =SBI!V17 -> 5125.13 | R5: =SBI!W17 -> 75 | S5: =SBI!X17 -> 5200.13 | T5: =SBI!Y17 -> 1451.8 | ... Y5: =SBI!AD17 -> 14500.79
A6: 3 | B6: SCB | C6: =VLOOKUP(Table242830891013141516232425323334353637[[#This Row],[SYMBOL]],Table2[[SYMBOL2]:[Sector ]],2,) -> Commercial Banks | D6: =SCB!F17 -> 1177 | E6: =SCB!H17 -> 772229.7 | F6: =SCB!I17 -> 1177 | G6: =SCB!K17 -> 787090 | H6: =SCB!M17 -> 0 | I6: =SCB!N17 -> 0 | J6: =SCB!O17 -> 0 | K6: =SCB!P17 -> 14860.3 | M6: =SCB!R17 -> 0 | N6: =SCB!S17 -> 0 | O6: =SCB!T17 -> 0 | P6: =SCB!U17 -> 787401.23 | Q6: =SCB!V17 -> 2724.68 | R6: =SCB!W17 -> 25 | S6: =SCB!X17 -> 2749.68 | T6: =SCB!Y17 -> 0 | ... Y6: =SCB!AD17 -> -3060.91
A7: 4 | B7: ICFC | C7: =VLOOKUP(Table242830891013141516232425323334353637[[#This Row],[SYMBOL]],Table2[[SYMBOL2]:[Sector ]],2,) -> Finance | D7: =ICFC!F17 -> 7777 | E7: =ICFC!H17 -> 4985618.9 | F7: =ICFC!I17 -> 7777 | G7: =ICFC!K17 -> 5303427.4 | H7: =ICFC!M17 -> 0 | I7: =ICFC!N17 -> 0 | J7: =ICFC!O17 -> 0 | K7: =ICFC!P17 -> 317808.51 | M7: =ICFC!R17 -> 455.46 | N7: =ICFC!S17 -> 25 | O7: =ICFC!T17 -> 480.46 | P7: =ICFC!U17 -> 5227311 | Q7: =ICFC!V17 -> 17923.25 | R7: =ICFC!W17 -> 50 | S7: =ICFC!X17 -> 17973.25 | T7: =ICFC!Y17 -> 5814.37 | ... Y7: =ICFC!AD17 -> 58143.167
A8: 5 | B8: MFIL | C8: =VLOOKUP(Table242830891013141516232425323334353637[[#This Row],[SYMBOL]],Table2[[SYMBOL2]:[Sector ]],2,) -> Finance | D8: =MFIL!F16 -> 3250 | E8: =MFIL!H16 -> 2025627.5 | F8: =MFIL!I16 -> 3250 | G8: =MFIL!K16 -> 2162074 | H8: =MFIL!M16 -> 0 | I8: =MFIL!N16 -> 0 | J8: =MFIL!O16 -> 0 | K8: =MFIL!P16 -> 136446.5 | M8: =MFIL!R16 -> 0 | N8: =MFIL!S16 -> 0 | O8: =MFIL!T16 -> 0 | P8: =MFIL!U16 -> 2109900 | Q8: =MFIL!V16 -> 7082.07 | R8: =MFIL!W16 -> 50 | S8: =MFIL!X16 -> 7132.07 | T8: =MFIL!Y16 -> 4503.22 | ... Y8: =MFIL!AD16 -> 45041.93
A9: 6 | B9: MNBBL | C9: =VLOOKUP(Table242830891013141516232425323334353637[[#This Row],[SYMBOL]],Table2[[SYMBOL2]:[Sector ]],2,) -> Development Banks | D9: =MNBBL!F12 -> 1000 | E9: =MNBBL!H12 -> 445000 | F9: =MNBBL!I12 -> 0 | G9: =MNBBL!K12 -> 0 | H9: =MNBBL!M12 -> 445000 | I9: =MNBBL!N12 -> 1000 | J9: =MNBBL!O12 -> 445 | K9: =MNBBL!P12 -> 0 | M9: =MNBBL!R12 -> 3070.5 | N9: =MNBBL!S12 -> 50 | O9: =MNBBL!T12 -> 3120.5 | P9: =MNBBL!U12 -> 893120.5 | Q9: =MNBBL!V12 -> 0 | R9: =MNBBL!W12 -> 0 | S9: =MNBBL!X12 -> 0 | T9: =MNBBL!Y12 -> 0 | ... Y9: =MNBBL!AD12 -> 0
A10: 7 | B10: KSBBL | C10: =VLOOKUP(Table242830891013141516232425323334353637[[#This Row],[SYMBOL]],Table2[[SYMBOL2]:[Sector ]],2,) -> Development Banks | D10: =KSBBL!F16 -> 1000 | E10: =KSBBL!H16 -> 532000 | F10: 0 | G10: 0 | H10: =KSBBL!M16 -> 532000 | I10: =KSBBL!N16 -> 1000 | J10: =KSBBL!O16 -> 532 | K10: =KSBBL!P16 -> 0 | M10: =KSBBL!R16 -> 1835.4 | N10: =KSBBL!S16 -> 25 | O10: =KSBBL!T16 -> 1860.4 | P10: =KSBBL!U16 -> 533860.4 | Q10: =KSBBL!V16 -> 0 | R10: =KSBBL!W16 -> 0 | S10: =KSBBL!X16 -> 0 | T10: =KSBBL!Y16 -> 0 | ... Y10: =KSBBL!AD16 -> 0
A11: 8 | B11: LBBL | C11: =VLOOKUP(Table242830891013141516232425323334353637[[#This Row],[SYMBOL]],Table2[[SYMBOL2]:[Sector ]],2,) -> Development Banks | D11: =LBBL!F10 -> 2500 | E11: =LBBL!H10 -> 1275000 | F11: =LBBL!I10 -> 2500 | G11: =LBBL!K10 -> 1373544.9 | H11: =LBBL!M10 -> 0 | I11: =LBBL!N10 -> 0 | J11: =LBBL!O10 -> 0 | K11: =LBBL!P10 -> 98544.9 | M11: =LBBL!R10 -> 4296.75 | N11: =LBBL!S10 -> 25 | O11: =LBBL!T10 -> 4321.75 | P11: =LBBL!U10 -> 1279321.8 | Q11: =LBBL!V10 -> 4747.1 | R11: =LBBL!W10 -> 25 | S11: =LBBL!X10 -> 4772.1 | T11: =LBBL!Y10 -> 8945.05 | ... Y11: =LBBL!AD10 -> 89451.05
A12: 9 | B12: IGI | C12: =VLOOKUP(Table242830891013141516232425323334353637[[#This Row],[SYMBOL]],Table2[[SYMBOL2]:[Sector ]],2,) -> Non Life Insurance | D12: =IGI!F16 -> 6674 | E12: =IGI!H16 -> 3743361.3 | F12: =IGI!I16 -> 0 | G12: =IGI!K16 -> 0 | H12: =IGI!M16 -> 3743361.3 | I12: =IGI!N16 -> 6674 | J12: =IGI!O16 -> 560.88721 | K12: =IGI!P16 -> 0 | M12: =IGI!R16 -> 0 | N12: =IGI!S16 -> 0 | O12: =IGI!T16 -> 0 | P12: =IGI!U16 -> 4152188.1 | Q12: =IGI!V16 -> 0 | R12: =IGI!W16 -> 0 | S12: =IGI!X16 -> 0 | T12: =IGI!Y16 -> 0 | ... Y12: =IGI!AD16 -> 0
A13: 10 | B13: SPIL | C13: =VLOOKUP(Table242830891013141516232425323334353637[[#This Row],[SYMBOL]],Table2[[SYMBOL2]:[Sector ]],2,) -> Non Life Insurance | D13: =SPIL!F12 -> 1500 | E13: =SPIL!H12 -> 1300000 | F13: =SPIL!I12 -> 0 | G13: =SPIL!K12 -> 0 | H13: =SPIL!M12 -> 1300000 | I13: =SPIL!N12 -> 1500 | J13: =SPIL!O12 -> 866.66667 | K13: =SPIL!P12 -> 0 | M13: =SPIL!R12 -> 4372.89 | N13: =SPIL!S12 -> 25 | O13: =SPIL!T12 -> 4397.89 | P13: =SPIL!U12 -> 1304397.9 | Q13: =SPIL!V12 -> 0 | R13: =SPIL!W12 -> 0 | S13: =SPIL!X12 -> 0 | T13: =SPIL!Y12 -> 0 | ... Y13: =SPIL!AD12 -> 0
A14: 11 | B14: HEI | C14: =VLOOKUP(Table242830891013141516232425323334353637[[#This Row],[SYMBOL]],Table2[[SYMBOL2]:[Sector ]],2,) -> Non Life Insurance | D14: =HEI!F12 -> 2381 | E14: =HEI!H12 -> 1505125 | F14: =HEI!I12 -> 0 | G14: =HEI!K12 -> 0 | H14: =HEI!M12 -> 1505125 | I14: =HEI!N12 -> 2381 | J14: =HEI!O12 -> 632.13986 | K14: =HEI!P12 -> 0 | M14: =HEI!R12 -> 5066.29 | N14: =HEI!S12 -> 75 | O14: =HEI!T12 -> 5141.29 | P14: =HEI!U12 -> 1510266.3 | Q14: =HEI!V12 -> 0 | R14: =HEI!W12 -> 0 | S14: =HEI!X12 -> 0 | T14: =HEI!Y12 -> 0 | ... Y14: =HEI!AD12 -> 0
A15: 12 | B15: UAIL | C15: =VLOOKUP(Table242830891013141516232425323334353637[[#This Row],[SYMBOL]],Table2[[SYMBOL2]:[Sector ]],2,) -> Non Life Insurance | D15: =UAIL!F17 -> 6513 | E15: =UAIL!H17 -> 3734290.3 | F15: =UAIL!I17 -> 5987 | G15: =UAIL!K17 -> 3461095 | H15: =UAIL!M17 -> 301587.09 | I15: =UAIL!N17 -> 526 | J15: =UAIL!O17 -> 573.35948 | K15: =UAIL!P17 -> 28391.805 | M15: =UAIL!R17 -> 1026.38 | N15: =UAIL!S17 -> 25 | O15: =UAIL!T17 -> 1051.38 | P15: =UAIL!U17 -> 4158327.9 | Q15: =UAIL!V17 -> 11933.53 | R15: =UAIL!W17 -> 175 | S15: =UAIL!X17 -> 12108.53 | T15: =UAIL!Y17 -> 0 | ... Y15: =UAIL!AD17 -> -477448.41
A16: 13 | B16: NLG | C16: =VLOOKUP(Table242830891013141516232425323334353637[[#This Row],[SYMBOL]],Table2[[SYMBOL2]:[Sector ]],2,) -> Non Life Insurance | D16: =NLG!F16 -> 7517 | E16: =NLG!H16 -> 5918657.8 | F16: =NLG!I16 -> 7320 | G16: =NLG!K16 -> 6741784 | H16: =NLG!M16 -> 158688.45 | I16: =NLG!N16 -> 197 | J16: =NLG!O16 -> 805.52514 | K16: =NLG!P16 -> 981814.69 | M16: =NLG!R16 -> 1554.06 | N16: =NLG!S16 -> 25 | O16: =NLG!T16 -> 1579.06 | P16: =NLG!U16 -> 7085058.8 | Q16: =NLG!V16 -> 22904.02 | R16: =NLG!W16 -> 100 | S16: =NLG!X16 -> 23004.02 | T16: =NLG!Y16 -> 3838.23 | ... Y16: =NLG!AD16 -> -180063.22
A17: 14 | B17: NICL | C17: =VLOOKUP(Table242830891013141516232425323334353637[[#This Row],[SYMBOL]],Table2[[SYMBOL2]:[Sector ]],2,) -> Non Life Insurance | D17: =NICL!F11 -> 3203 | E17: =NICL!H11 -> 2066511.5 | F17: =NICL!I11 -> 3203 | G17: =NICL!K11 -> 2172729.6 | H17: =NICL!M11 -> 0 | I17: =NICL!N11 -> 0 | J17: =NICL!O11 -> 0 | K17: =NICL!P11 -> 106218.06 | M17: =NICL!R11 -> 0 | N17: =NICL!S11 -> 0 | O17: =NICL!T11 -> 0 | P17: =NICL!U11 -> 2862745.3 | Q17: =NICL!V11 -> 7620.04 | R17: =NICL!W11 -> 75 | S17: =NICL!X11 -> 7695.04 | T17: =NICL!Y11 -> 0 | ... Y17: =NICL!AD11 -> -697710.75
A18: 15 | B18: SRLI | C18: =VLOOKUP(Table242830891013141516232425323334353637[[#This Row],[SYMBOL]],Table2[[SYMBOL2]:[Sector ]],2,) -> Life Insurance | D18: =SRLI!F16 -> 6184 | E18: =SRLI!H16 -> 2571222.5 | F18: =SPIL!F12 -> 1500 | G18: =SPIL!H12 -> 1300000 | H18: =SRLI!M16 -> 2571222.5 | I18: =SRLI!N16 -> 6184 | J18: =SRLI!O16 -> 415.78631 | K18: =SRLI!P16 -> 0 | M18: =SRLI!R16 -> 2579.9 | N18: =SRLI!S16 -> 50 | O18: =SRLI!T16 -> 2629.9 | P18: =SRLI!U16 -> 2974864.8 | Q18: =SRLI!V16 -> 0 | R18: =SRLI!W16 -> 0 | S18: =SRLI!X16 -> 0 | T18: =SRLI!Y16 -> 0 | ... Y18: =SRLI!AD16 -> 0
A19: 16 | B19: ILI | C19: =VLOOKUP(Table242830891013141516232425323334353637[[#This Row],[SYMBOL]],Table2[[SYMBOL2]:[Sector ]],2,) -> Life Insurance | D19: =ILI!F17 -> 12446 | E19: =ILI!H17 -> 5789169 | F19: =ILI!I17 -> 0 | G19: =ILI!K17 -> 0 | H19: =ILI!M17 -> 5789169 | I19: =ILI!N17 -> 12446 | J19: =ILI!O17 -> 465.14294 | K19: =ILI!P17 -> 0 | M19: =ILI!R17 -> 3376.55 | N19: =ILI!S17 -> 50 | O19: =ILI!T17 -> 3426.55 | P19: =ILI!U17 -> 6351461.5 | Q19: =ILI!V17 -> 0 | R19: =ILI!W17 -> 0 | S19: =ILI!X17 -> 0 | T19: =ILI!Y17 -> 0 | ... Y19: =ILI!AD17 -> 0
A20: 17 | B20: HLI | C20: =VLOOKUP(Table242830891013141516232425323334353637[[#This Row],[SYMBOL]],Table2[[SYMBOL2]:[Sector ]],2,) -> Life Insurance | D20: =HLI!F10 -> 5140 | E20: =HLI!H10 -> 2104385.4 | F20: =HLI!I10 -> 5140 | G20: =HLI!K10 -> 2219060 | H20: =HLI!M10 -> 0 | I20: =HLI!N10 -> 0 | J20: =HLI!O10 -> 0 | K20: =HLI!P10 -> 114674.6 | M20: =HLI!R10 -> 1491.02 | N20: =HLI!S10 -> 25 | O20: =HLI!T10 -> 1516.02 | P20: =HLI!U10 -> 2246783.5 | Q20: =HLI!V10 -> 7665.69 | R20: =HLI!W10 -> 25 | S20: =HLI!X10 -> 7690.69 | T20: =HLI!Y10 -> 0 | ... Y20: =HLI!AD10 -> -35414.14
A21: 18 | B21: LICN | C21: =VLOOKUP(Table242830891013141516232425323334353637[[#This Row],[SYMBOL]],Table2[[SYMBOL2]:[Sector ]],2,) -> Life Insurance | D21: =LICN!F17 -> 2790 | E21: =LICN!H17 -> 2518230.7 | F21: =LICN!I17 -> 0 | G21: =LICN!K17 -> 0 | H21: =LICN!M17 -> 2518230.7 | I21: =LICN!N17 -> 2790 | J21: =LICN!O17 -> 902.59165 | K21: =LICN!P17 -> 0 | M21: =LICN!R17 -> 2276.11 | N21: =LICN!S17 -> 50 | O21: =LICN!T17 -> 2326.11 | P21: =LICN!U17 -> 2887916.1 | Q21: =LICN!V17 -> 0 | R21: =LICN!W17 -> 0 | S21: =LICN!X17 -> 0 | T21: =LICN!Y17 -> 0 | ... Y21: =LICN!AD17 -> 0
A22: 19 | B22: CLI | C22: =VLOOKUP(Table242830891013141516232425323334353637[[#This Row],[SYMBOL]],Table2[[SYMBOL2]:[Sector ]],2,) -> Life Insurance | D22: =CLI!F17 -> 11147 | E22: =CLI!H17 -> 5302113.3 | F22: =CLI!I17 -> 0 | G22: =CLI!K17 -> 0 | H22: =CLI!M17 -> 5302113.3 | I22: =CLI!N17 -> 11147 | J22: =CLI!O17 -> 475.65383 | K22: =CLI!P17 -> 0 | M22: =CLI!R17 -> 1701.37 | N22: =CLI!S17 -> 25 | O22: =CLI!T17 -> 1726.37 | P22: =CLI!U17 -> 6290453.2 | Q22: =CLI!V17 -> 0 | R22: =CLI!W17 -> 0 | S22: =CLI!X17 -> 0 | T22: =CLI!Y17 -> 0 | ... Y22: =CLI!AD17 -> 0
A23: 20 | B23: SHPC | C23: =VLOOKUP(Table242830891013141516232425323334353637[[#This Row],[SYMBOL]],Table2[[SYMBOL2]:[Sector ]],2,) -> Hydro Power | D23: =SHPC!F9 -> 900 | E23: =SHPC!H9 -> 564219 | F23: =SHPC!I9 -> 900 | G23: =SHPC!K9 -> 583000 | H23: =SHPC!M9 -> 0 | I23: =SHPC!N9 -> 0 | J23: =IFERROR(#REF!/Table242830891013141516232425323334353637[[#This Row],[Closing Unit]],0) -> 0 | K23: =SHPC!P9 -> 18781 | M23: =SHPC!R9 -> 0 | N23: =SHPC!S9 -> 0 | O23: =SHPC!T9 -> 0 | P23: =SHPC!U9 -> 546768 | Q23: =SHPC!V9 -> 2011.35 | R23: =SHPC!W9 -> 25 | S23: =SHPC!X9 -> 2036.35 | T23: =SHPC!Y9 -> 3419.75 | ... Y23: =SHPC!AD9 -> 34195.65
A24: 21 | B24: SJCL | C24: =VLOOKUP(Table242830891013141516232425323334353637[[#This Row],[SYMBOL]],Table2[[SYMBOL2]:[Sector ]],2,) -> Hydro Power | D24: =SJCL!F10 -> 8298 | E24: =SJCL!H10 -> 2639149.4 | F24: =SJCL!I10 -> 0 | G24: =SJCL!K10 -> 0 | H24: =SJCL!M10 -> 2639149.4 | I24: =SJCL!N10 -> 8298 | J24: =SJCL!O10 -> 318.04645 | K24: =SJCL!P10 -> 0 | M24: =SJCL!R10 -> 569.25 | N24: =SJCL!S10 -> 25 | O24: =SJCL!T10 -> 594.25 | P24: =SJCL!U10 -> 2832620.2 | Q24: =SJCL!V10 -> 0 | R24: =SJCL!W10 -> 0 | S24: =SJCL!X10 -> 0 | T24: =SJCL!Y10 -> 0 | ... Y24: =SJCL!AD10 -> 0
A25: 22 | B25: AHPC | C25: =VLOOKUP(Table242830891013141516232425323334353637[[#This Row],[SYMBOL]],Table2[[SYMBOL2]:[Sector ]],2,) -> Hydro Power | D25: =AHPC!F10 -> 1015 | E25: =AHPC!H10 -> 328875.35 | F25: =AHPC!I10 -> 15 | G25: =AHPC!K10 -> 4575 | H25: =AHPC!M10 -> 324500 | I25: =AHPC!N10 -> 1000 | J25: =AHPC!O10 -> 324.5 | K25: =AHPC!P10 -> 199.65 | M25: =AHPC!R10 -> 1138.99 | N25: =AHPC!S10 -> 25 | O25: =AHPC!T10 -> 1163.99 | P25: =AHPC!U10 -> 330285.19 | Q25: =AHPC!V10 -> 17.16 | R25: =AHPC!W10 -> 25 | S25: =AHPC!X10 -> 42.16 | T25: =AHPC!Y10 -> 0 | ... Y25: =AHPC!AD10 -> -88.36
A26: 23 | B26: SMJC | C26: =VLOOKUP(Table242830891013141516232425323334353637[[#This Row],[SYMBOL]],Table2[[SYMBOL2]:[Sector ]],2,) -> Hydro Power | D26: =SMJC!F14 -> 6943 | E26: =SMJC!H14 -> 3696869.8 | F26: =SMJC!I14 -> 6943 | G26: =SMJC!K14 -> 4393017 | H26: =SMJC!M14 -> 0 | I26: =SMJC!N14 -> 0 | J26: =SMJC!O14 -> 0 | K26: =SMJC!P14 -> 696147.22 | M26: =SMJC!R14 -> 0 | N26: =SMJC!S14 -> 0 | O26: =SMJC!T14 -> 0 | P26: =SMJC!U14 -> 4395196.7 | Q26: =SMJC!V14 -> 15074.81 | R26: =SMJC!W14 -> 150 | S26: =SMJC!X14 -> 15224.81 | T26: =SMJC!Y14 -> 3460.77 | ... Y26: =SMJC!AD14 -> -17404.53
A27: 24 | B27: KMCDB | C27: =VLOOKUP(Table242830891013141516232425323334353637[[#This Row],[SYMBOL]],Table2[[SYMBOL2]:[Sector ]],2,) -> Microfinance | D27: =KMCDB!F12 -> 1000 | E27: =KMCDB!H12 -> 1138500 | F27: =KMCDB!I12 -> 0 | G27: =KMCDB!K12 -> 0 | H27: =KMCDB!M12 -> 1138500 | I27: =KMCDB!N12 -> 1000 | J27: =KMCDB!O12 -> 1138.5 | K27: =KMCDB!P12 -> 0 | M27: =KMCDB!R12 -> 3839.98 | N27: =KMCDB!S12 -> 25 | O27: =KMCDB!T12 -> 3864.98 | P27: =KMCDB!U12 -> 1142365 | Q27: =KMCDB!V12 -> 0 | R27: =KMCDB!W12 -> 0 | S27: =KMCDB!X12 -> 0 | T27: =KMCDB!Y12 -> 0 | ... Y27: =KMCDB!AD12 -> 0
A28: 25 | B28: FMDBL | C28: =VLOOKUP(Table242830891013141516232425323334353637[[#This Row],[SYMBOL]],Table2[[SYMBOL2]:[Sector ]],2,) -> Microfinance | D28: =FMDBL!F10 -> 2010 | E28: =FMDBL!H10 -> 1606150.8 | F28: =FMDBL!I10 -> 2010 | G28: =FMDBL!K10 -> 1830570 | H28: =FMDBL!M10 -> 0 | I28: =FMDBL!N10 -> 0 | J28: =FMDBL!O10 -> 0 | K28: =FMDBL!P10 -> 224419.2 | M28: =FMDBL!R10 -> 0 | N28: =FMDBL!S10 -> 0 | O28: =FMDBL!T10 -> 0 | P28: =FMDBL!U10 -> 1688239.2 | Q28: =FMDBL!V10 -> 6339.33 | R28: =FMDBL!W10 -> 50 | S28: =FMDBL!X10 -> 6389.33 | T28: =FMDBL!Y10 -> 13595.16 | ... Y28: =FMDBL!AD10 -> 135941.47
A29: 26 | B29: MSLB | C29: =VLOOKUP(Table242830891013141516232425323334353637[[#This Row],[SYMBOL]],Table2[[SYMBOL2]:[Sector ]],2,) -> Microfinance | D29: =MSLB!F18 -> 4906 | E29: =MSLB!H18 -> 6375557.7 | F29: =MSLB!I18 -> 4906 | G29: =MSLB!K18 -> 7204920 | H29: =MSLB!M18 -> 0 | I29: =MSLB!N18 -> 0 | J29: =MSLB!O18 -> 0 | K29: =MSLB!P18 -> 829362.34 | M29: =MSLB!R18 -> 745.44 | N29: =MSLB!S18 -> 50 | O29: =MSLB!T18 -> 795.44 | P29: =MSLB!U18 -> 7172942.3 | Q29: =MSLB!V18 -> 23928.71 | R29: =MSLB!W18 -> 175 | S29: =MSLB!X18 -> 24103.71 | T29: =MSLB!Y18 -> 11488.56 | ... Y29: =MSLB!AD18 -> 7873.95
A30: 27 | B30: NMLBBL | C30: =VLOOKUP(Table242830891013141516232425323334353637[[#This Row],[SYMBOL]],Table2[[SYMBOL2]:[Sector ]],2,) -> Microfinance | D30: =NMLBBL!F13 -> 1520 | E30: =NMLBBL!H13 -> 1064532 | F30: =NMLBBL!I13 -> 1520 | G30: =NMLBBL!K13 -> 1184112 | H30: =NMLBBL!M13 -> 0 | I30: =NMLBBL!N13 -> 0 | J30: =NMLBBL!O13 -> 0 | K30: =NMLBBL!P13 -> 119580 | M30: =NMLBBL!R13 -> 0 | N30: =NMLBBL!S13 -> 0 | O30: =NMLBBL!T13 -> 0 | P30: =NMLBBL!U13 -> 1223888.8 | Q30: =NMLBBL!V13 -> 3989.95 | R30: =NMLBBL!W13 -> 25 | S30: =NMLBBL!X13 -> 4014.95 | T30: =NMLBBL!Y13 -> 0 | ... Y30: =NMLBBL!AD13 -> -43791.75
A31: 28 | B31: DDBL | C31: =VLOOKUP(Table242830891013141516232425323334353637[[#This Row],[SYMBOL]],Table2[[SYMBOL2]:[Sector ]],2,) -> Microfinance | D31: =DDBL!F17 -> 7012 | E31: =DDBL!H17 -> 6186337 | F31: =DDBL!I17 -> 7012 | G31: =DDBL!K17 -> 6746904 | H31: =DDBL!M17 -> 0 | I31: =DDBL!N17 -> 0 | J31: =DDBL!O17 -> 0 | K31: =DDBL!P17 -> 560567 | M31: =DDBL!R17 -> 0 | N31: =DDBL!S17 -> 0 | O31: =DDBL!T17 -> 0 | P31: =DDBL!U17 -> 6200992.1 | Q31: =DDBL!V17 -> 22544.37 | R31: =DDBL!W17 -> 100 | S31: =DDBL!X17 -> 22644.37 | T31: =DDBL!Y17 -> 52326.77 | ... Y31: =DDBL!AD17 -> 523267.55
A32: 29 | B32: CHDC | C32: =VLOOKUP(Table242830891013141516232425323334353637[[#This Row],[SYMBOL]],Table2[[SYMBOL2]:[Sector ]],2,) -> Investment | D32: =CHDC!F11 -> 544 | E32: =CHDC!H11 -> 1554007 | F32: =CHDC!I11 -> 0 | G32: =CHDC!K11 -> 0 | H32: =CHDC!M11 -> 1554007 | I32: =CHDC!N11 -> 544 | J32: =CHDC!O11 -> 2856.6305 | K32: =CHDC!P11 -> 0 | M32: =CHDC!R11 -> 5261.95 | N32: =CHDC!S11 -> 75 | O32: =CHDC!T11 -> 5336.95 | P32: =CHDC!U11 -> 1559343.9 | Q32: =CHDC!V11 -> 0 | R32: =CHDC!W11 -> 0 | S32: =CHDC!X11 -> 0 | T32: =CHDC!Y11 -> 0 | ... Y32: =CHDC!AD11 -> 0
A33: 30 | B33: HATHY | C33: =VLOOKUP(Table242830891013141516232425323334353637[[#This Row],[SYMBOL]],Table2[[SYMBOL2]:[Sector ]],2,) -> Investment | D33: =HATHY!F14 -> 4946 | E33: =HATHY!H14 -> 6346607.4 | F33: =HATHY!I14 -> 1696 | G33: =HATHY!K14 -> 2203104 | H33: =HATHY!M14 -> 4277250 | I33: =HATHY!N14 -> 3250 | J33: =HATHY!O14 -> 1316.0769 | K33: =HATHY!P14 -> 133746.56 | M33: =HATHY!R14 -> 14228.09 | N33: =HATHY!S14 -> 125 | O33: =HATHY!T14 -> 14353.09 | P33: =HATHY!U14 -> 6418726.3 | Q33: =HATHY!V14 -> 6278.85 | R33: =HATHY!W14 -> 25 | S33: =HATHY!X14 -> 6303.85 | T33: =HATHY!Y14 -> 6967.7 | ... Y33: =HATHY!AD14 -> 69676.95
A34: 31 | B34: HIDCL | C34: =VLOOKUP(Table242830891013141516232425323334353637[[#This Row],[SYMBOL]],Table2[[SYMBOL2]:[Sector ]],2,) -> Investment | D34: =HIDCL!F10 -> 1893 | E34: =HIDCL!H10 -> 553910.73 | F34: =HIDCL!I10 -> 1893 | G34: =HIDCL!K10 -> 594561 | H34: =HIDCL!M10 -> 0 | I34: =HIDCL!N10 -> 0 | J34: =HIDCL!O10 -> 0 | K34: =HIDCL!P10 -> 40650.27 | M34: =HIDCL!R10 -> 0 | N34: =HIDCL!S10 -> 0 | O34: =HIDCL!T10 -> 0 | P34: =HIDCL!U10 -> 549133.24 | Q34: =HIDCL!V10 -> 2082.47 | R34: =HIDCL!W10 -> 50 | S34: =HIDCL!X10 -> 2132.47 | T34: =HIDCL!Y10 -> 4329.59 | ... Y34: =HIDCL!AD10 -> 43295.294
A35: 32 | B35: SMHL | C35: =VLOOKUP(Table242830891013141516232425323334353637[[#This Row],[SYMBOL]],Table2[[SYMBOL2]:[Sector ]],2,) -> Hydro Power | D35: =SMHL!F12 -> 1940 | E35: =SMHL!H12 -> 2150257.2 | F35: =SMHL!I12 -> 1940 | G35: =SMHL!K12 -> 2102370 | H35: =SMHL!M12 -> 0 | I35: =SMHL!N12 -> 0 | J35: =SMHL!O12 -> 0 | K35: =SMHL!P12 -> -47887.2 | M35: =SMHL!R12 -> 0 | N35: =SMHL!S12 -> 0 | O35: =SMHL!T12 -> 0 | P35: =SMHL!U12 -> 2060435.2 | Q35: =SMHL!V12 -> 6886.96 | R35: =SMHL!W12 -> 100 | S35: =SMHL!X12 -> 6986.96 | T35: =SMHL!Y12 -> 3494.58 | ... Y35: =SMHL!AD12 -> 34947.84
B36: TVCL | C36: =VLOOKUP(Table242830891013141516232425323334353637[[#This Row],[SYMBOL]],Table2[[SYMBOL2]:[Sector ]],2,) -> Hydro Power | D36: =TVCL!F17 -> 11172 | E36: =TVCL!H17 -> 5537290.1 | F36: =TVCL!I17 -> 0 | G36: =TVCL!K17 -> 0 | H36: =TVCL!M17 -> 5537290.1 | I36: =TVCL!N17 -> 11172 | J36: =TVCL!O17 -> 495.64 | K36: =TVCL!P17 -> 0 | M36: =TVCL!R17 -> 0 | N36: =TVCL!S17 -> 0 | O36: =TVCL!T17 -> 0 | P36: =TVCL!U17 -> 120957.01 | Q36: =TVCL!V17 -> 0 | R36: =TVCL!W17 -> 0 | S36: =TVCL!X17 -> 0 | T36: =TVCL!Y17 -> 0 | ... Y36: =TVCL!AD17 -> 568.8637
A37: 33 | B37: SGIC | C37: =VLOOKUP(Table242830891013141516232425323334353637[[#This Row],[SYMBOL]],Table2[[SYMBOL2]:[Sector ]],2,) -> Non Life Insurance | D37: =SGIC!F11 -> 8461 | E37: =SGIC!H11 -> 5161125.4 | F37: =SGIC!I11 -> 0 | G37: =SGIC!K11 -> 0 | H37: =SGIC!M11 -> 5161125.4 | I37: =SGIC!N11 -> 8461 | J37: =SGIC!O11 -> 609.99 | K37: =SGIC!P11 -> 0
A38: 34 | B38: HRL | C38: =VLOOKUP(Table242830891013141516232425323334353637[[#This Row],[SYMBOL]],Table2[[SYMBOL2]:[Sector ]],2,) -> Others | D38: =HRL!F9 -> 148 | E38: =HRL!H9 -> 136571.44 | F38: =HRL!I9 -> 65 | G38: =HRL!K9 -> 62003.5 | H38: =HRL!M9 -> 76590.74 | I38: =HRL!N9 -> 83 | J38: =HRL!O9 -> 922.78 | K38: =HRL!P9 -> 2022.8 | M38: =HRL!R9 -> 0 | N38: =HRL!S9 -> 0 | O38: =HRL!T9 -> 0 | P38: =HRL!U9 -> 136894.08 | Q38: =HRL!V9 -> 213.91 | R38: =HRL!W9 -> 25 | S38: =HRL!X9 -> 238.91 | T38: =HRL!Y9 -> 164.22 | ... Y38: =HRL!AD9 -> 1642.19
A39: 35 | B39: GWFD83 | C39: =VLOOKUP(Table242830891013141516232425323334353637[[#This Row],[SYMBOL]],Table2[[SYMBOL2]:[Sector ]],2,) -> Corporate Debenture | D39: =GWFD83!F17 -> 458 | E39: =GWFD83!H17 -> 572454.2 | F39: =GWFD83!I17 -> 0 | G39: =GWFD83!K17 -> 0 | H39: =GWFD83!M17 -> 572454.2 | I39: =GWFD83!N17 -> 458 | J39: =GWFD83!O17 -> 1249.9 | K39: =GWFD83!P17 -> 0 | M39: =GWFD83!R17 -> 0 | N39: =GWFD83!S17 -> 0 | O39: =GWFD83!T17 -> 0 | P39: =GWFD83!U17 -> 478014.33 | Q39: =GWFD83!V17 -> 0 | R39: =GWFD83!W17 -> 0 | S39: =GWFD83!X17 -> 0 | T39: =GWFD83!Y17 -> 0 | ... Y39: =GWFD83!AD17 -> 0
A40: 36 | B40: CCBD88 | C40: =VLOOKUP(Table242830891013141516232425323334353637[[#This Row],[SYMBOL]],Table2[[SYMBOL2]:[Sector ]],2,) -> Corporate Debenture | D40: =CCBD88!F17 -> 50 | E40: =CCBD88!H17 -> 60945 | F40: =CCBD88!I17 -> 0 | G40: =CCBD88!K17 -> 0 | H40: =CCBD88!M17 -> 60945 | I40: =CCBD88!N17 -> 50 | J40: =CCBD88!O17 -> 1218.9 | K40: =CCBD88!P17 -> 0 | M40: =CCBD88!R17 -> 0 | N40: =CCBD88!S17 -> 0 | O40: =CCBD88!T17 -> 0 | P40: =CCBD88!U17 -> 52385.005 | Q40: =CCBD88!V17 -> 0 | R40: =CCBD88!W17 -> 0 | S40: =CCBD88!X17 -> 0 | T40: =CCBD88!Y17 -> 0 | ... Y40: =CCBD88!AD17 -> 0
A41: 37 | B41: CBLD88 | C41: =VLOOKUP(Table242830891013141516232425323334353637[[#This Row],[SYMBOL]],Table2[[SYMBOL2]:[Sector ]],2,) -> Corporate Debenture | D41: =CBLD88!F17 -> 201 | E41: =CBLD88!H17 -> 242205 | F41: =CBLD88!I17 -> 0 | G41: =CBLD88!K17 -> 0 | H41: =CBLD88!M17 -> 242205 | I41: =CBLD88!N17 -> 201 | J41: =CBLD88!O17 -> 1205 | K41: =CBLD88!P17 -> 0 | M41: =CBLD88!R17 -> 0 | N41: =CBLD88!S17 -> 0 | O41: =CBLD88!T17 -> 0 | P41: =CBLD88!U17 -> 213398.18 | Q41: =CBLD88!V17 -> 0 | R41: =CBLD88!W17 -> 0 | S41: =CBLD88!X17 -> 0 | T41: =CBLD88!Y17 -> 0 | ... Y41: =CBLD88!AD17 -> 0
A42: 38 | B42: PBD88 | C42: =VLOOKUP(Table242830891013141516232425323334353637[[#This Row],[SYMBOL]],Table2[[SYMBOL2]:[Sector ]],2,) -> Corporate Debenture | D42: ='PBD88'!F17 -> 10030 | E42: ='PBD88'!H17 -> 12046030 | F42: ='PBD88'!I17 -> 0 | G42: ='PBD88'!K17 -> 0 | H42: ='PBD88'!M17 -> 12046030 | I42: ='PBD88'!N17 -> 10030 | J42: ='PBD88'!O17 -> 1201 | K42: ='PBD88'!P17 -> 0 | M42: ='PBD88'!R17 -> 0 | N42: ='PBD88'!S17 -> 0 | O42: ='PBD88'!T17 -> 0 | P42: ='PBD88'!U17 -> 9640250.2 | Q42: ='PBD88'!V17 -> 0 | R42: ='PBD88'!W17 -> 0 | S42: ='PBD88'!X17 -> 0 | T42: ='PBD88'!Y17 -> 0 | ... Y42: ='PBD88'!AD17 -> 0
A43: 39 | B43: GBILD86/87 | C43: =VLOOKUP(Table242830891013141516232425323334353637[[#This Row],[SYMBOL]],Table2[[SYMBOL2]:[Sector ]],2,) -> Corporate Debenture | D43: =GBILD86_87!F17 -> 105 | E43: =GBILD86_87!H17 -> 113400 | F43: =GBILD86_87!I17 -> 0 | G43: =GBILD86_87!K17 -> 0 | H43: =GBILD86_87!M17 -> 113400 | I43: =GBILD86_87!N17 -> 105 | J43: =GBILD86_87!O17 -> 1080 | K43: =GBILD86_87!P17 -> 0 | M43: =GBILD86_87!R17 -> 0 | N43: =GBILD86_87!S17 -> 0 | O43: =GBILD86_87!T17 -> 0 | P43: =GBILD86_87!U17 -> 108268.91 | Q43: =GBILD86_87!V17 -> 0 | R43: =GBILD86_87!W17 -> 0 | S43: =GBILD86_87!X17 -> 0 | T43: =GBILD86_87!Y17 -> 0 | ... Y43: =GBILD86_87!AD17 -> 0
A44: 40 | B44: NMBD87/88 | C44: =VLOOKUP(Table242830891013141516232425323334353637[[#This Row],[SYMBOL]],Table2[[SYMBOL2]:[Sector ]],2,) -> Corporate Debenture | D44: =NMBD87_88!F17 -> 25 | E44: =NMBD87_88!H17 -> 27425 | F44: =NMBD87_88!I17 -> 0 | G44: =NMBD87_88!K17 -> 0 | H44: =NMBD87_88!M17 -> 27425 | I44: =NMBD87_88!N17 -> 25 | J44: =NMBD87_88!O17 -> 1097 | K44: =NMBD87_88!P17 -> 0 | M44: =NMBD87_88!R17 -> 0 | N44: =NMBD87_88!S17 -> 0 | O44: =NMBD87_88!T17 -> 0 | P44: =NMBD87_88!U17 -> 25803.325 | Q44: =NMBD87_88!V17 -> 0 | R44: =NMBD87_88!W17 -> 0 | S44: =NMBD87_88!X17 -> 0 | T44: =NMBD87_88!Y17 -> 0 | ... Y44: =NMBD87_88!AD17 -> 0
A45: 41 | B45: SBLD84 | C45: =VLOOKUP(Table242830891013141516232425323334353637[[#This Row],[SYMBOL]],Table2[[SYMBOL2]:[Sector ]],2,) -> Corporate Debenture | D45: =SBLD84!F17 -> 96 | E45: =SBLD84!H17 -> 105840 | F45: =SBLD84!I17 -> 0 | G45: =SBLD84!K17 -> 0 | H45: =SBLD84!M17 -> 105840 | I45: =SBLD84!N17 -> 96 | J45: =SBLD84!O17 -> 1102.5 | K45: =SBLD84!P17 -> 0 | M45: =SBLD84!R17 -> 0 | N45: =SBLD84!S17 -> 0 | O45: =SBLD84!T17 -> 0 | P45: =SBLD84!U17 -> 98807.818 | Q45: =SBLD84!V17 -> 0 | R45: =SBLD84!W17 -> 0 | S45: =SBLD84!X17 -> 0 | T45: =SBLD84!Y17 -> 0 | ... Y45: =SBLD84!AD17 -> 0
A46: 42 | B46: NIBD84 | C46: =VLOOKUP(Table242830891013141516232425323334353637[[#This Row],[SYMBOL]],Table2[[SYMBOL2]:[Sector ]],2,) -> Corporate Debenture | D46: =NIBD84!F17 -> 25 | E46: =NIBD84!H17 -> 26050 | F46: =NIBD84!I17 -> 0 | G46: =NIBD84!K17 -> 0 | H46: =NIBD84!M17 -> 26050 | I46: =NIBD84!N17 -> 25 | J46: =NIBD84!O17 -> 1042 | K46: =NIBD84!P17 -> 0 | M46: =NIBD84!R17 -> 0 | N46: =NIBD84!S17 -> 0 | O46: =NIBD84!T17 -> 0 | P46: =NIBD84!U17 -> 25840.688 | Q46: =NIBD84!V17 -> 0 | R46: =NIBD84!W17 -> 0 | S46: =NIBD84!X17 -> 0 | T46: =NIBD84!Y17 -> 0 | ... Y46: =NIBD84!AD17 -> 0
A47: 43 | B47: KEF | C47: =VLOOKUP(Table242830891013141516232425323334353637[[#This Row],[SYMBOL]],Table2[[SYMBOL2]:[Sector ]],2,) -> Mutual Fund | D47: =KEF!F17 -> 2000 | E47: =KEF!H17 -> 19900 | F47: =KEF!I17 -> 0 | G47: =KEF!K17 -> 0 | H47: =KEF!M17 -> 19900 | I47: =KEF!N17 -> 2000 | J47: =KEF!O17 -> 9.95 | K47: =KEF!P17 -> 0 | M47: =KEF!R17 -> 0 | N47: =KEF!S17 -> 0 | O47: =KEF!T17 -> 0 | P47: =KEF!U17 -> 17908.8 | Q47: =KEF!V17 -> 0 | R47: =KEF!W17 -> 0 | S47: =KEF!X17 -> 0 | T47: =KEF!Y17 -> 0 | ... Y47: =KEF!AD17 -> 0
A48: 44 | B48: SFMF | C48: =VLOOKUP(Table242830891013141516232425323334353637[[#This Row],[SYMBOL]],Table2[[SYMBOL2]:[Sector ]],2,) -> Mutual Fund | D48: =SFMF!F17 -> 46876 | E48: =SFMF!H17 -> 500635.68 | F48: =SFMF!I17 -> 0 | G48: =SFMF!K17 -> 0 | H48: =SFMF!M17 -> 500635.68 | I48: =SFMF!N17 -> 46876 | J48: =SFMF!O17 -> 10.68 | K48: =SFMF!P17 -> 0 | M48: =SFMF!R17 -> 0 | N48: =SFMF!S17 -> 0 | O48: =SFMF!T17 -> 0 | P48: =SFMF!U17 -> 515115.68 | Q48: =SFMF!V17 -> 0 | R48: =SFMF!W17 -> 0 | S48: =SFMF!X17 -> 0 | T48: =SFMF!Y17 -> 0 | ... Y48: =SFMF!AD17 -> 0
A49: 45 | B49: NICFC | C49: =VLOOKUP(Table242830891013141516232425323334353637[[#This Row],[SYMBOL]],Table2[[SYMBOL2]:[Sector ]],2,) -> Mutual Fund | D49: =NICFC!F17 -> 2935 | E49: =NICFC!H17 -> 29790.25 | F49: =NICFC!I17 -> 0 | G49: =NICFC!K17 -> 0 | H49: =NICFC!M17 -> 29790.25 | I49: =NICFC!N17 -> 2935 | J49: =NICFC!O17 -> 10.15 | K49: =NICFC!P17 -> 0 | M49: =NICFC!R17 -> 0 | N49: =NICFC!S17 -> 0 | O49: =NICFC!T17 -> 0 | P49: =NICFC!U17 -> 28424.594 | Q49: =NICFC!V17 -> 0 | R49: =NICFC!W17 -> 0 | S49: =NICFC!X17 -> 0 | T49: =NICFC!Y17 -> 0 | ... Y49: =NICFC!AD17 -> 0
A50: 46 | B50: H8020 | C50: =VLOOKUP(Table242830891013141516232425323334353637[[#This Row],[SYMBOL]],Table2[[SYMBOL2]:[Sector ]],2,) -> Mutual Fund | D50: ='H8020'!F17 -> 3400 | E50: ='H8020'!H17 -> 39440 | F50: ='H8020'!I17 -> 0 | G50: ='H8020'!K17 -> 0 | H50: ='H8020'!M17 -> 39440 | I50: ='H8020'!N17 -> 3400 | J50: ='H8020'!O17 -> 11.6 | K50: ='H8020'!P17 -> 0 | M50: ='H8020'!R17 -> 0 | N50: ='H8020'!S17 -> 0 | O50: ='H8020'!T17 -> 0 | P50: ='H8020'!U17 -> 36811.12 | Q50: ='H8020'!V17 -> 0 | R50: ='H8020'!W17 -> 0 | S50: ='H8020'!X17 -> 0 | T50: ='H8020'!Y17 -> 0 | ... Y50: ='H8020'!AD17 -> 0
C51: Total | D51: =SUM(D4:D50) -> 222532 | E51: =SUM(E4:E50) -> 1.1050146e+08 | F51: =SUM(F4:F50) -> 70198 | G51: =SUM(G4:G50) -> 53966965 | H51: =SUM(H4:H50) -> 62232575 | I51: =SUM(I4:I50) -> 153834 | J51: =SUM(J4:J50) -> 24900.577 | K51: =SUM(K4:K50) -> 4398081.1 | ... Y51: =SUM(Y4:Y50) -> -396435.38

Sheet SGIC
A1: Jyoti Capital Limited
A2: Kamalpokhari, Kathmandu
A3: JCL Portfolio Statement
A5: 1. Shrawan | R5: Purchase | V5: Sales | Y5: Capital Gain Tax | Z5: Net Receivables | AA5: Principal Amt AP TAX (Sales Unit) | AB5: TC AP TAX | AC5: WACC AP TAX | AD5: P/L AP TAX
A6: S.No | B6: SYMBOL | C6: Bill No | D6: Txn Date | E6: Txn Type | F6: Purchase QTY | G6: PPPU | H6: Total Purchase Amount | I6: Sales Qty | J6: SPPU | K6: Sales Amt | L6: Principal Cost As per NFRS (In case of Sales) | M6: TC AP NFRS | N6: Unit Sum | O6: WACC AP NFRS | P6: P/L AP NFRS | R6: Purchase Commission | S6: DP Charges | T6: Total Commission on Purchase | U6: Total Investment Cost(Including Comission | V6: Sales Commission | W6: DP Charges | X6: Total Commission on Sales
A7: 1 | B7: SGIC | D7: 45855 | E7: Opening | F7: 8461 | G7: 609.99 | H7: =Table242830891013141516232425323334353641[[#This Row],[Purchase QTY]]*Table242830891013141516232425323334353641[[#This Row],[PPPU]] -> 5161125.4 | M7: =Table242830891013141516232425323334353641[[#This Row],[Total Purchase Amount]] -> 5161125.4 | N7: =IF(Table242830891013141516232425323334353641[[#This Row],[Txn Type]]="opening",Table242830891013141516232425323334353641[[#This Row],[Purchase QTY]],"Error") -> 8461 | O7: =IFERROR(Table242830891013141516232425323334353641[[#This Row],[TC AP NFRS]]/Table242830891013141516232425323334353641[[#This Row],[Unit Sum]],0) -> 609.99 | P7: =Table242830891013141516232425323334353641[[#This Row],[Sales Amt]]-Table242830891013141516232425323334353641[[#This Row],[Principal Cost As per NFRS (In case of Sales)]] -> 0 | T7: =R7+S7 -> 0 | U7: =AB7 -> 5568996.4 | AB7: =F7*AC7 -> 5568996.4 | AC7: 658.196
A8: =A7+1 -> 2 | B8: SGIC | G8: =Table242830891013141516232425323334353641[[#This Row],[Total Purchase Amount]]/Table242830891013141516232425323334353641[[#This Row],[Purchase QTY]] -> #DIV/0! | I8: 0 | J8: =IFERROR(Table242830891013141516232425323334353641[[#This Row],[Sales Amt]]/Table242830891013141516232425323334353641[[#This Row],[Sales Qty]],0) -> 0 | K8: 0 | L8: =Table242830891013141516232425323334353641[[#This Row],[Sales Qty]]*O7 -> 0 | M8: =M7+Table242830891013141516232425323334353641[[#This Row],[Total Purchase Amount]]-Table242830891013141516232425323334353641[[#This Row],[Principal Cost As per NFRS (In case of Sales)]] -> 5161125.4 | N8: =N7+Table242830891013141516232425323334353641[[#This Row],[Purchase QTY]]-Table242830891013141516232425323334353641[[#This Row],[Sales Qty]] -> 8461 | O8: =IFERROR(Table242830891013141516232425323334353641[[#This Row],[TC AP NFRS]]/Table242830891013141516232425323334353641[[#This Row],[Unit Sum]],0) -> 609.99 | P8: =Table242830891013141516232425323334353641[[#This Row],[Sales Amt]]-Table242830891013141516232425323334353641[[#This Row],[Principal Cost As per NFRS (In case of Sales)]] -> 0 | T8: =R8+S8 -> 0 | U8: =H8+T8 -> 0 | V8: 0 | W8: 0 | X8: =V8+W8 -> 0 | Y8: 0 | Z8: =K8-X8-Y8 -> 0 | AA8: =I8*AC7 -> 0 | AB8: =AB7+U8-AA8 -> 5568996.4 | AC8: =IFERROR(AB8/N8,0) -> 658.196 | AD8: =Z8-AA8+Y8 -> 0
A9: =A8+1 -> 3 | G9: =IF(Table242830891013141516232425323334353641[[#This Row],[SPPU]]>=0,0,Table242830891013141516232425323334353641[[#This Row],[Total Purchase Amount]]/Table242830891013141516232425323334353641[[#This Row],[Purchase QTY]]) -> 0 | J9: =IFERROR(Table242830891013141516232425323334353641[[#This Row],[Sales Amt]]/Table242830891013141516232425323334353641[[#This Row],[Sales Qty]],0) -> 0 | L9: =Table242830891013141516232425323334353641[[#This Row],[Sales Qty]]*O8 -> 0 | M9: =M8+Table242830891013141516232425323334353641[[#This Row],[Total Purchase Amount]]-Table242830891013141516232425323334353641[[#This Row],[Principal Cost As per NFRS (In case of Sales)]] -> 5161125.4 | N9: =N8+Table242830891013141516232425323334353641[[#This Row],[Purchase QTY]]-Table242830891013141516232425323334353641[[#This Row],[Sales Qty]] -> 8461 | O9: =IFERROR(Table242830891013141516232425323334353641[[#This Row],[TC AP NFRS]]/Table242830891013141516232425323334353641[[#This Row],[Unit Sum]],0) -> 609.99 | P9: =Table242830891013141516232425323334353641[[#This Row],[Sales Amt]]-Table242830891013141516232425323334353641[[#This Row],[Principal Cost As per NFRS (In case of Sales)]] -> 0 | R9: 0 | T9: =R9+S9 -> 0 | U9: =H9+T9 -> 0 | V9: 0 | W9: 0 | X9: =V9+W9 -> 0 | Y9: 0 | Z9: =K9-X9-Y9 -> 0 | AA9: =I9*AC8 -> 0 | AB9: =AB8+U9-AA9 -> 5568996.4 | AC9: =IFERROR(AB9/N9,0) -> 658.196 | AD9: =Z9-AA9+Y9 -> 0
A10: =A9+1 -> 4 | G10: =IF(Table242830891013141516232425323334353641[[#This Row],[SPPU]]>=0,0,Table242830891013141516232425323334353641[[#This Row],[Total Purchase Amount]]/Table242830891013141516232425323334353641[[#This Row],[Purchase QTY]]) -> 0 | I10: 0 | J10: =IFERROR(Table242830891013141516232425323334353641[[#This Row],[Sales Amt]]/Table242830891013141516232425323334353641[[#This Row],[Sales Qty]],0) -> 0 | K10: 0 | L10: =Table242830891013141516232425323334353641[[#This Row],[Sales Qty]]*O9 -> 0 | M10: =M9+Table242830891013141516232425323334353641[[#This Row],[Total Purchase Amount]]-Table242830891013141516232425323334353641[[#This Row],[Principal Cost As per NFRS (In case of Sales)]] -> 5161125.4 | N10: =N9+Table242830891013141516232425323334353641[[#This Row],[Purchase QTY]]-Table242830891013141516232425323334353641[[#This Row],[Sales Qty]] -> 8461 | O10: =IFERROR(Table242830891013141516232425323334353641[[#This Row],[TC AP NFRS]]/Table242830891013141516232425323334353641[[#This Row],[Unit Sum]],0) -> 609.99 | P10: =Table242830891013141516232425323334353641[[#This Row],[Sales Amt]]-Table242830891013141516232425323334353641[[#This Row],[Principal Cost As per NFRS (In case of Sales)]] -> 0 | R10: 0 | T10: =R10+S10 -> 0 | U10: =H10+T10 -> 0 | V10: 0 | W10: 0 | X10: =V10+W10 -> 0 | Y10: 0 | Z10: =K10-X10-Y10 -> 0 | AA10: =I10*AC9 -> 0 | AB10: =AB9+U10-AA10 -> 5568996.4 | AC10: =IFERROR(AB10/N10,0) -> 658.196 | AD10: =Z10-AA10+Y10 -> 0
A11: Total | B11: SGIC | F11: =SUM(INDIRECT("f4:f"&ROW()-1)) -> 8461 | H11: =SUM(INDIRECT("h4:h"&ROW()-1)) -> 5161125.4 | I11: =SUM(INDIRECT("i4:i"&ROW()-1)) -> 0 | J11: =Table242830891013141516232425323334353641[[#This Row],[Sales Amt]]/Table242830891013141516232425323334353641[[#This Row],[Sales Qty]] -> #DIV/0! | K11: =SUM(INDIRECT("k4:k"&ROW()-1)) -> 0 | M11: =Table242830891013141516232425323334353641[[#This Row],[Total Purchase Amount]]-Table242830891013141516232425323334353641[[#This Row],[Principal Cost As per NFRS (In case of Sales)]] -> 5161125.4 | N11: =Table242830891013141516232425323334353641[[#This Row],[Purchase QTY]]-Table242830891013141516232425323334353641[[#This Row],[Sales Qty]] -> 8461 | O11: =Table242830891013141516232425323334353641[[#This Row],[TC AP NFRS]]/Table242830891013141516232425323334353641[[#This Row],[Unit Sum]] -> 609.99 | P11: =SUM(INDIRECT("p4:p"&ROW()-1)) -> 0 | R11: =SUM(R7:R10) -> 0 | S11: =SUM(S7:S10) -> 0 | T11: =SUM(T7:T10) -> 0 | U11: =SUM(U7:U10) -> 5568996.4 | V11: =SUM(V7:V10) -> 0 | W11: =SUM(W7:W10) -> 0 | X11: =SUM(X7:X10) -> 0 | Y11: =SUM(Y7:Y10) -> 0 | ... AA11: =SUM(AA7:AA10) -> 0 | AB11: =U11-AA11 -> 5568996.4 | AC11: =AB11/Table242830891013141516232425323334353641[[#This Row],[Unit Sum]] -> 658.196 | AD11: =SGIC!AJ15 -> 0
A13: 2. Bhadra | R13: Purchase | V13: Sales | Y13: Capital Gain Tax | Z13: Net Receivables | AA13: Principal Amt AP TAX (Sales Unit) | AB13: TC AP TAX | AC13: WACC AP TAX | AD13: P/L AP TAX
A14: S.No | B14: SYMBOL | C14: Bill No | D14: Txn Date | E14: Txn Type | F14: Purchase QTY | G14: PPPU | H14: Total Purchase Amount | I14: Sales Qty | J14: SPPU | K14: Sales Amt | L14: Principal Cost As per NFRS (In case of Sales) | M14: TC AP NFRS | N14: Unit Sum | O14: WACC AP NFRS | P14: P/L AP NFRS | R14: Purchase Commission | S14: DP Charges | T14: Total Commission on Purchase | U14: Total Investment Cost(Including Comission | V14: Sales Commission | W14: DP Charges | X14: Total Commission on Sales
A15: 1 | B15: SGIC | D15: 45886 | E15: Opening | F15: 8461 | H15: 5161125.4 | M15: 5161125.4 | N15: 8461 | O15: 609.99 | P15: 0 | U15: 5568996.4 | AB15: 5568996.4 | AC15: 658.196
A16: Total | B16: SGIC | F16: =SUM(F15) -> 8461 | H16: =SUM(H15) -> 5161125.4 | I16: =SUM(INDIRECT("i4:i"&ROW()-1)) -> 0 | J16: =SUM(J15) -> 0 | K16: =SUM(INDIRECT("k4:k"&ROW()-1)) -> 0 | M16: =H16-L16 -> 5161125.4 | N16: =F16-I16 -> 8461 | O16: =M16/N16 -> 609.99 | P16: =SUM(P15) -> 0 | R16: =SUM(R12:R15) -> 0 | S16: =SUM(S12:S15) -> 0 | T16: =SUM(T12:T15) -> 0 | U16: =SUM(U15) -> 5568996.4 | V16: =SUM(V15) -> 0 | W16: =SUM(W15) -> 0 | X16: =SUM(X15) -> 0 | Y16: =SUM(Y15) -> 0 | Z16: =SUM(Z15) -> 0 | AA16: =SUM(AA15) -> 0 | AB16: =U16-AA16 -> 5568996.4 | AC16: =AB16/F16 -> 658.196 | AD16: =SGIC!AG19 -> 0
A18: 3. Ashoj | R18: Purchase | V18: Sales | Y18: Capital Gain Tax | Z18: Net Receivables | AA18: Principal Amt AP TAX (Sales Unit) | AB18: TC AP TAX | AC18: WACC AP TAX | AD18: P/L AP TAX
A19: S.No | B19: SYMBOL | C19: Bill No | D19: Txn Date | E19: Txn Type | F19: Purchase QTY | G19: PPPU | H19: Total Purchase Amount | I19: Sales Qty | J19: SPPU | K19: Sales Amt | L19: Principal Cost As per NFRS (In case of Sales) | M19: TC AP NFRS | N19: Unit Sum | O19: WACC AP NFRS | P19: P/L AP NFRS | R19: Purchase Commission | S19: DP Charges | T19: Total Commission on Purchase | U19: Total Investment Cost(Including Comission | V19: Sales Commission | W19: DP Charges | X19: Total Commission on Sales
A20: 1 | B20: SGIC | D20: 45917 | E20: Opening | F20: 8461 | H20: 5161125.4 | M20: 5161125.4 | N20: 8461 | O20: 609.99 | P20: 0 | U20: 5568996.4 | AB20: 5568996.4 | AC20: 658.196

Sheet SHL
A1: Jyoti Capital Limited
A2: Kamalpokhari, Kathmandu
A3: JCL Portfolio Statement
A5: 1. Shrawan | R5: Purchase | V5: Sales | Y5: Capital Gain Tax | Z5: Net Receivables | AA5: Principal Amt AP TAX (Sales Unit) | AB5: TC AP TAX | AC5: WACC AP TAX | AD5: P/L AP TAX
A6: S.No | B6: SYMBOL | C6: Bill No | D6: Txn Date | E6: Txn Type | F6: Purchase QTY | G6: PPPU | H6: Total Purchase Amount | I6: Sales Qty | J6: SPPU | K6: Sales Amt | L6: Principal Cost As per NFRS (In case of Sales) | M6: TC AP NFRS | N6: Unit Sum | O6: WACC AP NFRS | P6: P/L AP NFRS | R6: Purchase Commission | S6: DP Charges | T6: Total Commission on Purchase | U6: Total Investment Cost(Including Comission | V6: Sales Commission | W6: DP Charges | X6: Total Commission on Sales
A7: 1 | B7: SHL | D7: 45855 | E7: Opening | F7: 0 | G7: 0 | H7: =Table2428308910131415162324253233343536[[#This Row],[Purchase QTY]]*Table2428308910131415162324253233343536[[#This Row],[PPPU]] -> 0 | M7: =Table2428308910131415162324253233343536[[#This Row],[Total Purchase Amount]] -> 0 | N7: =IF(Table2428308910131415162324253233343536[[#This Row],[Txn Type]]="opening",Table2428308910131415162324253233343536[[#This Row],[Purchase QTY]],"Error") -> 0 | O7: =IFERROR(Table2428308910131415162324253233343536[[#This Row],[TC AP NFRS]]/Table2428308910131415162324253233343536[[#This Row],[Unit Sum]],0) -> 0 | P7: =Table2428308910131415162324253233343536[[#This Row],[Sales Amt]]-Table2428308910131415162324253233343536[[#This Row],[Principal Cost As per NFRS (In case of Sales)]] -> 0 | T7: =R7+S7 -> 0 | U7: =AB7 -> 0 | AB7: =F7*AC7 -> 0
A8: =A7+1 -> 2 | B8: SHL | C8: B/0001006/082-83 | D8: 45876 | E8: purchase | F8: 500 | G8: =Table2428308910131415162324253233343536[[#This Row],[Total Purchase Amount]]/Table2428308910131415162324253233343536[[#This Row],[Purchase QTY]] -> 565 | H8: 282500 | I8: 0 | J8: =IFERROR(Table2428308910131415162324253233343536[[#This Row],[Sales Amt]]/Table2428308910131415162324253233343536[[#This Row],[Sales Qty]],0) -> 0 | K8: 0 | L8: =Table2428308910131415162324253233343536[[#This Row],[Sales Qty]]*O7 -> 0 | M8: =M7+Table2428308910131415162324253233343536[[#This Row],[Total Purchase Amount]]-Table2428308910131415162324253233343536[[#This Row],[Principal Cost As per NFRS (In case of Sales)]] -> 282500 | N8: =N7+Table2428308910131415162324253233343536[[#This Row],[Purchase QTY]]-Table2428308910131415162324253233343536[[#This Row],[Sales Qty]] -> 500 | O8: =IFERROR(Table2428308910131415162324253233343536[[#This Row],[TC AP NFRS]]/Table2428308910131415162324253233343536[[#This Row],[Unit Sum]],0) -> 565 | P8: =Table2428308910131415162324253233343536[[#This Row],[Sales Amt]]-Table2428308910131415162324253233343536[[#This Row],[Principal Cost As per NFRS (In case of Sales)]] -> 0 | R8: =42.38+932.25 -> 974.63 | S8: 25 | T8: =R8+S8 -> 999.63 | U8: =H8+T8 -> 283499.63 | V8: 0 | W8: 0 | X8: =V8+W8 -> 0 | Y8: 0 | Z8: =K8-X8-Y8 -> 0 | AA8: =I8*AC7 -> 0 | AB8: =AB7+U8-AA8 -> 283499.63 | AC8: =IFERROR(AB8/N8,0) -> 566.99926 | AD8: =Z8-AA8+Y8 -> 0
A9: =A8+1 -> 3 | G9: =IF(Table2428308910131415162324253233343536[[#This Row],[SPPU]]>=0,0,Table2428308910131415162324253233343536[[#This Row],[Total Purchase Amount]]/Table2428308910131415162324253233343536[[#This Row],[Purchase QTY]]) -> 0 | J9: =IFERROR(Table2428308910131415162324253233343536[[#This Row],[Sales Amt]]/Table2428308910131415162324253233343536[[#This Row],[Sales Qty]],0) -> 0 | L9: =Table2428308910131415162324253233343536[[#This Row],[Sales Qty]]*O8 -> 0 | M9: =M8+Table2428308910131415162324253233343536[[#This Row],[Total Purchase Amount]]-Table2428308910131415162324253233343536[[#This Row],[Principal Cost As per NFRS (In case of Sales)]] -> 282500 | N9: =N8+Table2428308910131415162324253233343536[[#This Row],[Purchase QTY]]-Table2428308910131415162324253233343536[[#This Row],[Sales Qty]] -> 500 | O9: =IFERROR(Table2428308910131415162324253233343536[[#This Row],[TC AP NFRS]]/Table2428308910131415162324253233343536[[#This Row],[Unit Sum]],0) -> 565 | P9: =Table2428308910131415162324253233343536[[#This Row],[Sales Amt]]-Table2428308910131415162324253233343536[[#This Row],[Principal Cost As per NFRS (In case of Sales)]] -> 0 | R9: 0 | T9: =R9+S9 -> 0 | U9: =H9+T9 -> 0 | V9: 0 | W9: 0 | X9: =V9+W9 -> 0 | Y9: 0 | Z9: =K9-X9-Y9 -> 0 | AA9: =I9*AC8 -> 0 | AB9: =AB8+U9-AA9 -> 283499.63 | AC9: =IFERROR(AB9/N9,0) -> 566.99926 | AD9: =Z9-AA9+Y9 -> 0
A10: =A9+1 -> 4 | G10: =IF(Table2428308910131415162324253233343536[[#This Row],[SPPU]]>=0,0,Table2428308910131415162324253233343536[[#This Row],[Total Purchase Amount]]/Table2428308910131415162324253233343536[[#This Row],[Purchase QTY]]) -> 0 | I10: 0 | J10: =IFERROR(Table2428308910131415162324253233343536[[#This Row],[Sales Amt]]/Table2428308910131415162324253233343536[[#This Row],[Sales Qty]],0) -> 0 | K10: 0 | L10: =Table2428308910131415162324253233343536[[#This Row],[Sales Qty]]*O9 -> 0 | M10: =M9+Table2428308910131415162324253233343536[[#This Row],[Total Purchase Amount]]-Table2428308910131415162324253233343536[[#This Row],[Principal Cost As per NFRS (In case of Sales)]] -> 282500 | N10: =N9+Table2428308910131415162324253233343536[[#This Row],[Purchase QTY]]-Table2428308910131415162324253233343536[[#This Row],[Sales Qty]] -> 500 | O10: =IFERROR(Table2428308910131415162324253233343536[[#This Row],[TC AP NFRS]]/Table2428308910131415162324253233343536[[#This Row],[Unit Sum]],0) -> 565 | P10: =Table2428308910131415162324253233343536[[#This Row],[Sales Amt]]-Table2428308910131415162324253233343536[[#This Row],[Principal Cost As per NFRS (In case of Sales)]] -> 0 | R10: 0 | T10: =R10+S10 -> 0 | U10: =H10+T10 -> 0 | V10: 0 | W10: 0 | X10: =V10+W10 -> 0 | Y10: 0 | Z10: =K10-X10-Y10 -> 0 | AA10: =I10*AC9 -> 0 | AB10: =AB9+U10-AA10 -> 283499.63 | AC10: =IFERROR(AB10/N10,0) -> 566.99926 | AD10: =Z10-AA10+Y10 -> 0
A11: Total | B11: SHL | F11: =SUM(INDIRECT("f4:f"&ROW()-1)) -> 500 | H11: =SUM(INDIRECT("h4:h"&ROW()-1)) -> 282500 | I11: =SUM(INDIRECT("i4:i"&ROW()-1)) -> 0 | J11: =Table2428308910131415162324253233343536[[#This Row],[Sales Amt]]/Table2428308910131415162324253233343536[[#This Row],[Sales Qty]] -> #DIV/0! | K11: =SUM(INDIRECT("k4:k"&ROW()-1)) -> 0 | M11: =Table2428308910131415162324253233343536[[#This Row],[Total Purchase Amount]]-Table2428308910131415162324253233343536[[#This Row],[Principal Cost As per NFRS (In case of Sales)]] -> 282500 | N11: =Table2428308910131415162324253233343536[[#This Row],[Purchase QTY]]-Table2428308910131415162324253233343536[[#This Row],[Sales Qty]] -> 500 | O11: =Table2428308910131415162324253233343536[[#This Row],[TC AP NFRS]]/Table2428308910131415162324253233343536[[#This Row],[Unit Sum]] -> 565 | P11: =SUM(INDIRECT("p4:p"&ROW()-1)) -> 0 | R11: =SUM(R7:R10) -> 974.63 | S11: =SUM(S7:S10) -> 25 | T11: =SUM(T7:T10) -> 999.63 | U11: =SUM(U7:U10) -> 283499.63 | V11: =SUM(V7:V10) -> 0 | W11: =SUM(W7:W10) -> 0 | X11: =SUM(X7:X10) -> 0 | Y11: =SUM(Y7:Y10) -> 0 | ... AA11: =SUM(AA7:AA10) -> 0 | AB11: =U11-AA11 -> 283499.63 | AC11: =AB11/Table2428308910131415162324253233343536[[#This Row],[Unit Sum]] -> 566.99926 | AD11: =SHL!AJ15 -> 0
A13: 2. Bhadra | R13: Purchase | V13: Sales | Y13: Capital Gain Tax | Z13: Net Receivables | AA13: Principal Amt AP TAX (Sales Unit) | AB13: TC AP TAX | AC13: WACC AP TAX | AD13: P/L AP TAX
A14: S.No | B14: SYMBOL | C14: Bill No | D14: Txn Date | E14: Txn Type | F14: Purchase QTY | G14: PPPU | H14: Total Purchase Amount | I14: Sales Qty | J14: SPPU | K14: Sales Amt | L14: Principal Cost As per NFRS (In case of Sales) | M14: TC AP NFRS | N14: Unit Sum | O14: WACC AP NFRS | P14: P/L AP NFRS | R14: Purchase Commission | S14: DP Charges | T14: Total Commission on Purchase | U14: Total Investment Cost(Including Comission | V14: Sales Commission | W14: DP Charges | X14: Total Commission on Sales
A15: 1 | B15: SHL | D15: 45886 | E15: Opening | F15: 500 | H15: 282500 | I15: 0 | K15: 0 | M15: 282500 | N15: 500 | O15: 565 | P15: 0 | R15: 974.63 | S15: 25 | T15: 999.63 | U15: 283499.63 | V15: 0 | W15: 0 | X15: 0 | Y15: 0 | Z15: 0 | AA15: 0 | AB15: 283499.63 | AC15: 566.99926
A16: =A15+1 -> 2 | B16: SHL | C16: B/0001556/082-83 | D16: 45900 | E16: purchase | F16: 500 | G16: =H16/F16 -> 558 | H16: 279000 | M16: =M15+H16-L16 -> 561500 | N16: =N15+F16-I16 -> 1000 | O16: =IFERROR(M16/N16,0) -> 561.5 | R16: =920.7+41.85 -> 962.55 | S16: 25 | T16: =R16+S16 -> 987.55 | U16: =H16+T16 -> 279987.55 | V16: 0 | W16: 0 | X16: =V16+W16 -> 0 | Y16: 0 | Z16: =K16-X16-Y16 -> 0 | AA16: =I16*AC15 -> 0 | AB16: =AB15+U16-AA16 -> 563487.18 | AC16: =IFERROR(AB16/N16,0) -> 563.48718 | AD16: =Z16-AA16+Y16 -> 0
A17: Total | B17: SHL | F17: =SUM(F15:F16) -> 1000 | H17: =SUM(H15:H16) -> 561500 | I17: =SUM(INDIRECT("i4:i"&ROW()-1)) -> 0 | J17: =SUM(J16) -> 0 | K17: =SUM(INDIRECT("k4:k"&ROW()-1)) -> 0 | M17: =H17-L17 -> 561500 | N17: =F17-I17 -> 1000 | O17: =M17/N17 -> 561.5 | P17: =SUM(P16) -> 0 | R17: =SUM(R15:R16) -> 1937.18 | S17: =SUM(S15:S16) -> 50 | T17: =SUM(T15:T16) -> 1987.18 | U17: =SUM(U15:U16) -> 563487.18 | V17: =SUM(V16) -> 0 | W17: =SUM(W16) -> 0 | X17: =SUM(X16) -> 0 | Y17: =SUM(Y16) -> 0 | Z17: =SUM(Z16) -> 0 | AA17: =SUM(AA16) -> 0 | AB17: =U17-AA17 -> 563487.18 | AC17: =AB17/F17 -> 563.48718 | AD17: =SGIC!AG20 -> 0
A19: 3. Ashoj | R19: Purchase | V19: Sales | Y19: Capital Gain Tax | Z19: Net Receivables | AA19: Principal Amt AP TAX (Sales Unit) | AB19: TC AP TAX | AC19: WACC AP TAX | AD19: P/L AP TAX
A20: S.No | B20: SYMBOL | C20: Bill No | D20: Txn Date | E20: Txn Type | F20: Purchase QTY | G20: PPPU | H20: Total Purchase Amount | I20: Sales Qty | J20: SPPU | K20: Sales Amt | L20: Principal Cost As per NFRS (In case of Sales) | M20: TC AP NFRS | N20: Unit Sum | O20: WACC AP NFRS | P20: P/L AP NFRS | R20: Purchase Commission | S20: DP Charges | T20: Total Commission on Purchase | U20: Total Investment Cost(Including Comission | V20: Sales Commission | W20: DP Charges | X20: Total Commission on Sales
A21: 1 | B21: SHL | D21: 45886 | E21: Opening | F21: 1000 | H21: 561500 | I21: 0 | J21: 0 | K21: 0 | M21: 561500 | N21: 1000 | O21: 561.5 | P21: 0 | R21: 1937.18 | S21: 50 | T21: 1987.18 | U21: 563487.18 | V21: 0 | W21: 0 | X21: 0 | Y21: 0 | Z21: 0 | AA21: 0 | AB21: 563487.18 | AC21: 563.48718 | AD21: 0

Sheet MNBBL
A1: Jyoti Capital Limited
A2: Kamalpokhari, Kathmandu
A3: JCL Portfolio Statement
A5: 1. Shrawan | R5: Purchase | V5: Sales | Y5: Capital Gain Tax | Z5: Net Receivables | AA5: Principal Amt AP TAX (Sales Unit) | AB5: TC AP TAX | AC5: WACC AP TAX | AD5: P/L AP TAX
A6: S.No | B6: SYMBOL | C6: Bill No | D6: Txn Date | E6: Txn Type | F6: Purchase QTY | G6: PPPU | H6: Total Purchase Amount | I6: Sales Qty | J6: SPPU | K6: Sales Amt | L6: Principal Cost As per NFRS (In case of Sales) | M6: TC AP NFRS | N6: Unit Sum | O6: WACC AP NFRS | P6: P/L AP NFRS | R6: Purchase Commission | S6: DP Charges | T6: Total Commission on Purchase | U6: Total Investment Cost(Including Comission | V6: Sales Commission | W6: DP Charges | X6: Total Commission on Sales
A7: 1 | B7: MNBBL | D7: 45855 | E7: Opening | F7: 0 | G7: 0 | H7: =Table24283089101314151623242532333435[[#This Row],[Purchase QTY]]*Table24283089101314151623242532333435[[#This Row],[PPPU]] -> 0 | M7: =Table24283089101314151623242532333435[[#This Row],[Total Purchase Amount]] -> 0 | N7: =IF(Table24283089101314151623242532333435[[#This Row],[Txn Type]]="opening",Table24283089101314151623242532333435[[#This Row],[Purchase QTY]],"Error") -> 0 | O7: =IFERROR(Table24283089101314151623242532333435[[#This Row],[TC AP NFRS]]/Table24283089101314151623242532333435[[#This Row],[Unit Sum]],0) -> 0 | P7: =Table24283089101314151623242532333435[[#This Row],[Sales Amt]]-Table24283089101314151623242532333435[[#This Row],[Principal Cost As per NFRS (In case of Sales)]] -> 0 | T7: =R7+S7 -> 0 | U7: =AB7 -> 0 | AB7: =F7*AC7 -> 0
A8: =A7+1 -> 2 | B8: MNBBL | C8: B/0001005/082-83 | D8: 45876 | E8: purchase | F8: 1000 | G8: =Table24283089101314151623242532333435[[#This Row],[Total Purchase Amount]]/Table24283089101314151623242532333435[[#This Row],[Purchase QTY]] -> 445 | H8: 445000 | I8: 0 | J8: =IFERROR(Table24283089101314151623242532333435[[#This Row],[Sales Amt]]/Table24283089101314151623242532333435[[#This Row],[Sales Qty]],0) -> 0 | K8: 0 | L8: =Table24283089101314151623242532333435[[#This Row],[Sales Qty]]*O7 -> 0 | M8: =M7+Table24283089101314151623242532333435[[#This Row],[Total Purchase Amount]]-Table24283089101314151623242532333435[[#This Row],[Principal Cost As per NFRS (In case of Sales)]] -> 445000 | N8: =N7+Table24283089101314151623242532333435[[#This Row],[Purchase QTY]]-Table24283089101314151623242532333435[[#This Row],[Sales Qty]] -> 1000 | O8: =IFERROR(Table24283089101314151623242532333435[[#This Row],[TC AP NFRS]]/Table24283089101314151623242532333435[[#This Row],[Unit Sum]],0) -> 445 | P8: =Table24283089101314151623242532333435[[#This Row],[Sales Amt]]-Table24283089101314151623242532333435[[#This Row],[Principal Cost As per NFRS (In case of Sales)]] -> 0 | R8: =66.75+1468.5 -> 1535.25 | S8: 25 | T8: =R8+S8 -> 1560.25 | U8: =H8+T8 -> 446560.25 | V8: 0 | W8: 0 | X8: =V8+W8 -> 0 | Y8: 0 | Z8: =K8-X8-Y8 -> 0 | AA8: =I8*AC7 -> 0 | AB8: =AB7+U8-AA8 -> 446560.25 | AC8: =IFERROR(AB8/N8,0) -> 446.56025 | AD8: =Z8-AA8+Y8 -> 0
A9: =A8+1 -> 3 | G9: =IF(Table24283089101314151623242532333435[[#This Row],[SPPU]]>=0,0,Table24283089101314151623242532333435[[#This Row],[Total Purchase Amount]]/Table24283089101314151623242532333435[[#This Row],[Purchase QTY]]) -> 0 | J9: =IFERROR(Table24283089101314151623242532333435[[#This Row],[Sales Amt]]/Table24283089101314151623242532333435[[#This Row],[Sales Qty]],0) -> 0 | L9: =Table24283089101314151623242532333435[[#This Row],[Sales Qty]]*O8 -> 0 | M9: =M8+Table24283089101314151623242532333435[[#This Row],[Total Purchase Amount]]-Table24283089101314151623242532333435[[#This Row],[Principal Cost As per NFRS (In case of Sales)]] -> 445000 | N9: =N8+Table24283089101314151623242532333435[[#This Row],[Purchase QTY]]-Table24283089101314151623242532333435[[#This Row],[Sales Qty]] -> 1000 | O9: =IFERROR(Table24283089101314151623242532333435[[#This Row],[TC AP NFRS]]/Table24283089101314151623242532333435[[#This Row],[Unit Sum]],0) -> 445 | P9: =Table24283089101314151623242532333435[[#This Row],[Sales Amt]]-Table24283089101314151623242532333435[[#This Row],[Principal Cost As per NFRS (In case of Sales)]] -> 0 | R9: 0 | T9: =R9+S9 -> 0 | U9: =H9+T9 -> 0 | V9: 0 | W9: 0 | X9: =V9+W9 -> 0 | Y9: 0 | Z9: =K9-X9-Y9 -> 0 | AA9: =I9*AC8 -> 0 | AB9: =AB8+U9-AA9 -> 446560.25 | AC9: =IFERROR(AB9/N9,0) -> 446.56025 | AD9: =Z9-AA9+Y9 -> 0
A10: =A9+1 -> 4 | G10: =IF(Table24283089101314151623242532333435[[#This Row],[SPPU]]>=0,0,Table24283089101314151623242532333435[[#This Row],[Total Purchase Amount]]/Table24283089101314151623242532333435[[#This Row],[Purchase QTY]]) -> 0 | I10: 0 | J10: =IFERROR(Table24283089101314151623242532333435[[#This Row],[Sales Amt]]/Table24283089101314151623242532333435[[#This Row],[Sales Qty]],0) -> 0 | K10: 0 | L10: =Table24283089101314151623242532333435[[#This Row],[Sales Qty]]*O9 -> 0 | M10: =M9+Table24283089101314151623242532333435[[#This Row],[Total Purchase Amount]]-Table24283089101314151623242532333435[[#This Row],[Principal Cost As per NFRS (In case of Sales)]] -> 445000 | N10: =N9+Table24283089101314151623242532333435[[#This Row],[Purchase QTY]]-Table24283089101314151623242532333435[[#This Row],[Sales Qty]] -> 1000 | O10: =IFERROR(Table24283089101314151623242532333435[[#This Row],[TC AP NFRS]]/Table24283089101314151623242532333435[[#This Row],[Unit Sum]],0) -> 445 | P10: =Table24283089101314151623242532333435[[#This Row],[Sales Amt]]-Table24283089101314151623242532333435[[#This Row],[Principal Cost As per NFRS (In case of Sales)]] -> 0 | R10: 0 | T10: =R10+S10 -> 0 | U10: =H10+T10 -> 0 | V10: 0 | W10: 0 | X10: =V10+W10 -> 0 | Y10: 0 | Z10: =K10-X10-Y10 -> 0 | AA10: =I10*AC9 -> 0 | AB10: =AB9+U10-AA10 -> 446560.25 | AC10: =IFERROR(AB10/N10,0) -> 446.56025 | AD10: =Z10-AA10+Y10 -> 0
A11: =A10+1 -> 5 | F11: 0 | G11: =Table24283089101314151623242532333435[[#This Row],[Total Purchase Amount]]/Table24283089101314151623242532333435[[#This Row],[Purchase QTY]] -> #DIV/0! | H11: 0 | I11: 0 | J11: =IFERROR(Table24283089101314151623242532333435[[#This Row],[Sales Amt]]/Table24283089101314151623242532333435[[#This Row],[Sales Qty]],0) -> 0 | K11: =Table24283089101314151623242532333435[[#This Row],[Sales Qty]]*Table24283089101314151623242532333435[[#This Row],[SPPU]] -> 0 | L11: =Table24283089101314151623242532333435[[#This Row],[Sales Qty]]*O10 -> 0 | M11: =M10+Table24283089101314151623242532333435[[#This Row],[Total Purchase Amount]]-Table24283089101314151623242532333435[[#This Row],[Principal Cost As per NFRS (In case of Sales)]] -> 445000 | N11: =N10+Table24283089101314151623242532333435[[#This Row],[Purchase QTY]]-Table24283089101314151623242532333435[[#This Row],[Sales Qty]] -> 1000 | O11: =IFERROR(Table24283089101314151623242532333435[[#This Row],[TC AP NFRS]]/Table24283089101314151623242532333435[[#This Row],[Unit Sum]],0) -> 445 | P11: =Table24283089101314151623242532333435[[#This Row],[Sales Amt]]-Table24283089101314151623242532333435[[#This Row],[Principal Cost As per NFRS (In case of Sales)]] -> 0 | R11: =SUM(R7:R10) -> 1535.25 | S11: =SUM(S7:S10) -> 25 | T11: =SUM(T7:T10) -> 1560.25 | U11: =SUM(U7:U10) -> 446560.25 | V11: =SUM(V7:V10) -> 0 | W11: =SUM(W7:W10) -> 0 | X11: =SUM(X7:X10) -> 0 | Y11: =SUM(Y7:Y10) -> 0 | ... AA11: =SUM(AA7:AA10) -> 0 | AD11: =SUM(AD7:AD10) -> 0
A12: Total | F12: =SUM(INDIRECT("f4:f"&ROW()-1)) -> 1000 | H12: =SUM(INDIRECT("h4:h"&ROW()-1)) -> 445000 | I12: =SUM(INDIRECT("i4:i"&ROW()-1)) -> 0 | J12: =Table24283089101314151623242532333435[[#This Row],[Sales Amt]]/Table24283089101314151623242532333435[[#This Row],[Sales Qty]] -> #DIV/0! | K12: =SUM(INDIRECT("k4:k"&ROW()-1)) -> 0 | L12: =SUM(INDIRECT("l4:l"&ROW()-1)) -> 0 | M12: =Table24283089101314151623242532333435[[#This Row],[Total Purchase Amount]]-Table24283089101314151623242532333435[[#This Row],[Principal Cost As per NFRS (In case of Sales)]] -> 445000 | N12: =Table24283089101314151623242532333435[[#This Row],[Purchase QTY]]-Table24283089101314151623242532333435[[#This Row],[Sales Qty]] -> 1000 | O12: =Table24283089101314151623242532333435[[#This Row],[TC AP NFRS]]/Table24283089101314151623242532333435[[#This Row],[Unit Sum]] -> 445 | P12: =SUM(INDIRECT("p4:p"&ROW()-1)) -> 0 | R12: =SUM(R7:R11) -> 3070.5 | S12: =SUM(S7:S11) -> 50 | T12: =SUM(T7:T11) -> 3120.5 | U12: =SUM(U7:U11) -> 893120.5 | V12: =SUM(V7:V11) -> 0 | W12: =SUM(W7:W11) -> 0 | X12: =SUM(X7:X11) -> 0 | Y12: =SUM(Y7:Y11) -> 0 | ... AA12: =SUM(AA7:AA11) -> 0 | AB12: =U12-AA12 -> 893120.5 | AC12: =AB12/Table24283089101314151623242532333435[[#This Row],[Unit Sum]] -> 893.1205 | AD12: =SUM(AD7:AD11) -> 0
A14: 2. Bhadra | R14: Purchase | V14: Sales | Y14: Capital Gain Tax | Z14: Net Receivables | AA14: Principal Amt AP TAX (Sales Unit) | AB14: TC AP TAX | AC14: WACC AP TAX | AD14: P/L AP TAX
A15: S.No | B15: SYMBOL | C15: Bill No | D15: Txn Date | E15: Txn Type | F15: Purchase QTY | G15: PPPU | H15: Total Purchase Amount | I15: Sales Qty | J15: SPPU | K15: Sales Amt | L15: Principal Cost As per NFRS (In case of Sales) | M15: TC AP NFRS | N15: Unit Sum | O15: WACC AP NFRS | P15: P/L AP NFRS | R15: Purchase Commission | S15: DP Charges | T15: Total Commission on Purchase | U15: Total Investment Cost(Including Comission | V15: Sales Commission | W15: DP Charges | X15: Total Commission on Sales
A16: 1 | B16: MNBBL | D16: 45886 | E16: Opening | F16: 1000 | H16: 445000 | I16: 0 | K16: 0 | L16: 0 | M16: 445000 | N16: 1000 | O16: 445 | P16: 0 | R16: 3070.5 | S16: 50 | T16: 3120.5 | U16: 893120.5 | V16: 0 | W16: 0 | X16: 0 | Y16: 0 | Z16: 0 | AA16: 0 | AB16: 893120.5 | AC16: 893.1205 | AD16: 0
A17: 2 | B17: MNBBL | D17: 45897 | E17: purchase | F17: 1000 | G17: =H17/F17 -> 463.4975 | H17: 463497.5 | I17: 0 | J17: =IFERROR(Table24283089101314151623242532333435[[#This Row],[Sales Amt]]/Table24283089101314151623242532333435[[#This Row],[Sales Qty]],0) -> 0 | K17: 0 | M17: =M16+H17-L17 -> 908497.5 | N17: =N16+F17-I17 -> 2000 | O17: =M17/N17 -> 454.24875 | R17: =1533.72+69.52 -> 1603.24 | S17: 25 | T17: =R17+S17 -> 1628.24 | U17: =H17+T17 -> 465125.74 | V17: 0 | W17: 0 | X17: =V17+W17 -> 0 | Y17: 0 | Z17: =K17-X17-Y17 -> 0 | AA17: =I17*AC16 -> 0 | AB17: =AB16+U17-AA17 -> 1358246.2 | AC17: =IFERROR(AB17/N17,0) -> 679.12312 | AD17: =Z17-AA17+Y17 -> 0
A18: Total | B18: MNBBL | F18: =SUM(F16:F17) -> 2000 | H18: =SUM(H16:H17) -> 908497.5 | I18: =SUM(INDIRECT("i4:i"&ROW()-1)) -> 0 | J18: =SUM(J17) -> 0 | K18: =SUM(INDIRECT("k4:k"&ROW()-1)) -> 0 | M18: =H18-L18 -> 908497.5 | N18: =F18-I18 -> 2000 | O18: =M18/N18 -> 454.24875 | P18: =SUM(P17) -> 0 | R18: =SUM(R16:R17) -> 4673.74 | S18: =SUM(S16:S17) -> 75 | T18: =SUM(T16:T17) -> 4748.74 | U18: =SUM(U16:U17) -> 1358246.2 | V18: =SUM(V17) -> 0 | W18: =SUM(W17) -> 0 | X18: =SUM(X17) -> 0 | Y18: =SUM(Y17) -> 0 | Z18: =SUM(Z17) -> 0 | AA18: =SUM(AA17) -> 0 | AB18: =U18-AA18 -> 1358246.2 | AC18: =AB18/F18 -> 679.12312 | AD18: =SGIC!AG21 -> 0
A20: 3. Ashoj | R20: Purchase | V20: Sales | Y20: Capital Gain Tax | Z20: Net Receivables | AA20: Principal Amt AP TAX (Sales Unit) | AB20: TC AP TAX | AC20: WACC AP TAX | AD20: P/L AP TAX
A21: S.No | B21: SYMBOL | C21: Bill No | D21: Txn Date | E21: Txn Type | F21: Purchase QTY | G21: PPPU | H21: Total Purchase Amount | I21: Sales Qty | J21: SPPU | K21: Sales Amt | L21: Principal Cost As per NFRS (In case of Sales) | M21: TC AP NFRS | N21: Unit Sum | O21: WACC AP NFRS | P21: P/L AP NFRS | R21: Purchase Commission | S21: DP Charges | T21: Total Commission on Purchase | U21: Total Investment Cost(Including Comission | V21: Sales Commission | W21: DP Charges | X21: Total Commission on Sales
A22: 1 | B22: MNBBL | D22: 45917 | E22: Opening | F22: 2000 | H22: 908497.5 | I22: 0 | J22: 0 | K22: 0 | M22: 908497.5 | N22: 2000 | O22: 454.24875 | P22: 0 | R22: 4673.74 | S22: 75 | T22: 4748.74 | U22: 1358246.2 | V22: 0 | W22: 0 | X22: 0 | Y22: 0 | Z22: 0 | AA22: 0 | AB22: 1358246.2 | AC22: 679.12312 | AD22: 0

Sheet KSBBL
A1: Jyoti Capital Limited
A2: Kamalpokhari, Kathmandu
A3: JCL Portfolio Statement
A5: 1. Shrawan | R5: Purchase | V5: Sales | Y5: Capital Gain Tax | Z5: Net Receivables | AA5: Principal Amt AP TAX (Sales Unit) | AB5: TC AP TAX | AC5: WACC AP TAX | AD5: P/L AP TAX
A6: S.No | B6: SYMBOL | C6: Bill No | D6: Txn Date | E6: Txn Type | F6: Purchase QTY | G6: PPPU | H6: Total Purchase Amount | I6: Sales Qty | J6: SPPU | K6: Sales Amt | L6: Principal Cost As per NFRS (In case of Sales) | M6: TC AP NFRS | N6: Unit Sum | O6: WACC AP NFRS | P6: P/L AP NFRS | R6: Purchase Commission | S6: DP Charges | T6: Total Commission on Purchase | U6: Total Investment Cost(Including Comission | V6: Sales Commission | W6: DP Charges | X6: Total Commission on Sales
A7: 1 | B7: KSBBL | D7: 45855 | E7: Opening | F7: 0 | G7: 0 | H7: =Table242830891013141516232425323334[[#This Row],[Purchase QTY]]*Table242830891013141516232425323334[[#This Row],[PPPU]] -> 0 | M7: =Table242830891013141516232425323334[[#This Row],[Total Purchase Amount]] -> 0 | N7: =IF(Table242830891013141516232425323334[[#This Row],[Txn Type]]="opening",Table242830891013141516232425323334[[#This Row],[Purchase QTY]],"Error") -> 0 | O7: =IFERROR(Table242830891013141516232425323334[[#This Row],[TC AP NFRS]]/Table242830891013141516232425323334[[#This Row],[Unit Sum]],0) -> 0 | P7: =Table242830891013141516232425323334[[#This Row],[Sales Amt]]-Table242830891013141516232425323334[[#This Row],[Principal Cost As per NFRS (In case of Sales)]] -> 0 | T7: =R7+S7 -> 0 | U7: =AB7 -> 0 | AB7: =F7*AC7 -> 0
A8: =A7+1 -> 2 | B8: KSBBL | C8: B/0001004/082-83 | D8: 45876 | E8: purchase | F8: 1000 | G8: =Table242830891013141516232425323334[[#This Row],[Total Purchase Amount]]/Table242830891013141516232425323334[[#This Row],[Purchase QTY]] -> 532 | H8: 532000 | I8: 0 | J8: =IFERROR(Table242830891013141516232425323334[[#This Row],[Sales Amt]]/Table242830891013141516232425323334[[#This Row],[Sales Qty]],0) -> 0 | K8: 0 | L8: =Table242830891013141516232425323334[[#This Row],[Sales Qty]]*O7 -> 0 | M8: =M7+Table242830891013141516232425323334[[#This Row],[Total Purchase Amount]]-Table242830891013141516232425323334[[#This Row],[Principal Cost As per NFRS (In case of Sales)]] -> 532000 | N8: =N7+Table242830891013141516232425323334[[#This Row],[Purchase QTY]]-Table242830891013141516232425323334[[#This Row],[Sales Qty]] -> 1000 | O8: =IFERROR(Table242830891013141516232425323334[[#This Row],[TC AP NFRS]]/Table242830891013141516232425323334[[#This Row],[Unit Sum]],0) -> 532 | P8: =Table242830891013141516232425323334[[#This Row],[Sales Amt]]-Table242830891013141516232425323334[[#This Row],[Principal Cost As per NFRS (In case of Sales)]] -> 0 | R8: =79.8+1755.6 -> 1835.4 | S8: 25 | T8: =R8+S8 -> 1860.4 | U8: =H8+T8 -> 533860.4 | V8: 0 | W8: 0 | X8: =V8+W8 -> 0 | Y8: 0 | Z8: =K8-X8-Y8 -> 0 | AA8: =I8*AC7 -> 0 | AB8: =AB7+U8-AA8 -> 533860.4 | AC8: =IFERROR(AB8/N8,0) -> 533.8604 | AD8: =Z8-AA8+Y8 -> 0
A9: =A8+1 -> 3 | G9: =IF(Table242830891013141516232425323334[[#This Row],[SPPU]]>=0,0,Table242830891013141516232425323334[[#This Row],[Total Purchase Amount]]/Table242830891013141516232425323334[[#This Row],[Purchase QTY]]) -> 0 | J9: =IFERROR(Table242830891013141516232425323334[[#This Row],[Sales Amt]]/Table242830891013141516232425323334[[#This Row],[Sales Qty]],0) -> 0 | L9: =Table242830891013141516232425323334[[#This Row],[Sales Qty]]*O8 -> 0 | M9: =M8+Table242830891013141516232425323334[[#This Row],[Total Purchase Amount]]-Table242830891013141516232425323334[[#This Row],[Principal Cost As per NFRS (In case of Sales)]] -> 532000 | N9: =N8+Table242830891013141516232425323334[[#This Row],[Purchase QTY]]-Table242830891013141516232425323334[[#This Row],[Sales Qty]] -> 1000 | O9: =IFERROR(Table242830891013141516232425323334[[#This Row],[TC AP NFRS]]/Table242830891013141516232425323334[[#This Row],[Unit Sum]],0) -> 532 | P9: =Table242830891013141516232425323334[[#This Row],[Sales Amt]]-Table242830891013141516232425323334[[#This Row],[Principal Cost As per NFRS (In case of Sales)]] -> 0 | R9: 0 | T9: =R9+S9 -> 0 | U9: =H9+T9 -> 0 | V9: 0 | W9: 0 | X9: =V9+W9 -> 0 | Y9: 0 | Z9: =K9-X9-Y9 -> 0 | AA9: =I9*AC8 -> 0 | AB9: =AB8+U9-AA9 -> 533860.4 | AC9: =IFERROR(AB9/N9,0) -> 533.8604 | AD9: =Z9-AA9+Y9 -> 0
A10: =A9+1 -> 4 | G10: =IF(Table242830891013141516232425323334[[#This Row],[SPPU]]>=0,0,Table242830891013141516232425323334[[#This Row],[Total Purchase Amount]]/Table242830891013141516232425323334[[#This Row],[Purchase QTY]]) -> 0 | I10: 0 | J10: =IFERROR(Table242830891013141516232425323334[[#This Row],[Sales Amt]]/Table242830891013141516232425323334[[#This Row],[Sales Qty]],0) -> 0 | K10: 0 | L10: =Table242830891013141516232425323334[[#This Row],[Sales Qty]]*O9 -> 0 | M10: =M9+Table242830891013141516232425323334[[#This Row],[Total Purchase Amount]]-Table242830891013141516232425323334[[#This Row],[Principal Cost As per NFRS (In case of Sales)]] -> 532000 | N10: =N9+Table242830891013141516232425323334[[#This Row],[Purchase QTY]]-Table242830891013141516232425323334[[#This Row],[Sales Qty]] -> 1000 | O10: =IFERROR(Table242830891013141516232425323334[[#This Row],[TC AP NFRS]]/Table242830891013141516232425323334[[#This Row],[Unit Sum]],0) -> 532 | P10: =Table242830891013141516232425323334[[#This Row],[Sales Amt]]-Table242830891013141516232425323334[[#This Row],[Principal Cost As per NFRS (In case of Sales)]] -> 0 | R10: 0 | T10: =R10+S10 -> 0 | U10: =H10+T10 -> 0 | V10: 0 | W10: 0 | X10: =V10+W10 -> 0 | Y10: 0 | Z10: =K10-X10-Y10 -> 0 | AA10: =I10*AC9 -> 0 | AB10: =AB9+U10-AA10 -> 533860.4 | AC10: =IFERROR(AB10/N10,0) -> 533.8604 | AD10: =Z10-AA10+Y10 -> 0
A11: =A10+1 -> 5 | F11: 0 | G11: =Table242830891013141516232425323334[[#This Row],[Total Purchase Amount]]/Table242830891013141516232425323334[[#This Row],[Purchase QTY]] -> #DIV/0! | H11: 0 | I11: 0 | J11: =IFERROR(Table242830891013141516232425323334[[#This Row],[Sales Amt]]/Table242830891013141516232425323334[[#This Row],[Sales Qty]],0) -> 0 | K11: =Table242830891013141516232425323334[[#This Row],[Sales Qty]]*Table242830891013141516232425323334[[#This Row],[SPPU]] -> 0 | L11: =Table242830891013141516232425323334[[#This Row],[Sales Qty]]*O10 -> 0 | M11: =M10+Table242830891013141516232425323334[[#This Row],[Total Purchase Amount]]-Table242830891013141516232425323334[[#This Row],[Principal Cost As per NFRS (In case of Sales)]] -> 532000 | N11: =N10+Table242830891013141516232425323334[[#This Row],[Purchase QTY]]-Table242830891013141516232425323334[[#This Row],[Sales Qty]] -> 1000 | O11: =IFERROR(Table242830891013141516232425323334[[#This Row],[TC AP NFRS]]/Table242830891013141516232425323334[[#This Row],[Unit Sum]],0) -> 532 | P11: =Table242830891013141516232425323334[[#This Row],[Sales Amt]]-Table242830891013141516232425323334[[#This Row],[Principal Cost As per NFRS (In case of Sales)]] -> 0 | R11: 0 | T11: =R11+S11 -> 0 | U11: =H11+T11 -> 0 | V11: 0 | W11: 0 | X11: =V11+W11 -> 0 | Y11: 0 | Z11: =K11-X11-Y11 -> 0 | AA11: =I11*AC10 -> 0 | AB11: =AB10+U11-AA11 -> 533860.4 | AC11: =IFERROR(AB11/N11,0) -> 533.8604 | AD11: =Z11-AA11+Y11 -> 0
A12: =A11+1 -> 6 | F12: 0 | G12: =Table242830891013141516232425323334[[#This Row],[Total Purchase Amount]]/Table242830891013141516232425323334[[#This Row],[Purchase QTY]] -> #DIV/0! | H12: 0 | I12: 0 | J12: =IFERROR(Table242830891013141516232425323334[[#This Row],[Sales Amt]]/Table242830891013141516232425323334[[#This Row],[Sales Qty]],0) -> 0 | K12: =Table242830891013141516232425323334[[#This Row],[Sales Qty]]*Table242830891013141516232425323334[[#This Row],[SPPU]] -> 0 | L12: =Table242830891013141516232425323334[[#This Row],[Sales Qty]]*O11 -> 0 | M12: =M11+Table242830891013141516232425323334[[#This Row],[Total Purchase Amount]]-Table242830891013141516232425323334[[#This Row],[Principal Cost As per NFRS (In case of Sales)]] -> 532000 | N12: =N11+Table242830891013141516232425323334[[#This Row],[Purchase QTY]]-Table242830891013141516232425323334[[#This Row],[Sales Qty]] -> 1000 | O12: =IFERROR(Table242830891013141516232425323334[[#This Row],[TC AP NFRS]]/Table242830891013141516232425323334[[#This Row],[Unit Sum]],0) -> 532 | P12: =Table242830891013141516232425323334[[#This Row],[Sales Amt]]-Table242830891013141516232425323334[[#This Row],[Principal Cost As per NFRS (In case of Sales)]] -> 0 | R12: 0 | T12: =R12+S12 -> 0 | U12: =H12+T12 -> 0 | V12: 0 | W12: 0 | X12: =V12+W12 -> 0 | Y12: 0 | Z12: =K12-X12-Y12 -> 0 | AA12: =I12*AC11 -> 0 | AB12: =AB11+U12-AA12 -> 533860.4 | AC12: =IFERROR(AB12/N12,0) -> 533.8604 | AD12: =Z12-AA12+Y12 -> 0
A13: =A12+1 -> 7 | G13: =IF(Table242830891013141516232425323334[[#This Row],[SPPU]]>=0,0,Table242830891013141516232425323334[[#This Row],[Total Purchase Amount]]/Table242830891013141516232425323334[[#This Row],[Purchase QTY]]) -> 0 | I13: 0 | J13: =IFERROR(Table242830891013141516232425323334[[#This Row],[Sales Amt]]/Table242830891013141516232425323334[[#This Row],[Sales Qty]],0) -> 0 | K13: 0 | L13: =Table242830891013141516232425323334[[#This Row],[Sales Qty]]*O11 -> 0 | M13: =M12+Table242830891013141516232425323334[[#This Row],[Total Purchase Amount]]-Table242830891013141516232425323334[[#This Row],[Principal Cost As per NFRS (In case of Sales)]] -> 532000 | N13: =N12+Table242830891013141516232425323334[[#This Row],[Purchase QTY]]-Table242830891013141516232425323334[[#This Row],[Sales Qty]] -> 1000 | O13: =IFERROR(Table242830891013141516232425323334[[#This Row],[TC AP NFRS]]/Table242830891013141516232425323334[[#This Row],[Unit Sum]],0) -> 532 | P13: =Table242830891013141516232425323334[[#This Row],[Sales Amt]]-Table242830891013141516232425323334[[#This Row],[Principal Cost As per NFRS (In case of Sales)]] -> 0 | R13: 0 | T13: =R13+S13 -> 0 | U13: =H13+T13 -> 0 | V13: 0 | W13: 0 | X13: =V13+W13 -> 0 | Y13: 0 | Z13: =K13-X13-Y13 -> 0 | AA13: =I13*AC12 -> 0 | AB13: =AB12+U13-AA13 -> 533860.4 | AC13: =IFERROR(AB13/N13,0) -> 533.8604 | AD13: =Z13-AA13+Y13 -> 0
A14: =A13+1 -> 8 | G14: =IF(Table242830891013141516232425323334[[#This Row],[SPPU]]>=0,0,Table242830891013141516232425323334[[#This Row],[Total Purchase Amount]]/Table242830891013141516232425323334[[#This Row],[Purchase QTY]]) -> 0 | I14: 0 | J14: =IFERROR(Table242830891013141516232425323334[[#This Row],[Sales Amt]]/Table242830891013141516232425323334[[#This Row],[Sales Qty]],0) -> 0 | K14: 0 | L14: =Table242830891013141516232425323334[[#This Row],[Sales Qty]]*O13 -> 0 | M14: =M13+Table242830891013141516232425323334[[#This Row],[Total Purchase Amount]]-Table242830891013141516232425323334[[#This Row],[Principal Cost As per NFRS (In case of Sales)]] -> 532000 | N14: =N13+Table242830891013141516232425323334[[#This Row],[Purchase QTY]]-Table242830891013141516232425323334[[#This Row],[Sales Qty]] -> 1000 | O14: =IFERROR(Table242830891013141516232425323334[[#This Row],[TC AP NFRS]]/Table242830891013141516232425323334[[#This Row],[Unit Sum]],0) -> 532 | P14: =Table242830891013141516232425323334[[#This Row],[Sales Amt]]-Table242830891013141516232425323334[[#This Row],[Principal Cost As per NFRS (In case of Sales)]] -> 0 | R14: 0 | T14: =R14+S14 -> 0 | U14: =H14+T14 -> 0 | V14: 0 | W14: 0 | X14: =V14+W14 -> 0 | Y14: 0 | Z14: =K14-X14-Y14 -> 0 | AA14: =I14*AC13 -> 0 | AB14: =AB13+U14-AA14 -> 533860.4 | AC14: =IFERROR(AB14/N14,0) -> 533.8604 | AD14: =Z14-AA14+Y14 -> 0
A15: =A14+1 -> 9 | G15: =IF(Table242830891013141516232425323334[[#This Row],[SPPU]]>=0,0,Table242830891013141516232425323334[[#This Row],[Total Purchase Amount]]/Table242830891013141516232425323334[[#This Row],[Purchase QTY]]) -> 0 | I15: 0 | J15: =IFERROR(Table242830891013141516232425323334[[#This Row],[Sales Amt]]/Table242830891013141516232425323334[[#This Row],[Sales Qty]],0) -> 0 | K15: 0 | L15: =Table242830891013141516232425323334[[#This Row],[Sales Qty]]*O14 -> 0 | M15: =M14+Table242830891013141516232425323334[[#This Row],[Total Purchase Amount]]-Table242830891013141516232425323334[[#This Row],[Principal Cost As per NFRS (In case of Sales)]] -> 532000 | N15: =N14+Table242830891013141516232425323334[[#This Row],[Purchase QTY]]-Table242830891013141516232425323334[[#This Row],[Sales Qty]] -> 1000 | O15: =IFERROR(Table242830891013141516232425323334[[#This Row],[TC AP NFRS]]/Table242830891013141516232425323334[[#This Row],[Unit Sum]],0) -> 532 | P15: =Table242830891013141516232425323334[[#This Row],[Sales Amt]]-Table242830891013141516232425323334[[#This Row],[Principal Cost As per NFRS (In case of Sales)]] -> 0 | R15: 0 | T15: =R15+S15 -> 0 | U15: =H15+T15 -> 0 | V15: 0 | W15: 0 | X15: =V15+W15 -> 0 | Y15: 0 | Z15: =K15-X15-Y15 -> 0 | AA15: =I15*AC14 -> 0 | AB15: =AB14+U15-AA15 -> 533860.4 | AC15: =IFERROR(AB15/N15,0) -> 533.8604 | AD15: =Z15-AA15+Y15 -> 0
A16: Total | F16: =SUM(INDIRECT("f4:f"&ROW()-1)) -> 1000 | H16: =SUM(INDIRECT("h4:h"&ROW()-1)) -> 532000 | I16: =SUM(INDIRECT("i4:i"&ROW()-1)) -> 0 | J16: =Table242830891013141516232425323334[[#This Row],[Sales Amt]]/Table242830891013141516232425323334[[#This Row],[Sales Qty]] -> #DIV/0! | K16: =SUM(K7:K9) -> 0 | L16: =SUM(INDIRECT("i4:i"&ROW()-1)) -> 0 | M16: =Table242830891013141516232425323334[[#This Row],[Total Purchase Amount]]-Table242830891013141516232425323334[[#This Row],[Principal Cost As per NFRS (In case of Sales)]] -> 532000 | N16: =Table242830891013141516232425323334[[#This Row],[Purchase QTY]]-Table242830891013141516232425323334[[#This Row],[Sales Qty]] -> 1000 | O16: =Table242830891013141516232425323334[[#This Row],[TC AP NFRS]]/Table242830891013141516232425323334[[#This Row],[Unit Sum]] -> 532 | P16: =SUM(INDIRECT("p4:p"&ROW()-1)) -> 0 | R16: =SUM(R7:R15) -> 1835.4 | S16: =SUM(S7:S15) -> 25 | T16: =SUM(T7:T15) -> 1860.4 | U16: =SUM(U7:U15) -> 533860.4 | V16: =SUM(V7:V15) -> 0 | W16: =SUM(W7:W15) -> 0 | X16: =SUM(X7:X15) -> 0 | Y16: =SUM(Y7:Y15) -> 0 | ... AA16: =SUM(AA7:AA15) -> 0 | AB16: =U16-AA16 -> 533860.4 | AC16: =IFERROR(AB16/N16,0) -> 533.8604 | AD16: =SUM(AD7:AD15) -> 0
A18: 2. Bhadra | R18: Purchase | V18: Sales | Y18: Capital Gain Tax | Z18: Net Receivables | AA18: Principal Amt AP TAX (Sales Unit) | AB18: TC AP TAX | AC18: WACC AP TAX | AD18: P/L AP TAX
A19: S.No | B19: SYMBOL | C19: Bill No | D19: Txn Date | E19: Txn Type | F19: Purchase QTY | G19: PPPU | H19: Total Purchase Amount | I19: Sales Qty | J19: SPPU | K19: Sales Amt | L19: Principal Cost As per NFRS (In case of Sales) | M19: TC AP NFRS | N19: Unit Sum | O19: WACC AP NFRS | P19: P/L AP NFRS | R19: Purchase Commission | S19: DP Charges | T19: Total Commission on Purchase | U19: Total Investment Cost(Including Comission | V19: Sales Commission | W19: DP Charges | X19: Total Commission on Sales
A20: 1 | B20: KSBBL | D20: 45886 | E20: Opening | F20: 1000 | H20: 532000 | I20: 0 | K20: 0 | L20: 0 | M20: 532000 | N20: 1000 | O20: 532 | P20: 0 | R20: 1835.4 | S20: 25 | T20: 1860.4 | U20: 533860.4 | V20: 0 | W20: 0 | X20: 0 | Y20: 0 | Z20: 0 | AA20: 0 | AB20: 533860.4 | AC20: 533.8604 | AD20: 0
A21: Total | F21: =SUM(F20) -> 1000 | H21: =SUM(H20) -> 532000 | I21: =SUM(INDIRECT("i4:i"&ROW()-1)) -> 0 | J21: =SUM(J20) -> 0 | K21: =SUM(INDIRECT("k4:k"&ROW()-1)) -> 0 | M21: =H21-L21 -> 532000 | N21: =F21-I21 -> 1000 | O21: =M21/N21 -> 532 | P21: =SUM(P20) -> 0 | R21: =SUM(R17:R20) -> 1835.4 | S21: =SUM(S17:S20) -> 25 | T21: =SUM(T17:T20) -> 1860.4 | U21: =SUM(U20) -> 533860.4 | V21: =SUM(V20) -> 0 | W21: =SUM(W20) -> 0 | X21: =SUM(X20) -> 0 | Y21: =SUM(Y20) -> 0 | Z21: =SUM(Z20) -> 0 | AA21: =SUM(AA20) -> 0 | AB21: =U21-AA21 -> 533860.4 | AC21: =AB21/F21 -> 533.8604 | AD21: =SGIC!AG24 -> 0
A23: 3. Ashoj | R23: Purchase | V23: Sales | Y23: Capital Gain Tax | Z23: Net Receivables | AA23: Principal Amt AP TAX (Sales Unit) | AB23: TC AP TAX | AC23: WACC AP TAX | AD23: P/L AP TAX
A24: S.No | B24: SYMBOL | C24: Bill No | D24: Txn Date | E24: Txn Type | F24: Purchase QTY | G24: PPPU | H24: Total Purchase Amount | I24: Sales Qty | J24: SPPU | K24: Sales Amt | L24: Principal Cost As per NFRS (In case of Sales) | M24: TC AP NFRS | N24: Unit Sum | O24: WACC AP NFRS | P24: P/L AP NFRS | R24: Purchase Commission | S24: DP Charges | T24: Total Commission on Purchase | U24: Total Investment Cost(Including Comission | V24: Sales Commission | W24: DP Charges | X24: Total Commission on Sales
A25: 1 | B25: KSBBL | D25: 45917 | E25: Opening | F25: 1000 | H25: 532000 | I25: 0 | K25: 0 | L25: 0 | M25: 532000 | N25: 1000 | O25: 532 | P25: 0 | R25: 1835.4 | S25: 25 | T25: 1860.4 | U25: 533860.4 | V25: 0 | W25: 0 | X25: 0 | Y25: 0 | Z25: 0 | AA25: 0 | AB25: 533860.4 | AC25: 533.8604 | AD25: 0

Sheet IGI
A1: Jyoti Capital Limited
A2: Kamalpokhari, Kathmandu
A3: JCL Portfolio Statement
A5: 1. Shrawan | R5: Purchase | V5: Sales | Y5: Capital Gain Tax | Z5: Net Receivables | AA5: Principal Amt AP TAX (Sales Unit) | AB5: TC AP TAX | AC5: WACC AP TAX | AD5: P/L AP TAX
A6: S.No | B6: SYMBOL | C6: Bill No | D6: Txn Date | E6: Txn Type | F6: Purchase QTY | G6: PPPU | H6: Total Purchase Amount | I6: Sales Qty | J6: SPPU | K6: Sales Amt | L6: Principal Cost As per NFRS (In case of Sales) | M6: TC AP NFRS | N6: Unit Sum | O6: WACC AP NFRS | P6: P/L AP NFRS | R6: Purchase Commission | S6: DP Charges | T6: Total Commission on Purchase | U6: Total Investment Cost(Including Comission | V6: Sales Commission | W6: DP Charges | X6: Total Commission on Sales
A7: 1 | B7: IGI | D7: 45855 | E7: Opening | F7: 5674 | G7: 556.99 | H7: =Table2428308910131415162324253233[[#This Row],[Purchase QTY]]*Table2428308910131415162324253233[[#This Row],[PPPU]] -> 3160361.3 | M7: =Table2428308910131415162324253233[[#This Row],[Total Purchase Amount]] -> 3160361.3 | N7: =IF(Table2428308910131415162324253233[[#This Row],[Txn Type]]="opening",Table2428308910131415162324253233[[#This Row],[Purchase QTY]],"Error") -> 5674 | O7: =IFERROR(Table2428308910131415162324253233[[#This Row],[TC AP NFRS]]/Table2428308910131415162324253233[[#This Row],[Unit Sum]],0) -> 556.99 | P7: =Table2428308910131415162324253233[[#This Row],[Sales Amt]]-Table2428308910131415162324253233[[#This Row],[Principal Cost As per NFRS (In case of Sales)]] -> 0 | T7: =R7+S7 -> 0 | U7: =AB7 -> 3569188.1 | AB7: =F7*AC7 -> 3569188.1 | AC7: 629.04267
A8: =A7+1 -> 2 | B8: IGI | C8: B/0000596/082-83 | D8: 45867 | E8: purchase | F8: 1000 | G8: =Table2428308910131415162324253233[[#This Row],[Total Purchase Amount]]/Table2428308910131415162324253233[[#This Row],[Purchase QTY]] -> 583 | H8: 583000 | I8: 0 | J8: =IFERROR(Table2428308910131415162324253233[[#This Row],[Sales Amt]]/Table2428308910131415162324253233[[#This Row],[Sales Qty]],0) -> 0 | K8: 0 | L8: =Table2428308910131415162324253233[[#This Row],[Sales Qty]]*O7 -> 0 | M8: =M7+Table2428308910131415162324253233[[#This Row],[Total Purchase Amount]]-Table2428308910131415162324253233[[#This Row],[Principal Cost As per NFRS (In case of Sales)]] -> 3743361.3 | N8: =N7+Table2428308910131415162324253233[[#This Row],[Purchase QTY]]-Table2428308910131415162324253233[[#This Row],[Sales Qty]] -> 6674 | O8: =IFERROR(Table2428308910131415162324253233[[#This Row],[TC AP NFRS]]/Table2428308910131415162324253233[[#This Row],[Unit Sum]],0) -> 560.88721 | P8: =Table2428308910131415162324253233[[#This Row],[Sales Amt]]-Table2428308910131415162324253233[[#This Row],[Principal Cost As per NFRS (In case of Sales)]] -> 0 | R8: 0 | T8: =R8+S8 -> 0 | U8: =H8+T8 -> 583000 | V8: 0 | W8: 0 | X8: =V8+W8 -> 0 | Y8: 0 | Z8: =K8-X8-Y8 -> 0 | AA8: =I8*AC7 -> 0 | AB8: =AB7+U8-AA8 -> 4152188.1 | AC8: =IFERROR(AB8/N8,0) -> 622.14386 | AD8: =Z8-AA8+Y8 -> 0
A9: =A8+1 -> 3 | B9: IGI | G9: =IF(Table2428308910131415162324253233[[#This Row],[SPPU]]>=0,0,Table2428308910131415162324253233[[#This Row],[Total Purchase Amount]]/Table2428308910131415162324253233[[#This Row],[Purchase QTY]]) -> 0 | J9: =IFERROR(Table2428308910131415162324253233[[#This Row],[Sales Amt]]/Table2428308910131415162324253233[[#This Row],[Sales Qty]],0) -> 0 | L9: =Table2428308910131415162324253233[[#This Row],[Sales Qty]]*O8 -> 0 | M9: =M8+Table2428308910131415162324253233[[#This Row],[Total Purchase Amount]]-Table2428308910131415162324253233[[#This Row],[Principal Cost As per NFRS (In case of Sales)]] -> 3743361.3 | N9: =N8+Table2428308910131415162324253233[[#This Row],[Purchase QTY]]-Table2428308910131415162324253233[[#This Row],[Sales Qty]] -> 6674 | O9: =IFERROR(Table2428308910131415162324253233[[#This Row],[TC AP NFRS]]/Table2428308910131415162324253233[[#This Row],[Unit Sum]],0) -> 560.88721 | P9: =Table2428308910131415162324253233[[#This Row],[Sales Amt]]-Table2428308910131415162324253233[[#This Row],[Principal Cost As per NFRS (In case of Sales)]] -> 0 | R9: 0 | T9: =R9+S9 -> 0 | U9: =H9+T9 -> 0 | V9: 0 | W9: 0 | X9: =V9+W9 -> 0 | Y9: 0 | Z9: =K9-X9-Y9 -> 0 | AA9: =I9*AC8 -> 0 | AB9: =AB8+U9-AA9 -> 4152188.1 | AC9: =IFERROR(AB9/N9,0) -> 622.14386 | AD9: =Z9-AA9+Y9 -> 0
A10: =A9+1 -> 4 | G10: =IF(Table2428308910131415162324253233[[#This Row],[SPPU]]>=0,0,Table2428308910131415162324253233[[#This Row],[Total Purchase Amount]]/Table2428308910131415162324253233[[#This Row],[Purchase QTY]]) -> 0 | I10: 0 | J10: =IFERROR(Table2428308910131415162324253233[[#This Row],[Sales Amt]]/Table2428308910131415162324253233[[#This Row],[Sales Qty]],0) -> 0 | K10: 0 | L10: =Table2428308910131415162324253233[[#This Row],[Sales Qty]]*O9 -> 0 | M10: =M9+Table2428308910131415162324253233[[#This Row],[Total Purchase Amount]]-Table2428308910131415162324253233[[#This Row],[Principal Cost As per NFRS (In case of Sales)]] -> 3743361.3 | N10: =N9+Table2428308910131415162324253233[[#This Row],[Purchase QTY]]-Table2428308910131415162324253233[[#This Row],[Sales Qty]] -> 6674 | O10: =IFERROR(Table2428308910131415162324253233[[#This Row],[TC AP NFRS]]/Table2428308910131415162324253233[[#This Row],[Unit Sum]],0) -> 560.88721 | P10: =Table2428308910131415162324253233[[#This Row],[Sales Amt]]-Table2428308910131415162324253233[[#This Row],[Principal Cost As per NFRS (In case of Sales)]] -> 0 | R10: 0 | T10: =R10+S10 -> 0 | U10: =H10+T10 -> 0 | V10: 0 | W10: 0 | X10: =V10+W10 -> 0 | Y10: 0 | Z10: =K10-X10-Y10 -> 0 | AA10: =I10*AC9 -> 0 | AB10: =AB9+U10-AA10 -> 4152188.1 | AC10: =IFERROR(AB10/N10,0) -> 622.14386 | AD10: =Z10-AA10+Y10 -> 0
A11: =A10+1 -> 5 | F11: 0 | G11: =Table2428308910131415162324253233[[#This Row],[Total Purchase Amount]]/Table2428308910131415162324253233[[#This Row],[Purchase QTY]] -> #DIV/0! | H11: 0 | I11: 0 | J11: =IFERROR(Table2428308910131415162324253233[[#This Row],[Sales Amt]]/Table2428308910131415162324253233[[#This Row],[Sales Qty]],0) -> 0 | K11: =Table2428308910131415162324253233[[#This Row],[Sales Qty]]*Table2428308910131415162324253233[[#This Row],[SPPU]] -> 0 | L11: =Table2428308910131415162324253233[[#This Row],[Sales Qty]]*O10 -> 0 | M11: =M10+Table2428308910131415162324253233[[#This Row],[Total Purchase Amount]]-Table2428308910131415162324253233[[#This Row],[Principal Cost As per NFRS (In case of Sales)]] -> 3743361.3 | N11: =N10+Table2428308910131415162324253233[[#This Row],[Purchase QTY]]-Table2428308910131415162324253233[[#This Row],[Sales Qty]] -> 6674 | O11: =IFERROR(Table2428308910131415162324253233[[#This Row],[TC AP NFRS]]/Table2428308910131415162324253233[[#This Row],[Unit Sum]],0) -> 560.88721 | P11: =Table2428308910131415162324253233[[#This Row],[Sales Amt]]-Table2428308910131415162324253233[[#This Row],[Principal Cost As per NFRS (In case of Sales)]] -> 0 | R11: 0 | T11: =R11+S11 -> 0 | U11: =H11+T11 -> 0 | V11: 0 | W11: 0 | X11: =V11+W11 -> 0 | Y11: 0 | Z11: =K11-X11-Y11 -> 0 | AA11: =I11*AC10 -> 0 | AB11: =AB10+U11-AA11 -> 4152188.1 | AC11: =IFERROR(AB11/N11,0) -> 622.14386 | AD11: =Z11-AA11+Y11 -> 0
A12: =A11+1 -> 6 | F12: 0 | G12: =Table2428308910131415162324253233[[#This Row],[Total Purchase Amount]]/Table2428308910131415162324253233[[#This Row],[Purchase QTY]] -> #DIV/0! | H12: 0 | I12: 0 | J12: =IFERROR(Table2428308910131415162324253233[[#This Row],[Sales Amt]]/Table2428308910131415162324253233[[#This Row],[Sales Qty]],0) -> 0 | K12: =Table2428308910131415162324253233[[#This Row],[Sales Qty]]*Table2428308910131415162324253233[[#This Row],[SPPU]] -> 0 | L12: =Table2428308910131415162324253233[[#This Row],[Sales Qty]]*O11 -> 0 | M12: =M11+Table2428308910131415162324253233[[#This Row],[Total Purchase Amount]]-Table2428308910131415162324253233[[#This Row],[Principal Cost As per NFRS (In case of Sales)]] -> 3743361.3 | N12: =N11+Table2428308910131415162324253233[[#This Row],[Purchase QTY]]-Table2428308910131415162324253233[[#This Row],[Sales Qty]] -> 6674 | O12: =IFERROR(Table2428308910131415162324253233[[#This Row],[TC AP NFRS]]/Table2428308910131415162324253233[[#This Row],[Unit Sum]],0) -> 560.88721 | P12: =Table2428308910131415162324253233[[#This Row],[Sales Amt]]-Table2428308910131415162324253233[[#This Row],[Principal Cost As per NFRS (In case of Sales)]] -> 0 | R12: 0 | T12: =R12+S12 -> 0 | U12: =H12+T12 -> 0 | V12: 0 | W12: 0 | X12: =V12+W12 -> 0 | Y12: 0 | Z12: =K12-X12-Y12 -> 0 | AA12: =I12*AC11 -> 0 | AB12: =AB11+U12-AA12 -> 4152188.1 | AC12: =IFERROR(AB12/N12,0) -> 622.14386 | AD12: =Z12-AA12+Y12 -> 0
A13: =A12+1 -> 7 | G13: =IF(Table2428308910131415162324253233[[#This Row],[SPPU]]>=0,0,Table2428308910131415162324253233[[#This Row],[Total Purchase Amount]]/Table2428308910131415162324253233[[#This Row],[Purchase QTY]]) -> 0 | I13: 0 | J13: =IFERROR(Table2428308910131415162324253233[[#This Row],[Sales Amt]]/Table2428308910131415162324253233[[#This Row],[Sales Qty]],0) -> 0 | K13: 0 | L13: =Table2428308910131415162324253233[[#This Row],[Sales Qty]]*O11 -> 0 | M13: =M12+Table2428308910131415162324253233[[#This Row],[Total Purchase Amount]]-Table2428308910131415162324253233[[#This Row],[Principal Cost As per NFRS (In case of Sales)]] -> 3743361.3 | N13: =N12+Table2428308910131415162324253233[[#This Row],[Purchase QTY]]-Table2428308910131415162324253233[[#This Row],[Sales Qty]] -> 6674 | O13: =IFERROR(Table2428308910131415162324253233[[#This Row],[TC AP NFRS]]/Table2428308910131415162324253233[[#This Row],[Unit Sum]],0) -> 560.88721 | P13: =Table2428308910131415162324253233[[#This Row],[Sales Amt]]-Table2428308910131415162324253233[[#This Row],[Principal Cost As per NFRS (In case of Sales)]] -> 0 | R13: 0 | T13: =R13+S13 -> 0 | U13: =H13+T13 -> 0 | V13: 0 | W13: 0 | X13: =V13+W13 -> 0 | Y13: 0 | Z13: =K13-X13-Y13 -> 0 | AA13: =I13*AC12 -> 0 | AB13: =AB12+U13-AA13 -> 4152188.1 | AC13: =IFERROR(AB13/N13,0) -> 622.14386 | AD13: =Z13-AA13+Y13 -> 0
A14: =A13+1 -> 8 | G14: =IF(Table2428308910131415162324253233[[#This Row],[SPPU]]>=0,0,Table2428308910131415162324253233[[#This Row],[Total Purchase Amount]]/Table2428308910131415162324253233[[#This Row],[Purchase QTY]]) -> 0 | I14: 0 | J14: =IFERROR(Table2428308910131415162324253233[[#This Row],[Sales Amt]]/Table2428308910131415162324253233[[#This Row],[Sales Qty]],0) -> 0 | K14: 0 | L14: =Table2428308910131415162324253233[[#This Row],[Sales Qty]]*O13 -> 0 | M14: =M13+Table2428308910131415162324253233[[#This Row],[Total Purchase Amount]]-Table2428308910131415162324253233[[#This Row],[Principal Cost As per NFRS (In case of Sales)]] -> 3743361.3 | N14: =N13+Table2428308910131415162324253233[[#This Row],[Purchase QTY]]-Table2428308910131415162324253233[[#This Row],[Sales Qty]] -> 6674 | O14: =IFERROR(Table2428308910131415162324253233[[#This Row],[TC AP NFRS]]/Table2428308910131415162324253233[[#This Row],[Unit Sum]],0) -> 560.88721 | P14: =Table2428308910131415162324253233[[#This Row],[Sales Amt]]-Table2428308910131415162324253233[[#This Row],[Principal Cost As per NFRS (In case of Sales)]] -> 0 | R14: 0 | T14: =R14+S14 -> 0 | U14: =H14+T14 -> 0 | V14: 0 | W14: 0 | X14: =V14+W14 -> 0 | Y14: 0 | Z14: =K14-X14-Y14 -> 0 | AA14: =I14*AC13 -> 0 | AB14: =AB13+U14-AA14 -> 4152188.1 | AC14: =IFERROR(AB14/N14,0) -> 622.14386 | AD14: =Z14-AA14+Y14 -> 0
A15: =A14+1 -> 9 | G15: =IF(Table2428308910131415162324253233[[#This Row],[SPPU]]>=0,0,Table2428308910131415162324253233[[#This Row],[Total Purchase Amount]]/Table2428308910131415162324253233[[#This Row],[Purchase QTY]]) -> 0 | I15: 0 | J15: =IFERROR(Table2428308910131415162324253233[[#This Row],[Sales Amt]]/Table2428308910131415162324253233[[#This Row],[Sales Qty]],0) -> 0 | K15: 0 | L15: =Table2428308910131415162324253233[[#This Row],[Sales Qty]]*O14 -> 0 | M15: =M14+Table2428308910131415162324253233[[#This Row],[Total Purchase Amount]]-Table2428308910131415162324253233[[#This Row],[Principal Cost As per NFRS (In case of Sales)]] -> 3743361.3 | N15: =N14+Table2428308910131415162324253233[[#This Row],[Purchase QTY]]-Table2428308910131415162324253233[[#This Row],[Sales Qty]] -> 6674 | O15: =IFERROR(Table2428308910131415162324253233[[#This Row],[TC AP NFRS]]/Table2428308910131415162324253233[[#This Row],[Unit Sum]],0) -> 560.88721 | P15: =Table2428308910131415162324253233[[#This Row],[Sales Amt]]-Table2428308910131415162324253233[[#This Row],[Principal Cost As per NFRS (In case of Sales)]] -> 0 | R15: 0 | T15: =R15+S15 -> 0 | U15: =H15+T15 -> 0 | V15: 0 | W15: 0 | X15: =V15+W15 -> 0 | Y15: 0 | Z15: =K15-X15-Y15 -> 0 | AA15: =I15*AC14 -> 0 | AB15: =AB14+U15-AA15 -> 4152188.1 | AC15: =IFERROR(AB15/N15,0) -> 622.14386 | AD15: =Z15-AA15+Y15 -> 0
A16: Total | F16: =SUM(INDIRECT("f4:f"&ROW()-1)) -> 6674 | H16: =SUM(INDIRECT("h4:h"&ROW()-1)) -> 3743361.3 | I16: =SUM(INDIRECT("i4:i"&ROW()-1)) -> 0 | J16: =IFERROR(Table2428308910131415162324253233[[#This Row],[Sales Amt]]/Table2428308910131415162324253233[[#This Row],[Sales Qty]],0) -> 0 | K16: =SUM(K7:K15) -> 0 | M16: =Table2428308910131415162324253233[[#This Row],[Total Purchase Amount]]-Table2428308910131415162324253233[[#This Row],[Sales Amt]] -> 3743361.3 | N16: =Table2428308910131415162324253233[[#This Row],[Purchase QTY]]-Table2428308910131415162324253233[[#This Row],[Sales Qty]] -> 6674 | O16: =Table2428308910131415162324253233[[#This Row],[TC AP NFRS]]/Table2428308910131415162324253233[[#This Row],[Unit Sum]] -> 560.88721 | P16: =SUM(INDIRECT("p4:p"&ROW()-1)) -> 0 | R16: =SUM(R7:R15) -> 0 | S16: =SUM(S7:S15) -> 0 | T16: =SUM(T7:T15) -> 0 | U16: =SUM(U7:U15) -> 4152188.1 | V16: =SUM(V7:V15) -> 0 | W16: =SUM(W7:W15) -> 0 | X16: =SUM(X7:X15) -> 0 | Y16: =SUM(Y7:Y15) -> 0 | ... AA16: =SUM(AA7:AA15) -> 0 | AB16: =U16-AA16 -> 4152188.1 | AC16: =IFERROR(AB16/N16,0) -> 622.14386 | AD16: =SUM(AD7:AD15) -> 0
A18: 2. Bhadra | R18: Purchase | V18: Sales | Y18: Capital Gain Tax | Z18: Net Receivables | AA18: Principal Amt AP TAX (Sales Unit) | AB18: TC AP TAX | AC18: WACC AP TAX | AD18: P/L AP TAX
A19: S.No | B19: SYMBOL | C19: Bill No | D19: Txn Date | E19: Txn Type | F19: Purchase QTY | G19: PPPU | H19: Total Purchase Amount | I19: Sales Qty | J19: SPPU | K19: Sales Amt | L19: Principal Cost As per NFRS (In case of Sales) | M19: TC AP NFRS | N19: Unit Sum | O19: WACC AP NFRS | P19: P/L AP NFRS | R19: Purchase Commission | S19: DP Charges | T19: Total Commission on Purchase | U19: Total Investment Cost(Including Comission | V19: Sales Commission | W19: DP Charges | X19: Total Commission on Sales
A20: 1 | B20: IGI | D20: 45886 | E20: Opening | F20: 6674 | H20: 3743361.3 | M20: 3743361.3 | N20: 6674 | O20: 560.88721 | P20: 0 | U20: 4152188.1 | AB20: 4152188.1 | AC20: 622.14386
A21: Total | F21: =SUM(F20) -> 6674 | H21: =SUM(H20) -> 3743361.3 | I21: =SUM(INDIRECT("i4:i"&ROW()-1)) -> 0 | J21: =SUM(J20) -> 0 | K21: =SUM(INDIRECT("k4:k"&ROW()-1)) -> 0 | M21: =H21-L21 -> 3743361.3 | N21: =F21-I21 -> 6674 | O21: =M21/N21 -> 560.88721 | P21: =SUM(P20) -> 0 | R21: =SUM(R17:R20) -> 0 | S21: =SUM(S17:S20) -> 0 | T21: =SUM(T17:T20) -> 0 | U21: =SUM(U20) -> 4152188.1 | V21: =SUM(V20) -> 0 | W21: =SUM(W20) -> 0 | X21: =SUM(X20) -> 0 | Y21: =SUM(Y20) -> 0 | Z21: =SUM(Z20) -> 0 | AA21: =SUM(AA20) -> 0 | AB21: =U21-AA21 -> 4152188.1 | AC21: =AB21/F21 -> 622.14386 | AD21: =SGIC!AG24 -> 0
A23: 3. Ashoj | R23: Purchase | V23: Sales | Y23: Capital Gain Tax | Z23: Net Receivables | AA23: Principal Amt AP TAX (Sales Unit) | AB23: TC AP TAX | AC23: WACC AP TAX | AD23: P/L AP TAX
A24: S.No | B24: SYMBOL | C24: Bill No | D24: Txn Date | E24: Txn Type | F24: Purchase QTY | G24: PPPU | H24: Total Purchase Amount | I24: Sales Qty | J24: SPPU | K24: Sales Amt | L24: Principal Cost As per NFRS (In case of Sales) | M24: TC AP NFRS | N24: Unit Sum | O24: WACC AP NFRS | P24: P/L AP NFRS | R24: Purchase Commission | S24: DP Charges | T24: Total Commission on Purchase | U24: Total Investment Cost(Including Comission | V24: Sales Commission | W24: DP Charges | X24: Total Commission on Sales
A25: 1 | B25: IGI | D25: 45917 | E25: Opening | F25: 6674 | H25: 3743361.3 | I25: 0 | J25: 0 | K25: 0 | M25: 3743361.3 | N25: 6674 | O25: 560.88721 | P25: 0 | R25: 0 | S25: 0 | T25: 0 | U25: 4152188.1 | V25: 0 | W25: 0 | X25: 0 | Y25: 0 | Z25: 0 | AA25: 0 | AB25: 4152188.1 | AC25: 622.14386 | AD25: 0

Sheet SRLI
A1: Jyoti Capital Limited
A2: Kamalpokhari, Kathmandu
A3: JCL Portfolio Statement
A5: 1. Shrawan | R5: Purchase | V5: Sales | Y5: Capital Gain Tax | Z5: Net Receivables | AA5: Principal Amt AP TAX (Sales Unit) | AB5: TC AP TAX | AC5: WACC AP TAX | AD5: P/L AP TAX
A6: S.No | B6: SYMBOL | C6: Bill No | D6: Txn Date | E6: Txn Type | F6: Purchase QTY | G6: PPPU | H6: Total Purchase Amount | I6: Sales Qty | J6: SPPU | K6: Sales Amt | L6: Principal Cost As per NFRS (In case of Sales) | M6: TC AP NFRS | N6: Unit Sum | O6: WACC AP NFRS | P6: P/L AP NFRS | R6: Purchase Commission | S6: DP Charges | T6: Total Commission on Purchase | U6: Total Investment Cost(Including Comission | V6: Sales Commission | W6: DP Charges | X6: Total Commission on Sales
A7: 1 | B7: SRLI | D7: 45855 | E7: Opening | F7: 4506 | G7: 410.19 | H7: =Table24283089101314151623242532[[#This Row],[Purchase QTY]]*Table24283089101314151623242532[[#This Row],[PPPU]] -> 1848316.1 | M7: =Table24283089101314151623242532[[#This Row],[Total Purchase Amount]] -> 1848316.1 | N7: =IF(Table24283089101314151623242532[[#This Row],[Txn Type]]="opening",Table24283089101314151623242532[[#This Row],[Purchase QTY]],"Error") -> 4506 | O7: =IFERROR(Table24283089101314151623242532[[#This Row],[TC AP NFRS]]/Table24283089101314151623242532[[#This Row],[Unit Sum]],0) -> 410.19 | P7: =Table24283089101314151623242532[[#This Row],[Sales Amt]]-Table24283089101314151623242532[[#This Row],[Principal Cost As per NFRS (In case of Sales)]] -> 0 | T7: =R7+S7 -> 0 | U7: =AB7 -> 2249328.5 | AB7: =F7*AC7 -> 2249328.5 | AC7: 499.18519
A8: =A7+1 -> 2 | B8: SRLI | C8: B/0000515/082-83 | D8: 45866 | E8: purchase | F8: 678 | G8: =Table24283089101314151623242532[[#This Row],[Total Purchase Amount]]/Table24283089101314151623242532[[#This Row],[Purchase QTY]] -> 426.11563 | H8: 288906.4 | I8: 0 | J8: =IFERROR(Table24283089101314151623242532[[#This Row],[Sales Amt]]/Table24283089101314151623242532[[#This Row],[Sales Qty]],0) -> 0 | K8: 0 | L8: =Table24283089101314151623242532[[#This Row],[Sales Qty]]*O7 -> 0 | M8: =M7+Table24283089101314151623242532[[#This Row],[Total Purchase Amount]]-Table24283089101314151623242532[[#This Row],[Principal Cost As per NFRS (In case of Sales)]] -> 2137222.5 | N8: =N7+Table24283089101314151623242532[[#This Row],[Purchase QTY]]-Table24283089101314151623242532[[#This Row],[Sales Qty]] -> 5184 | O8: =IFERROR(Table24283089101314151623242532[[#This Row],[TC AP NFRS]]/Table24283089101314151623242532[[#This Row],[Unit Sum]],0) -> 412.27287 | P8: =Table24283089101314151623242532[[#This Row],[Sales Amt]]-Table24283089101314151623242532[[#This Row],[Principal Cost As per NFRS (In case of Sales)]] -> 0 | R8: =43.33+988.69 -> 1032.02 | S8: 25 | T8: =R8+S8 -> 1057.02 | U8: =H8+T8 -> 289963.42 | V8: 0 | W8: 0 | X8: =V8+W8 -> 0 | Y8: 0 | Z8: =K8-X8-Y8 -> 0 | AA8: =I8*AC7 -> 0 | AB8: =AB7+U8-AA8 -> 2539291.9 | AC8: =IFERROR(AB8/N8,0) -> 489.83254 | AD8: =Z8-AA8+Y8 -> 0
A9: =A8+1 -> 3 | B9: SRLI | C9: B/0000601/082-83 | D9: 45867 | E9: purchase | F9: 1000 | G9: =IF(Table24283089101314151623242532[[#This Row],[SPPU]]>0,0,Table24283089101314151623242532[[#This Row],[Total Purchase Amount]]/Table24283089101314151623242532[[#This Row],[Purchase QTY]]) -> 434 | H9: 434000 | J9: =IFERROR(Table24283089101314151623242532[[#This Row],[Sales Amt]]/Table24283089101314151623242532[[#This Row],[Sales Qty]],0) -> 0 | L9: =Table24283089101314151623242532[[#This Row],[Sales Qty]]*O8 -> 0 | M9: =M8+Table24283089101314151623242532[[#This Row],[Total Purchase Amount]]-Table24283089101314151623242532[[#This Row],[Principal Cost As per NFRS (In case of Sales)]] -> 2571222.5 | N9: =N8+Table24283089101314151623242532[[#This Row],[Purchase QTY]]-Table24283089101314151623242532[[#This Row],[Sales Qty]] -> 6184 | O9: =IFERROR(Table24283089101314151623242532[[#This Row],[TC AP NFRS]]/Table24283089101314151623242532[[#This Row],[Unit Sum]],0) -> 415.78631 | P9: =Table24283089101314151623242532[[#This Row],[Sales Amt]]-Table24283089101314151623242532[[#This Row],[Principal Cost As per NFRS (In case of Sales)]] -> 0 | R9: =65.13+1482.75 -> 1547.88 | S9: 25 | T9: =R9+S9 -> 1572.88 | U9: =H9+T9 -> 435572.88 | V9: 0 | W9: 0 | X9: =V9+W9 -> 0 | Y9: 0 | Z9: =K9-X9-Y9 -> 0 | AA9: =I9*AC8 -> 0 | AB9: =AB8+U9-AA9 -> 2974864.8 | AC9: =IFERROR(AB9/N9,0) -> 481.05834 | AD9: =Z9-AA9+Y9 -> 0
A10: =A9+1 -> 4 | G10: =IF(Table24283089101314151623242532[[#This Row],[SPPU]]>=0,0,Table24283089101314151623242532[[#This Row],[Total Purchase Amount]]/Table24283089101314151623242532[[#This Row],[Purchase QTY]]) -> 0 | I10: 0 | J10: =IFERROR(Table24283089101314151623242532[[#This Row],[Sales Amt]]/Table24283089101314151623242532[[#This Row],[Sales Qty]],0) -> 0 | K10: 0 | L10: =Table24283089101314151623242532[[#This Row],[Sales Qty]]*O9 -> 0 | M10: =M9+Table24283089101314151623242532[[#This Row],[Total Purchase Amount]]-Table24283089101314151623242532[[#This Row],[Principal Cost As per NFRS (In case of Sales)]] -> 2571222.5 | N10: =N9+Table24283089101314151623242532[[#This Row],[Purchase QTY]]-Table24283089101314151623242532[[#This Row],[Sales Qty]] -> 6184 | O10: =IFERROR(Table24283089101314151623242532[[#This Row],[TC AP NFRS]]/Table24283089101314151623242532[[#This Row],[Unit Sum]],0) -> 415.78631 | P10: =Table24283089101314151623242532[[#This Row],[Sales Amt]]-Table24283089101314151623242532[[#This Row],[Principal Cost As per NFRS (In case of Sales)]] -> 0 | R10: 0 | T10: =R10+S10 -> 0 | U10: =H10+T10 -> 0 | V10: 0 | W10: 0 | X10: =V10+W10 -> 0 | Y10: 0 | Z10: =K10-X10-Y10 -> 0 | AA10: =I10*AC9 -> 0 | AB10: =AB9+U10-AA10 -> 2974864.8 | AC10: =IFERROR(AB10/N10,0) -> 481.05834 | AD10: =Z10-AA10+Y10 -> 0
A11: =A10+1 -> 5 | F11: 0 | G11: =Table24283089101314151623242532[[#This Row],[Total Purchase Amount]]/Table24283089101314151623242532[[#This Row],[Purchase QTY]] -> #DIV/0! | H11: 0 | I11: 0 | J11: =IFERROR(Table24283089101314151623242532[[#This Row],[Sales Amt]]/Table24283089101314151623242532[[#This Row],[Sales Qty]],0) -> 0 | K11: =Table24283089101314151623242532[[#This Row],[Sales Qty]]*Table24283089101314151623242532[[#This Row],[SPPU]] -> 0 | L11: =Table24283089101314151623242532[[#This Row],[Sales Qty]]*O10 -> 0 | M11: =M10+Table24283089101314151623242532[[#This Row],[Total Purchase Amount]]-Table24283089101314151623242532[[#This Row],[Principal Cost As per NFRS (In case of Sales)]] -> 2571222.5 | N11: =N10+Table24283089101314151623242532[[#This Row],[Purchase QTY]]-Table24283089101314151623242532[[#This Row],[Sales Qty]] -> 6184 | O11: =IFERROR(Table24283089101314151623242532[[#This Row],[TC AP NFRS]]/Table24283089101314151623242532[[#This Row],[Unit Sum]],0) -> 415.78631 | P11: =Table24283089101314151623242532[[#This Row],[Sales Amt]]-Table24283089101314151623242532[[#This Row],[Principal Cost As per NFRS (In case of Sales)]] -> 0 | R11: 0 | T11: =R11+S11 -> 0 | U11: =H11+T11 -> 0 | V11: 0 | W11: 0 | X11: =V11+W11 -> 0 | Y11: 0 | Z11: =K11-X11-Y11 -> 0 | AA11: =I11*AC10 -> 0 | AB11: =AB10+U11-AA11 -> 2974864.8 | AC11: =IFERROR(AB11/N11,0) -> 481.05834 | AD11: =Z11-AA11+Y11 -> 0
A12: =A11+1 -> 6 | F12: 0 | G12: =Table24283089101314151623242532[[#This Row],[Total Purchase Amount]]/Table24283089101314151623242532[[#This Row],[Purchase QTY]] -> #DIV/0! | H12: 0 | I12: 0 | J12: =IFERROR(Table24283089101314151623242532[[#This Row],[Sales Amt]]/Table24283089101314151623242532[[#This Row],[Sales Qty]],0) -> 0 | K12: =Table24283089101314151623242532[[#This Row],[Sales Qty]]*Table24283089101314151623242532[[#This Row],[SPPU]] -> 0 | L12: =Table24283089101314151623242532[[#This Row],[Sales Qty]]*O11 -> 0 | M12: =M11+Table24283089101314151623242532[[#This Row],[Total Purchase Amount]]-Table24283089101314151623242532[[#This Row],[Principal Cost As per NFRS (In case of Sales)]] -> 2571222.5 | N12: =N11+Table24283089101314151623242532[[#This Row],[Purchase QTY]]-Table24283089101314151623242532[[#This Row],[Sales Qty]] -> 6184 | O12: =IFERROR(Table24283089101314151623242532[[#This Row],[TC AP NFRS]]/Table24283089101314151623242532[[#This Row],[Unit Sum]],0) -> 415.78631 | P12: =Table24283089101314151623242532[[#This Row],[Sales Amt]]-Table24283089101314151623242532[[#This Row],[Principal Cost As per NFRS (In case of Sales)]] -> 0 | R12: 0 | T12: =R12+S12 -> 0 | U12: =H12+T12 -> 0 | V12: 0 | W12: 0 | X12: =V12+W12 -> 0 | Y12: 0 | Z12: =K12-X12-Y12 -> 0 | AA12: =I12*AC11 -> 0 | AB12: =AB11+U12-AA12 -> 2974864.8 | AC12: =IFERROR(AB12/N12,0) -> 481.05834 | AD12: =Z12-AA12+Y12 -> 0
A13: =A12+1 -> 7 | G13: =IF(Table24283089101314151623242532[[#This Row],[SPPU]]>=0,0,Table24283089101314151623242532[[#This Row],[Total Purchase Amount]]/Table24283089101314151623242532[[#This Row],[Purchase QTY]]) -> 0 | I13: 0 | J13: =IFERROR(Table24283089101314151623242532[[#This Row],[Sales Amt]]/Table24283089101314151623242532[[#This Row],[Sales Qty]],0) -> 0 | K13: 0 | L13: =Table24283089101314151623242532[[#This Row],[Sales Qty]]*O11 -> 0 | M13: =M12+Table24283089101314151623242532[[#This Row],[Total Purchase Amount]]-Table24283089101314151623242532[[#This Row],[Principal Cost As per NFRS (In case of Sales)]] -> 2571222.5 | N13: =N12+Table24283089101314151623242532[[#This Row],[Purchase QTY]]-Table24283089101314151623242532[[#This Row],[Sales Qty]] -> 6184 | O13: =IFERROR(Table24283089101314151623242532[[#This Row],[TC AP NFRS]]/Table24283089101314151623242532[[#This Row],[Unit Sum]],0) -> 415.78631 | P13: =Table24283089101314151623242532[[#This Row],[Sales Amt]]-Table24283089101314151623242532[[#This Row],[Principal Cost As per NFRS (In case of Sales)]] -> 0 | R13: 0 | T13: =R13+S13 -> 0 | U13: =H13+T13 -> 0 | V13: 0 | W13: 0 | X13: =V13+W13 -> 0 | Y13: 0 | Z13: =K13-X13-Y13 -> 0 | AA13: =I13*AC12 -> 0 | AB13: =AB12+U13-AA13 -> 2974864.8 | AC13: =IFERROR(AB13/N13,0) -> 481.05834 | AD13: =Z13-AA13+Y13 -> 0
A14: =A13+1 -> 8 | G14: =IF(Table24283089101314151623242532[[#This Row],[SPPU]]>=0,0,Table24283089101314151623242532[[#This Row],[Total Purchase Amount]]/Table24283089101314151623242532[[#This Row],[Purchase QTY]]) -> 0 | I14: 0 | J14: =IFERROR(Table24283089101314151623242532[[#This Row],[Sales Amt]]/Table24283089101314151623242532[[#This Row],[Sales Qty]],0) -> 0 | K14: 0 | L14: =Table24283089101314151623242532[[#This Row],[Sales Qty]]*O13 -> 0 | M14: =M13+Table24283089101314151623242532[[#This Row],[Total Purchase Amount]]-Table24283089101314151623242532[[#This Row],[Principal Cost As per NFRS (In case of Sales)]] -> 2571222.5 | N14: =N13+Table24283089101314151623242532[[#This Row],[Purchase QTY]]-Table24283089101314151623242532[[#This Row],[Sales Qty]] -> 6184 | O14: =IFERROR(Table24283089101314151623242532[[#This Row],[TC AP NFRS]]/Table24283089101314151623242532[[#This Row],[Unit Sum]],0) -> 415.78631 | P14: =Table24283089101314151623242532[[#This Row],[Sales Amt]]-Table24283089101314151623242532[[#This Row],[Principal Cost As per NFRS (In case of Sales)]] -> 0 | R14: 0 | T14: =R14+S14 -> 0 | U14: =H14+T14 -> 0 | V14: 0 | W14: 0 | X14: =V14+W14 -> 0 | Y14: 0 | Z14: =K14-X14-Y14 -> 0 | AA14: =I14*AC13 -> 0 | AB14: =AB13+U14-AA14 -> 2974864.8 | AC14: =IFERROR(AB14/N14,0) -> 481.05834 | AD14: =Z14-AA14+Y14 -> 0
A15: =A14+1 -> 9 | G15: =IF(Table24283089101314151623242532[[#This Row],[SPPU]]>=0,0,Table24283089101314151623242532[[#This Row],[Total Purchase Amount]]/Table24283089101314151623242532[[#This Row],[Purchase QTY]]) -> 0 | I15: 0 | J15: =IFERROR(Table24283089101314151623242532[[#This Row],[Sales Amt]]/Table24283089101314151623242532[[#This Row],[Sales Qty]],0) -> 0 | K15: 0 | L15: =Table24283089101314151623242532[[#This Row],[Sales Qty]]*O14 -> 0 | M15: =M14+Table24283089101314151623242532[[#This Row],[Total Purchase Amount]]-Table24283089101314151623242532[[#This Row],[Principal Cost As per NFRS (In case of Sales)]] -> 2571222.5 | N15: =N14+Table24283089101314151623242532[[#This Row],[Purchase QTY]]-Table24283089101314151623242532[[#This Row],[Sales Qty]] -> 6184 | O15: =IFERROR(Table24283089101314151623242532[[#This Row],[TC AP NFRS]]/Table24283089101314151623242532[[#This Row],[Unit Sum]],0) -> 415.78631 | P15: =Table24283089101314151623242532[[#This Row],[Sales Amt]]-Table24283089101314151623242532[[#This Row],[Principal Cost As per NFRS (In case of Sales)]] -> 0 | R15: 0 | T15: =R15+S15 -> 0 | U15: =H15+T15 -> 0 | V15: 0 | W15: 0 | X15: =V15+W15 -> 0 | Y15: 0 | Z15: =K15-X15-Y15 -> 0 | AA15: =I15*AC14 -> 0 | AB15: =AB14+U15-AA15 -> 2974864.8 | AC15: =IFERROR(AB15/N15,0) -> 481.05834 | AD15: =Z15-AA15+Y15 -> 0
A16: Total | F16: =SUM(INDIRECT("f4:f"&ROW()-1)) -> 6184 | H16: =SUM(INDIRECT("h4:h"&ROW()-1)) -> 2571222.5 | I16: =SUM(INDIRECT("i4:i"&ROW()-1)) -> 0 | J16: =Table24283089101314151623242532[[#This Row],[Sales Amt]]/Table24283089101314151623242532[[#This Row],[Sales Qty]] -> #DIV/0! | K16: =SUM(K7:K15) -> 0 | L16: =SUM(L7:L15) -> 0 | M16: =Table24283089101314151623242532[[#This Row],[Total Purchase Amount]]-Table24283089101314151623242532[[#This Row],[Sales Amt]] -> 2571222.5 | N16: =Table24283089101314151623242532[[#This Row],[Purchase QTY]]-Table24283089101314151623242532[[#This Row],[Sales Qty]] -> 6184 | O16: =Table24283089101314151623242532[[#This Row],[TC AP NFRS]]/Table24283089101314151623242532[[#This Row],[Unit Sum]] -> 415.78631 | P16: =SUM(INDIRECT("p4:p"&ROW()-1)) -> 0 | R16: =SUM(R7:R15) -> 2579.9 | S16: =SUM(S7:S15) -> 50 | T16: =SUM(T7:T15) -> 2629.9 | U16: =SUM(U7:U15) -> 2974864.8 | V16: =SUM(V7:V15) -> 0 | W16: =SUM(W7:W15) -> 0 | X16: =SUM(X7:X15) -> 0 | Y16: =SUM(Y7:Y15) -> 0 | ... AA16: =SUM(AA7:AA15) -> 0 | AB16: =U16-AA16 -> 2974864.8 | AC16: =IFERROR(AB16/N16,0) -> 481.05834 | AD16: =SUM(AD7:AD15) -> 0
A19: 2. Bhadra | R19: Purchase | V19: Sales | Y19: Capital Gain Tax | Z19: Net Receivables | AA19: Principal Amt AP TAX (Sales Unit) | AB19: TC AP TAX | AC19: WACC AP TAX | AD19: P/L AP TAX
A20: S.No | B20: SYMBOL | C20: Bill No | D20: Txn Date | E20: Txn Type | F20: Purchase QTY | G20: PPPU | H20: Total Purchase Amount | I20: Sales Qty | J20: SPPU | K20: Sales Amt | L20: Principal Cost As per NFRS (In case of Sales) | M20: TC AP NFRS | N20: Unit Sum | O20: WACC AP NFRS | P20: P/L AP NFRS | R20: Purchase Commission | S20: DP Charges | T20: Total Commission on Purchase | U20: Total Investment Cost(Including Comission | V20: Sales Commission | W20: DP Charges | X20: Total Commission on Sales
A21: 1 | B21: SRLI | D21: 45886 | E21: Opening | F21: 6184 | H21: 2571222.5 | M21: 2571222.5 | N21: 6184 | O21: 415.78631 | R21: 2579.9 | S21: 50 | T21: 2629.9 | U21: 2974864.8 | AB21: 2974864.8 | AC21: 481.05834
F22: =SUM(F21) -> 6184 | H22: =SUM(H21) -> 2571222.5 | I22: =SUM(INDIRECT("i4:i"&ROW()-1)) -> 0 | J22: =SUM(J21) -> 0 | K22: =SUM(INDIRECT("k4:k"&ROW()-1)) -> 0 | M22: =H22-L22 -> 2571222.5 | N22: =F22-I22 -> 6184 | O22: =M22/N22 -> 415.78631 | P22: =SUM(P21) -> 0 | R22: =SUM(R18:R21) -> 2579.9 | S22: =SUM(S18:S21) -> 50 | T22: =SUM(T18:T21) -> 2629.9 | U22: =SUM(U21) -> 2974864.8 | V22: =SUM(V21) -> 0 | W22: =SUM(W21) -> 0 | X22: =SUM(X21) -> 0 | Y22: =SUM(Y21) -> 0 | Z22: =SUM(Z21) -> 0 | AA22: =SUM(AA21) -> 0 | AB22: =U22-AA22 -> 2974864.8 | AC22: =AB22/F22 -> 481.05834 | AD22: =SGIC!AG25 -> 0
A24: 3. Ashoj | R24: Purchase | V24: Sales | Y24: Capital Gain Tax | Z24: Net Receivables | AA24: Principal Amt AP TAX (Sales Unit) | AB24: TC AP TAX | AC24: WACC AP TAX | AD24: P/L AP TAX
A25: S.No | B25: SYMBOL | C25: Bill No | D25: Txn Date | E25: Txn Type | F25: Purchase QTY | G25: PPPU | H25: Total Purchase Amount | I25: Sales Qty | J25: SPPU | K25: Sales Amt | L25: Principal Cost As per NFRS (In case of Sales) | M25: TC AP NFRS | N25: Unit Sum | O25: WACC AP NFRS | P25: P/L AP NFRS | R25: Purchase Commission | S25: DP Charges | T25: Total Commission on Purchase | U25: Total Investment Cost(Including Comission | V25: Sales Commission | W25: DP Charges | X25: Total Commission on Sales
A26: 1 | B26: SRLI | D26: 45917 | E26: Opening | F26: 6184 | H26: 2571222.5 | I26: 0 | J26: 0 | K26: 0 | M26: 2571222.5 | N26: 6184 | O26: 415.78631 | P26: 0 | R26: 2579.9 | S26: 50 | T26: 2629.9 | U26: 2974864.8 | V26: 0 | W26: 0 | X26: 0 | Y26: 0 | Z26: 0 | AA26: 0 | AB26: 2974864.8 | AC26: 481.05834 | AD26: 0

Sheet SALICO
A1: Jyoti Capital Limited
A2: Kamalpokhari, Kathmandu
A3: JCL Portfolio Statement
A5: 1. Shrawan | R5: Purchase | V5: Sales | Y5: Capital Gain Tax | Z5: Net Receivables | AA5: Principal Amt AP TAX (Sales Unit) | AB5: TC AP TAX | AC5: WACC AP TAX | AD5: P/L AP TAX
A6: S.No | B6: SYMBOL | C6: Bill No | D6: Txn Date | E6: Txn Type | F6: Purchase QTY | G6: PPPU | H6: Total Purchase Amount | I6: Sales Qty | J6: SPPU | K6: Sales Amt | L6: Principal Cost As per NFRS (In case of Sales) | M6: TC AP NFRS | N6: Unit Sum | O6: WACC AP NFRS | P6: P/L AP NFRS | R6: Purchase Commission | S6: DP Charges | T6: Total Commission on Purchase | U6: Total Investment Cost(Including Comission | V6: Sales Commission | W6: DP Charges | X6: Total Commission on Sales
A7: 1 | B7: SALICO | D7: 45855 | E7: Opening | F7: 0 | G7: 0 | H7: =Table242830282956[[#This Row],[PPPU]]*Table242830282956[[#This Row],[Purchase QTY]] -> 0 | K7: =Table242830282956[[#This Row],[Sales Qty]]*Table242830282956[[#This Row],[SPPU]] -> 0 | M7: =Table242830282956[[#This Row],[Total Purchase Amount]] -> 0 | N7: =IF(Table242830282956[[#This Row],[Txn Type]]="opening",Table242830282956[[#This Row],[Purchase QTY]],"Error") -> 0 | O7: =IFERROR(Table242830282956[[#This Row],[TC AP NFRS]]/Table242830282956[[#This Row],[Unit Sum]],0) -> 0 | P7: =Table242830282956[[#This Row],[Sales Amt]]-Table242830282956[[#This Row],[Principal Cost As per NFRS (In case of Sales)]] -> 0 | T7: =R7+S7 -> 0 | U7: =AB7 -> 0 | AB7: =F7*AC7 -> 0
A8: 2 | B8: SALICO | C8: B/0001067/082-83 | D8: 45880 | E8: purchase | F8: 760 | G8: =IF(Table242830282956[[#This Row],[SPPU]]>0,0,Table242830282956[[#This Row],[Total Purchase Amount]]/Table242830282956[[#This Row],[Purchase QTY]]) -> 686.86842 | H8: 522020 | I8: 0 | J8: 0 | K8: 0 | L8: =Table242830282956[[#This Row],[Sales Qty]]*O7 -> 0 | M8: =M7+Table242830282956[[#This Row],[Total Purchase Amount]]-Table242830282956[[#This Row],[Principal Cost As per NFRS (In case of Sales)]] -> 522020 | N8: =N7+Table242830282956[[#This Row],[Purchase QTY]]-Table242830282956[[#This Row],[Sales Qty]] -> 760 | O8: =IFERROR(Table242830282956[[#This Row],[TC AP NFRS]]/Table242830282956[[#This Row],[Unit Sum]],0) -> 686.86842 | P8: =Table242830282956[[#This Row],[Sales Amt]]-Table242830282956[[#This Row],[Principal Cost As per NFRS (In case of Sales)]] -> 0 | R8: =1731.32+78.31 -> 1809.63 | S8: 25 | T8: =R8+S8 -> 1834.63 | U8: =H8+T8 -> 523854.63 | V8: 0 | W8: 0 | X8: =V8+W8 -> 0 | Y8: 0 | Z8: =K8-X8-Y8 -> 0 | AA8: =I8*AC7 -> 0 | AB8: =AB7+U8-AA8 -> 523854.63 | AC8: =IFERROR(AB8/N8,0) -> 689.28241 | AD8: =Z8-AA8+Y8 -> 0
A9: 3 | B9: SALICO | C9: B/0001132/082-83 | D9: 45882 | E9: purchase | F9: 470 | G9: =H9/F9 -> 681.57447 | H9: 320340 | I9: 0 | J9: 0 | K9: 0 | M9: =M8+H9-L9 -> 842360 | N9: =N8+G9-J9 -> 1441.5745 | O9: =IFERROR(M9/N9,0) -> 584.33332 | R9: =1091.93+48.06 -> 1139.99 | S9: 25 | T9: =R9+S9 -> 1164.99 | U9: =H9+T9 -> 321504.99 | V9: 0 | W9: 0 | X9: =V9+W9 -> 0 | Y9: 0 | Z9: =K9-X9-Y9 -> 0 | AA9: =I9*AC16 -> 0 | AB9: =AB16+U9-AA9 -> 845359.62 | AC9: =IFERROR(AB9/N9,0) -> 586.41412 | AD9: =Z9-AA9+Y9 -> 0
A10: Total | F10: =SUM(INDIRECT("f4:f"&ROW()-1)) -> 1230 | G10: =Table242830282956[[#This Row],[Total Purchase Amount]]/Table242830282956[[#This Row],[Purchase QTY]] -> 684.84553 | H10: =SUM(INDIRECT("h4:h"&ROW()-1)) -> 842360 | I10: =SUM(INDIRECT("i4:i"&ROW()-1)) -> 0 | J10: =Table242830282956[[#This Row],[Sales Amt]]/Table242830282956[[#This Row],[Sales Qty]] -> #DIV/0! | K10: =SUM(INDIRECT("k4:k"&ROW()-1)) -> 0 | M10: =Table242830282956[[#This Row],[Total Purchase Amount]]-Table242830282956[[#This Row],[Principal Cost As per NFRS (In case of Sales)]] -> 842360 | N10: =Table242830282956[[#This Row],[Purchase QTY]]-Table242830282956[[#This Row],[Sales Qty]] -> 1230 | O10: =Table242830282956[[#This Row],[TC AP NFRS]]/Table242830282956[[#This Row],[Unit Sum]] -> 684.84553 | P10: =SUM(P7:P8) -> 0 | R10: =SUM(R7:R8) -> 1809.63 | S10: =SUM(S7:S8) -> 25 | T10: =SUM(T7:T8) -> 1834.63 | U10: =SUM(U7:U8) -> 523854.63 | V10: =SUM(V7:V8) -> 0 | W10: =SUM(W7:W8) -> 0 | X10: =SUM(X7:X8) -> 0 | Y10: =SUM(Y7:Y8) -> 0 | ... AA10: =SUM(AA7:AA8) -> 0 | AB10: =U10-AA10 -> 523854.63 | AC10: =IFERROR(AB10/N10,0) -> 425.89807 | AD10: =SUM(AD7:AD8) -> 0
A14: 2. Bhadra | R14: Purchase | V14: Sales | Y14: Capital Gain Tax | Z14: Net Receivables | AA14: Principal Amt AP TAX (Sales Unit) | AB14: TC AP TAX | AC14: WACC AP TAX | AD14: P/L AP TAX
A15: S.No | B15: SYMBOL | C15: Bill No | D15: Txn Date | E15: Txn Type | F15: Purchase QTY | G15: PPPU | H15: Total Purchase Amount | I15: Sales Qty | J15: SPPU | K15: Sales Amt | L15: Principal Cost As per NFRS (In case of Sales) | M15: TC AP NFRS | N15: Unit Sum | O15: WACC AP NFRS | P15: P/L AP NFRS | R15: Purchase Commission | S15: DP Charges | T15: Total Commission on Purchase | U15: Total Investment Cost(Including Comission | V15: Sales Commission | W15: DP Charges | X15: Total Commission on Sales
A16: 1 | B16: SALICO | D16: 45886 | E16: Opening | F16: 1230 | G16: 684.84553 | H16: 842360 | M16: 842360 | N16: 1230 | O16: 684.84553 | R16: 1809.63 | S16: 25 | T16: 1834.63 | U16: 523854.63 | AB16: 523854.63 | AC16: 425.89807
A17: 2

Sheet KPCL
A1: 1. Shrawan | R1: Purchase | V1: Sales | Y1: Capital Gain Tax | Z1: Net Receivables | AA1: Principal Amt AP TAX (Sales Unit) | AB1: TC AP TAX | AC1: WACC AP TAX | AD1: P/L AP TAX
A2: S.No | B2: SYMBOL | C2: Bill No | D2: Txn Date | E2: Txn Type | F2: Purchase QTY | G2: PPPU | H2: Total Purchase Amount | I2: Sales Qty | J2: SPPU | K2: Sales Amt | L2: Principal Cost As per NFRS (In case of Sales) | M2: TC AP NFRS | N2: Unit Sum | O2: WACC AP NFRS | P2: P/L AP NFRS | R2: Purchase Commission | S2: DP Charges | T2: Total Commission on Purchase | U2: Total Investment Cost(Including Comission | V2: Sales Commission | W2: DP Charges | X2: Total Commission on Sales
A3: 1 | B3: KPCL | D3: 45886 | E3: Opening | F3: 0 | G3: 0 | H3: 0 | K3: 0 | M3: 0 | N3: 0 | O3: 0 | P3: 0 | T3: =R3+S3 -> 0 | U3: =AB3 -> 0 | AB3: =F3*AC3 -> 0
A4: 2 | B4: KPCL | C4: B/0001131/082-83 | D4: 45882 | E4: Purchase | F4: 100 | G4: =H4/F4 -> 598 | H4: 59800 | I4: 0 | J4: 0 | K4: 0 | L4: 0 | M4: =M3+H4-L4 -> 59800 | N4: =N3+F4-I4 -> 100 | O4: =IFERROR(M4/N4,0) -> 598 | P4: 0 | R4: =197.34+8.97 -> 206.31 | S4: 25 | T4: =R4+S4 -> 231.31 | U4: =H4+T4 -> 60031.31 | V4: 0 | W4: 0 | X4: =V4+W4 -> 0 | Y4: 0 | Z4: =K4-X4-Y4 -> 0 | AA4: =I4*AC3 -> 0 | AB4: =AB3+U4-AA4 -> 60031.31 | AC4: =IFERROR(AB4/N4,0) -> 600.3131 | AD4: =Z4-AA4+Y4 -> 0

Sheet SHLB
A1: 1. Bhadra | R1: Purchase | V1: Sales | Y1: Capital Gain Tax | Z1: Net Receivables | AA1: Principal Amt AP TAX (Sales Unit) | AB1: TC AP TAX | AC1: WACC AP TAX | AD1: P/L AP TAX
A2: S.No | B2: SYMBOL | C2: Bill No | D2: Txn Date | E2: Txn Type | F2: Purchase QTY | G2: PPPU | H2: Total Purchase Amount | I2: Sales Qty | J2: SPPU | K2: Sales Amt | L2: Principal Cost As per NFRS (In case of Sales) | M2: TC AP NFRS | N2: Unit Sum | O2: WACC AP NFRS | P2: P/L AP NFRS | R2: Purchase Commission | S2: DP Charges | T2: Total Commission on Purchase | U2: Total Investment Cost(Including Comission | V2: Sales Commission | W2: DP Charges | X2: Total Commission on Sales
A3: 1 | B3: SHLB | D3: 45886 | E3: Opening | F3: 0 | G3: 0 | H3: 0 | K3: 0 | M3: 0 | N3: 0 | O3: 0 | P3: 0 | T3: =R3+S3 -> 0 | U3: =AB3 -> 0 | AB3: =F3*AC3 -> 0
A4: 2 | B4: SHLB | C4: B/0001185/082-83 | D4: 45886 | E4: Purchase | F4: 221 | G4: =H4/F4 -> 2017.0452 | H4: 445767 | I4: 0 | J4: 0 | K4: 0 | L4: 0 | M4: =M3+H4-L4 -> 445767 | N4: =N3+F4-I4 -> 221 | O4: =IFERROR(M4/N4,0) -> 2017.0452 | P4: 0 | R4: =197.34+8.97 -> 206.31 | S4: 25 | T4: =R4+S4 -> 231.31 | U4: =H4+T4 -> 445998.31 | V4: 0 | W4: 0 | X4: =V4+W4 -> 0 | Y4: 0 | Z4: =K4-X4-Y4 -> 0 | AA4: =I4*AC3 -> 0 | AB4: =AB3+U4-AA4 -> 445998.31 | AC4: =IFERROR(AB4/N4,0) -> 2018.0919 | AD4: =Z4-AA4+Y4 -> 0

Sheet SIBBL
A1: 1. Bhadra | R1: Purchase | V1: Sales | Y1: Capital Gain Tax | Z1: Net Receivables | AA1: Principal Amt AP TAX (Sales Unit) | AB1: TC AP TAX | AC1: WACC AP TAX | AD1: P/L AP TAX
A2: S.No | B2: SYMBOL | C2: Bill No | D2: Txn Date | E2: Txn Type | F2: Purchase QTY | G2: PPPU | H2: Total Purchase Amount | I2: Sales Qty | J2: SPPU | K2: Sales Amt | L2: Principal Cost As per NFRS (In case of Sales) | M2: TC AP NFRS | N2: Unit Sum | O2: WACC AP NFRS | P2: P/L AP NFRS | R2: Purchase Commission | S2: DP Charges | T2: Total Commission on Purchase | U2: Total Investment Cost(Including Comission | V2: Sales Commission | W2: DP Charges | X2: Total Commission on Sales
A3: 1 | B3: SIBBL | D3: 45886 | E3: Opening | F3: 0 | G3: 0 | H3: 0 | K3: 0 | M3: 0 | N3: 0 | O3: 0 | P3: 0 | T3: =R3+S3 -> 0 | U3: =AB3 -> 0 | AB3: =F3*AC3 -> 0
A4: 2 | B4: SIBBL | C4: B/0001278/082-83 | D4: 45886 | E4: Purchase | F4: 500 | G4: =H4/F4 -> 976.2 | H4: 488100 | I4: 0 | J4: 0 | K4: 0 | L4: 0 | M4: =M3+H4-L4 -> 488100 | N4: =N3+F4-I4 -> 500 | O4: =IFERROR(M4/N4,0) -> 976.2 | P4: 0 | R4: =1628.57+73.22 -> 1701.79 | S4: 25 | T4: =R4+S4 -> 1726.79 | U4: =H4+T4 -> 489826.79 | V4: 0 | W4: 0 | X4: =V4+W4 -> 0 | Y4: 0 | Z4: =K4-X4-Y4 -> 0 | AA4: =I4*AC3 -> 0 | AB4: =AB3+U4-AA4 -> 489826.79 | AC4: =IFERROR(AB4/N4,0) -> 979.65358 | AD4: =Z4-AA4+Y4 -> 0

Sheet VLUCL
A1: 1. Bhadra | R1: Purchase | V1: Sales | Y1: Capital Gain Tax | Z1: Net Receivables | AA1: Principal Amt AP TAX (Sales Unit) | AB1: TC AP TAX | AC1: WACC AP TAX | AD1: P/L AP TAX
A2: S.No | B2: SYMBOL | C2: Bill No | D2: Txn Date | E2: Txn Type | F2: Purchase QTY | G2: PPPU | H2: Total Purchase Amount | I2: Sales Qty | J2: SPPU | K2: Sales Amt | L2: Principal Cost As per NFRS (In case of Sales) | M2: TC AP NFRS | N2: Unit Sum | O2: WACC AP NFRS | P2: P/L AP NFRS | R2: Purchase Commission | S2: DP Charges | T2: Total Commission on Purchase | U2: Total Investment Cost(Including Comission | V2: Sales Commission | W2: DP Charges | X2: Total Commission on Sales
A3: 1 | B3: VLUCL | D3: 45886 | E3: Opening | F3: 0 | G3: 0 | H3: 0 | K3: 0 | M3: 0 | N3: 0 | O3: 0 | P3: 0 | T3: =R3+S3 -> 0 | U3: =AB3 -> 0 | AB3: =F3*AC3 -> 0
A4: 2 | B4: VLUCL | C4: B/0001279/082-83 | D4: 45888 | E4: Purchase | F4: 870 | G4: =H4/F4 -> 609.01149 | H4: 529840 | I4: 0 | J4: 0 | K4: 0 | L4: 0 | M4: =M3+H4-L4 -> 529840 | N4: =N3+F4-I4 -> 870 | O4: =IFERROR(M4/N4,0) -> 609.01149 | P4: 0 | R4: =1628.57+73.22 -> 1701.79 | S4: 25 | T4: =R4+S4 -> 1726.79 | U4: =H4+T4 -> 531566.79 | V4: 0 | W4: 0 | X4: =V4+W4 -> 0 | Y4: 0 | Z4: =K4-X4-Y4 -> 0 | AA4: =I4*AC3 -> 0 | AB4: =AB3+U4-AA4 -> 531566.79 | AC4: =IFERROR(AB4/N4,0) -> 610.99631 | AD4: =Z4-AA4+Y4 -> 0
A5: 3 | B5: VLUCL | C5: B/0001702/082-83 | D5: 45908 | E5: Purchase | F5: 100 | G5: =H5/F5 -> 543 | H5: 54300 | I5: 0 | J5: 0 | K5: 0 | L5: 0 | M5: =M4+H5-L5 -> 584140 | N5: =N4+F5-I5 -> 970 | O5: =IFERROR(M5/N5,0) -> 602.20619 | P5: 0 | R5: =195.48+8.14 -> 203.62 | S5: 25 | T5: =R5+S5 -> 228.62 | U5: =H5+T5 -> 54528.62 | V5: 0 | W5: 0 | X5: =V5+W5 -> 0 | Y5: 0 | Z5: =K5-X5-Y5 -> 0 | AA5: =I5*AC4 -> 0 | AB5: =AB4+U5-AA5 -> 586095.41 | AC5: =IFERROR(AB5/N5,0) -> 604.22207 | AD5: =Z5-AA5+Y5 -> 0

Sheet UPCL
A1: 1. Bhadra | R1: Purchase | V1: Sales | Y1: Capital Gain Tax | Z1: Net Receivables | AA1: Principal Amt AP TAX (Sales Unit) | AB1: TC AP TAX | AC1: WACC AP TAX | AD1: P/L AP TAX
A2: S.No | B2: SYMBOL | C2: Bill No | D2: Txn Date | E2: Txn Type | F2: Purchase QTY | G2: PPPU | H2: Total Purchase Amount | I2: Sales Qty | J2: SPPU | K2: Sales Amt | L2: Principal Cost As per NFRS (In case of Sales) | M2: TC AP NFRS | N2: Unit Sum | O2: WACC AP NFRS | P2: P/L AP NFRS | R2: Purchase Commission | S2: DP Charges | T2: Total Commission on Purchase | U2: Total Investment Cost(Including Comission | V2: Sales Commission | W2: DP Charges | X2: Total Commission on Sales
A3: 1 | B3: UPCL | D3: 45886 | E3: Opening | F3: 0 | G3: 0 | H3: 0 | K3: 0 | M3: 0 | N3: 0 | O3: 0 | P3: 0 | T3: =R3+S3 -> 0 | U3: =AB3 -> 0 | AB3: =F3*AC3 -> 0
A4: 2 | B4: UPCL | C4: B/0001280/082-83 | D4: 45888 | E4: Purchase | F4: 450 | G4: =H4/F4 -> 404.22222 | H4: 181900 | I4: 0 | J4: 0 | K4: 0 | L4: 0 | M4: =M3+H4-L4 -> 181900 | N4: =N3+F4-I4 -> 450 | O4: =IFERROR(M4/N4,0) -> 404.22222 | P4: 0 | R4: =1628.57+73.22 -> 1701.79 | S4: 25 | T4: =R4+S4 -> 1726.79 | U4: =H4+T4 -> 183626.79 | V4: 0 | W4: 0 | X4: =V4+W4 -> 0 | Y4: 0 | Z4: =K4-X4-Y4 -> 0 | AA4: =I4*AC3 -> 0 | AB4: =AB3+U4-AA4 -> 183626.79 | AC4: =IFERROR(AB4/N4,0) -> 408.05953 | AD4: =Z4-AA4+Y4 -> 0
A5: 3 | B5: UPCL | C5: B/0001558/082-83 | D5: 45900 | E5: Purchase | F5: 50 | G5: =H5/F5 -> 384 | H5: 19200 | I5: 0 | J5: 0 | K5: 0 | L5: 0 | M5: =M4+H5-L5 -> 201100 | N5: =N4+F5-I5 -> 500 | O5: =IFERROR(M5/N5,0) -> 402.2 | P5: 0 | R5: =69.12+2.88 -> 72 | S5: 25 | T5: =R5+S5 -> 97 | U5: =H5+T5 -> 19297 | V5: 0 | W5: 0 | X5: =V5+W5 -> 0 | Y5: 0 | Z5: =K5-X5-Y5 -> 0 | AA5: =I5*AC4 -> 0 | AB5: =AB4+U5-AA5 -> 202923.79 | AC5: =IFERROR(AB5/N5,0) -> 405.84758 | AD5: =Z5-AA5+Y5 -> 0

Sheet USLB
A1: 1. Bhadra | R1: Purchase | V1: Sales | Y1: Capital Gain Tax | Z1: Net Receivables | AA1: Principal Amt AP TAX (Sales Unit) | AB1: TC AP TAX | AC1: WACC AP TAX | AD1: P/L AP TAX
A2: S.No | B2: SYMBOL | C2: Bill No | D2: Txn Date | E2: Txn Type | F2: Purchase QTY | G2: PPPU | H2: Total Purchase Amount | I2: Sales Qty | J2: SPPU | K2: Sales Amt | L2: Principal Cost As per NFRS (In case of Sales) | M2: TC AP NFRS | N2: Unit Sum | O2: WACC AP NFRS | P2: P/L AP NFRS | R2: Purchase Commission | S2: DP Charges | T2: Total Commission on Purchase | U2: Total Investment Cost(Including Comission | V2: Sales Commission | W2: DP Charges | X2: Total Commission on Sales
A3: 1 | B3: NHDL | D3: 45886 | E3: Opening | F3: 0 | G3: 0 | H3: 0 | K3: 0 | M3: 0 | N3: 0 | O3: 0 | P3: 0 | T3: =R3+S3 -> 0 | U3: =AB3 -> 0 | AB3: =F3*AC3 -> 0
A4: 2 | B4: NHDL | C4: B/0001701/082-83 | D4: 45908 | E4: Purchase | F4: 100 | G4: =H4/F4 -> 1920 | H4: 192000 | I4: 0 | J4: 0 | K4: 0 | L4: 0 | M4: =M3+H4-L4 -> 192000 | N4: =N3+F4-I4 -> 100 | O4: =IFERROR(M4/N4,0) -> 1920 | P4: 0 | R4: =633.6+28.8 -> 662.4 | S4: 25 | T4: =R4+S4 -> 687.4 | U4: =H4+T4 -> 192687.4 | V4: 0 | W4: 0 | X4: =V4+W4 -> 0 | Y4: 0 | Z4: =K4-X4-Y4 -> 0 | AA4: =I4*AC3 -> 0 | AB4: =AB3+U4-AA4 -> 192687.4 | AC4: =IFERROR(AB4/N4,0) -> 1926.874 | AD4: =Z4-AA4+Y4 -> 0

Sheet NHDL
A1: 1. Bhadra | R1: Purchase | V1: Sales | Y1: Capital Gain Tax | Z1: Net Receivables | AA1: Principal Amt AP TAX (Sales Unit) | AB1: TC AP TAX | AC1: WACC AP TAX | AD1: P/L AP TAX
A2: S.No | B2: SYMBOL | C2: Bill No | D2: Txn Date | E2: Txn Type | F2: Purchase QTY | G2: PPPU | H2: Total Purchase Amount | I2: Sales Qty | J2: SPPU | K2: Sales Amt | L2: Principal Cost As per NFRS (In case of Sales) | M2: TC AP NFRS | N2: Unit Sum | O2: WACC AP NFRS | P2: P/L AP NFRS | R2: Purchase Commission | S2: DP Charges | T2: Total Commission on Purchase | U2: Total Investment Cost(Including Comission | V2: Sales Commission | W2: DP Charges | X2: Total Commission on Sales
A3: 1 | B3: NHDL | D3: 45886 | E3: Opening | F3: 0 | G3: 0 | H3: 0 | K3: 0 | M3: 0 | N3: 0 | O3: 0 | P3: 0 | T3: =R3+S3 -> 0 | U3: =AB3 -> 0 | AB3: =F3*AC3 -> 0
A4: 2 | B4: NHDL | C4: B/0001700/082-83 | D4: 45908 | E4: Purchase | F4: 200 | G4: =H4/F4 -> 670 | H4: 134000 | I4: 0 | J4: 0 | K4: 0 | L4: 0 | M4: =M3+H4-L4 -> 134000 | N4: =N3+F4-I4 -> 200 | O4: =IFERROR(M4/N4,0) -> 670 | P4: 0 | R4: =442.2+20.1 -> 462.3 | S4: 25 | T4: =R4+S4 -> 487.3 | U4: =H4+T4 -> 134487.3 | V4: 0 | W4: 0 | X4: =V4+W4 -> 0 | Y4: 0 | Z4: =K4-X4-Y4 -> 0 | AA4: =I4*AC3 -> 0 | AB4: =AB3+U4-AA4 -> 134487.3 | AC4: =IFERROR(AB4/N4,0) -> 672.4365 | AD4: =Z4-AA4+Y4 -> 0

Sheet GILB
A1: 1. Bhadra | R1: Purchase | V1: Sales | Y1: Capital Gain Tax | Z1: Net Receivables | AA1: Principal Amt AP TAX (Sales Unit) | AB1: TC AP TAX | AC1: WACC AP TAX | AD1: P/L AP TAX
A2: S.No | B2: SYMBOL | C2: Bill No | D2: Txn Date | E2: Txn Type | F2: Purchase QTY | G2: PPPU | H2: Total Purchase Amount | I2: Sales Qty | J2: SPPU | K2: Sales Amt | L2: Principal Cost As per NFRS (In case of Sales) | M2: TC AP NFRS | N2: Unit Sum | O2: WACC AP NFRS | P2: P/L AP NFRS | R2: Purchase Commission | S2: DP Charges | T2: Total Commission on Purchase | U2: Total Investment Cost(Including Comission | V2: Sales Commission | W2: DP Charges | X2: Total Commission on Sales
A3: 1 | B3: GILB | D3: 45886 | E3: Opening | F3: 0 | G3: 0 | H3: 0 | K3: 0 | M3: 0 | N3: 0 | O3: 0 | P3: 0 | T3: =R3+S3 -> 0 | U3: =AB3 -> 0 | AB3: =F3*AC3 -> 0
A4: 2 | B4: GILB | C4: B/0001615/082-83 | D4: 45902 | E4: Purchase | F4: 700 | G4: =H4/F4 -> 1291.5957 | H4: 904117 | I4: 0 | J4: 0 | K4: 0 | L4: 0 | M4: =M3+H4-L4 -> 904117 | N4: =N3+F4-I4 -> 700 | O4: =IFERROR(M4/N4,0) -> 1291.5957 | P4: 0 | R4: =2862.22+135.63 -> 2997.85 | S4: 25 | T4: =R4+S4 -> 3022.85 | U4: =H4+T4 -> 907139.85 | V4: 0 | W4: 0 | X4: =V4+W4 -> 0 | Y4: 0 | Z4: =K4-X4-Y4 -> 0 | AA4: =I4*AC3 -> 0 | AB4: =AB3+U4-AA4 -> 907139.85 | AC4: =IFERROR(AB4/N4,0) -> 1295.9141 | AD4: =Z4-AA4+Y4 -> 0
A5: 3 | B5: GILB | C5: B/0001699/082-83 | D5: 45908 | E5: Purchase | F5: 500 | G5: =H5/F5 -> 1238.17 | H5: 619085 | I5: 0 | J5: 0 | K5: 0 | L5: 0 | M5: =M4+H5-L5 -> 1523202 | N5: =N4+F5-I5 -> 1200 | O5: =IFERROR(M5/N5,0) -> 1269.335 | P5: 0 | R5: 2142.25 | S5: 25 | T5: =R5+S5 -> 2167.25 | U5: =H5+T5 -> 621252.25 | V5: 0 | W5: 0 | X5: =V5+W5 -> 0 | Y5: 0 | Z5: =K5-X5-Y5 -> 0 | AA5: =I5*AC4 -> 0 | AB5: =AB4+U5-AA5 -> 1528392.1 | AC5: =IFERROR(AB5/N5,0) -> 1273.6601 | AD5: =Z5-AA5+Y5 -> 0

Sheet NMFBS
A1: 1. Bhadra | R1: Purchase | V1: Sales | Y1: Capital Gain Tax | Z1: Net Receivables | AA1: Principal Amt AP TAX (Sales Unit) | AB1: TC AP TAX | AC1: WACC AP TAX | AD1: P/L AP TAX
A2: S.No | B2: SYMBOL | C2: Bill No | D2: Txn Date | E2: Txn Type | F2: Purchase QTY | G2: PPPU | H2: Total Purchase Amount | I2: Sales Qty | J2: SPPU | K2: Sales Amt | L2: Principal Cost As per NFRS (In case of Sales) | M2: TC AP NFRS | N2: Unit Sum | O2: WACC AP NFRS | P2: P/L AP NFRS | R2: Purchase Commission | S2: DP Charges | T2: Total Commission on Purchase | U2: Total Investment Cost(Including Comission | V2: Sales Commission | W2: DP Charges | X2: Total Commission on Sales
A3: 1 | B3: NMFBS | D3: 45886 | E3: Opening | F3: 0 | G3: 0 | H3: 0 | K3: 0 | M3: 0 | N3: 0 | O3: 0 | P3: 0 | T3: =R3+S3 -> 0 | U3: =AB3 -> 0 | AB3: =F3*AC3 -> 0
A4: 2 | B4: NMFBS | C4: B/0001289/082-83 | D4: 45889 | E4: Purchase | F4: 45 | G4: =H4/F4 -> 1301 | H4: 58545 | I4: 0 | J4: 0 | K4: 0 | L4: 0 | M4: =M3+H4-L4 -> 58545 | N4: =N3+F4-I4 -> 45 | O4: =IFERROR(M4/N4,0) -> 1301 | P4: 0 | R4: =193.2+8.78 -> 201.98 | S4: 25 | T4: =R4+S4 -> 226.98 | U4: =H4+T4 -> 58771.98 | V4: 0 | W4: 0 | X4: =V4+W4 -> 0 | Y4: 0 | Z4: =K4-X4-Y4 -> 0 | AA4: =I4*AC3 -> 0 | AB4: =AB3+U4-AA4 -> 58771.98 | AC4: =IFERROR(AB4/N4,0) -> 1306.044 | AD4: =Z4-AA4+Y4 -> 0
A5: 3 | B5: NMFBS | C5: B/0001320/082-83 | D5: 45890 | E5: Purchase | F5: 485 | G5: =H5/F5 -> 1309.2887 | H5: 635005 | I5: 0 | J5: 0 | K5: 0 | L5: 0 | M5: =M4+H5-L5 -> 693550 | N5: =N4+F5-I5 -> 530 | O5: =IFERROR(M5/N5,0) -> 1308.5849 | P5: 0 | R5: =2095.52+95.25 -> 2190.77 | S5: 25 | T5: =R5+S5 -> 2215.77 | U5: =H5+T5 -> 637220.77 | V5: 0 | W5: 0 | X5: =V5+W5 -> 0 | Y5: 0 | Z5: =K5-X5-Y5 -> 0 | AA5: =I5*AC4 -> 0 | AB5: =AB4+U5-AA5 -> 695992.75 | AC5: =IFERROR(AB5/N5,0) -> 1313.1939 | AD5: =Z5-AA5+Y5 -> 0

Sheet SMPDA
A1: 1. Bhadra | R1: Purchase | V1: Sales | Y1: Capital Gain Tax | Z1: Net Receivables | AA1: Principal Amt AP TAX (Sales Unit) | AB1: TC AP TAX | AC1: WACC AP TAX | AD1: P/L AP TAX
A2: S.No | B2: SYMBOL | C2: Bill No | D2: Txn Date | E2: Txn Type | F2: Purchase QTY | G2: PPPU | H2: Total Purchase Amount | I2: Sales Qty | J2: SPPU | K2: Sales Amt | L2: Principal Cost As per NFRS (In case of Sales) | M2: TC AP NFRS | N2: Unit Sum | O2: WACC AP NFRS | P2: P/L AP NFRS | R2: Purchase Commission | S2: DP Charges | T2: Total Commission on Purchase | U2: Total Investment Cost(Including Comission | V2: Sales Commission | W2: DP Charges | X2: Total Commission on Sales
A3: 1 | B3: SMPDA | D3: 45886 | E3: Opening | F3: 0 | G3: 0 | H3: 0 | K3: 0 | M3: 0 | N3: 0 | O3: 0 | P3: 0 | T3: =R3+S3 -> 0 | U3: =AB3 -> 0 | AB3: =F3*AC3 -> 0
A4: 2 | B4: SMPDA | C4: B/0001350/082-83 | D4: 45893 | E4: Purchase | F4: 390 | G4: =H4/F4 -> 913.84615 | H4: 356400 | I4: 0 | J4: 0 | K4: 0 | L4: 0 | M4: =M3+H4-L4 -> 356400 | N4: =N3+F4-I4 -> 390 | O4: =IFERROR(M4/N4,0) -> 913.84615 | P4: 0 | R4: =193.2+8.78 -> 201.98 | S4: 25 | T4: =R4+S4 -> 226.98 | U4: =H4+T4 -> 356626.98 | V4: 0 | W4: 0 | X4: =V4+W4 -> 0 | Y4: 0 | Z4: =K4-X4-Y4 -> 0 | AA4: =I4*AC3 -> 0 | AB4: =AB3+U4-AA4 -> 356626.98 | AC4: =IFERROR(AB4/N4,0) -> 914.42815 | AD4: =Z4-AA4+Y4 -> 0
A5: 3 | B5: SMPDA | C5: S/0007392/082-83 | D5: 45897 | E5: Sales | I5: 390 | J5: =K5/I5 -> 946 | K5: 368940 | L5: =I5*O4 -> 356400 | M5: =M4+H5-L5 -> 0 | N5: =N4+F5-I5 -> 0 | O5: =-IFERROR(M5/N5,0) -> 0 | P5: =K5-L5 -> 12540 | V5: =1217.5+55.34 -> 1272.84 | W5: 25 | X5: =V5+W5 -> 1297.84 | Y5: 992.91 | Z5: =K5-X5-Y5 -> 366649.25 | AA5: =I5*AC4 -> 356626.98 | AB5: =AB4+U5-AA5 -> 0 | AC5: 917.21 | AD5: =Y5+Z5-AA5 -> 11015.18

Sheet SHPC
A1: Jyoti Capital Limited
A2: Kamalpokhari, Kathmandu
A3: JCL Portfolio Statement
A5: 1. Shrawan | R5: Purchase | V5: Sales | Y5: Capital Gain Tax | Z5: Net Receivables | AA5: Principal Amt AP TAX (Sales Unit) | AB5: TC AP TAX | AC5: WACC AP TAX | AD5: P/L AP TAX
A6: S.No | B6: SYMBOL | C6: Bill No | D6: Txn Date | E6: Txn Type | F6: Purchase QTY | G6: PPPU | H6: Total Purchase Amount | I6: Sales Qty | J6: SPPU | K6: Sales Amt | L6: Principal Cost As per NFRS (In case of Sales) | M6: TC AP NFRS | N6: Unit Sum | O6: WACC AP NFRS | P6: P/L AP NFRS | R6: Purchase Commission | S6: DP Charges | T6: Total Commission on Purchase | U6: Investment Cost (Including Comission) | V6: Sales Commission | W6: DP Charges | X6: Total Commission on Sales
A7: 1 | B7: SHPC | D7: 45855 | E7: Opening | F7: 900 | G7: 626.91 | H7: =Table24283028293031[[#This Row],[PPPU]]*Table24283028293031[[#This Row],[Purchase QTY]] -> 564219 | K7: =Table24283028293031[[#This Row],[Sales Qty]]*Table24283028293031[[#This Row],[SPPU]] -> 0 | M7: =Table24283028293031[[#This Row],[Total Purchase Amount]] -> 564219 | N7: =IF(Table24283028293031[[#This Row],[Txn Type]]="opening",Table24283028293031[[#This Row],[Purchase QTY]],"Error") -> 900 | O7: =IFERROR(Table24283028293031[[#This Row],[TC AP NFRS]]/Table24283028293031[[#This Row],[Unit Sum]],0) -> 626.91 | P7: =Table24283028293031[[#This Row],[Sales Amt]]-Table24283028293031[[#This Row],[Principal Cost As per NFRS (In case of Sales)]] -> 0 | T7: =R7+S7 -> 0 | U7: =AB7 -> 546768 | X7: =V7+W7 -> 0 | AB7: =Table24283028293031[[#This Row],[Purchase QTY]]*AC7 -> 546768 | AC7: 607.52
A8: 2 | B8: SHPC | C8: S/0002387/082-083 | D8: 45500 | E8: sale | F8: 0 | G8: =IF(Table24283028293031[[#This Row],[SPPU]]>0,0,Table24283028293031[[#This Row],[Total Purchase Amount]]/Table24283028293031[[#This Row],[Purchase QTY]]) -> 0 | H8: 0 | I8: 900 | J8: =Table24283028293031[[#This Row],[Sales Amt]]/Table24283028293031[[#This Row],[Sales Qty]] -> 647.77778 | K8: 583000 | L8: =Table24283028293031[[#This Row],[Sales Qty]]*O7 -> 564219 | M8: =M7+Table24283028293031[[#This Row],[Total Purchase Amount]]-Table24283028293031[[#This Row],[Principal Cost As per NFRS (In case of Sales)]] -> 0 | N8: =N7+Table24283028293031[[#This Row],[Purchase QTY]]-Table24283028293031[[#This Row],[Sales Qty]] -> 0 | O8: =IFERROR(Table24283028293031[[#This Row],[TC AP NFRS]]/Table24283028293031[[#This Row],[Unit Sum]],0) -> 0 | P8: =Table24283028293031[[#This Row],[Sales Amt]]-Table24283028293031[[#This Row],[Principal Cost As per NFRS (In case of Sales)]] -> 18781 | T8: =R8+S8 -> 0 | U8: =T8+Table24283028293031[[#This Row],[Total Purchase Amount]] -> 0 | V8: =1923.9+87.45 -> 2011.35 | W8: 25 | X8: =V8+W8 -> 2036.35 | Y8: 3419.75 | Z8: =Table24283028293031[[#This Row],[Sales Amt]]-X8-Y8 -> 577543.9 | AA8: =Table24283028293031[[#This Row],[Sales Qty]]*AC7 -> 546768 | AB8: =AB7+U8-AA8 -> 0 | AC8: =IFERROR(AB8/Table24283028293031[[#This Row],[Unit Sum]],0) -> 0 | AD8: =Z8+Y8-AA8 -> 34195.65
A9: Total | F9: =SUM(INDIRECT("f4:f"&ROW()-1)) -> 900 | G9: =Table24283028293031[[#This Row],[Total Purchase Amount]]/Table24283028293031[[#This Row],[Purchase QTY]] -> 626.91 | H9: =SUM(INDIRECT("h4:h"&ROW()-1)) -> 564219 | I9: =SUM(INDIRECT("i4:i"&ROW()-1)) -> 900 | J9: =Table24283028293031[[#This Row],[Sales Amt]]/Table24283028293031[[#This Row],[Sales Qty]] -> 647.77778 | K9: =SUM(INDIRECT("k4:k"&ROW()-1)) -> 583000 | L9: =SUBTOTAL(109,L7:L8) -> 564219 | M9: =Table24283028293031[[#This Row],[Total Purchase Amount]]-Table24283028293031[[#This Row],[Principal Cost As per NFRS (In case of Sales)]] -> 0 | N9: =Table24283028293031[[#This Row],[Purchase QTY]]-Table24283028293031[[#This Row],[Sales Qty]] -> 0 | O9: =IFERROR(Table24283028293031[[#This Row],[Unit Sum]]/Table24283028293031[[#This Row],[TC AP NFRS]],0) -> 0 | P9: =SUM(P7:P8) -> 18781 | R9: =SUM(R7:R8) -> 0 | S9: =SUM(S7:S8) -> 0 | T9: =SUM(T7:T8) -> 0 | U9: =SUM(U7:U8) -> 546768 | V9: =SUM(V7:V8) -> 2011.35 | W9: =SUM(W7:W8) -> 25 | X9: =SUM(X7:X8) -> 2036.35 | Y9: =SUM(Y7:Y8) -> 3419.75 | ... AA9: =SUM(AA7:AA8) -> 546768 | AB9: =U9-AA9 -> 0 | AC9: =IFERROR(AB9/Table24283028293031[[#This Row],[Unit Sum]],0) -> 0 | AD9: =SUM(AD7:AD8) -> 34195.65
G10: =Table24283028293031[[#This Row],[Total Purchase Amount]]/Table24283028293031[[#This Row],[Purchase QTY]] -> #DIV/0! | K10: =Table24283028293031[[#This Row],[Sales Qty]]*Table24283028293031[[#This Row],[SPPU]] -> 0 | O10: =Table24283028293031[[#This Row],[TC AP NFRS]]/Table24283028293031[[#This Row],[Unit Sum]] -> #DIV/0!
A11: 2. Bhadra | R11: Purchase | V11: Sales | Y11: Capital Gain Tax | Z11: Net Receivables | AA11: Principal Amt AP TAX (Sales Unit) | AB11: TC AP TAX | AC11: WACC AP TAX | AD11: P/L AP TAX
A12: S.No | B12: SYMBOL | C12: Bill No | D12: Txn Date | E12: Txn Type | F12: Purchase QTY | G12: PPPU | H12: Total Purchase Amount | I12: Sales Qty | J12: SPPU | K12: Sales Amt | L12: Principal Cost As per NFRS (In case of Sales) | M12: TC AP NFRS | N12: Unit Sum | O12: WACC AP NFRS | P12: P/L AP NFRS | R12: Purchase Commission | S12: DP Charges | T12: Total Commission on Purchase | U12: Total Investment Cost(Including Comission | V12: Sales Commission | W12: DP Charges | X12: Total Commission on Sales
A13: 1 | B13: SHPC | D13: 45886 | E13: Opening | F13: 900 | G13: 626.91 | H13: 564219 | I13: 900 | J13: 647.77778 | K13: 583000 | L13: 564219 | M13: 0 | N13: 0 | O13: 0 | P13: 18781 | R13: 0 | S13: 0 | T13: 0 | U13: 546768 | V13: 2011.35 | W13: 25 | X13: 2036.35 | Y13: 3419.75 | Z13: 577543.9 | AA13: 546768 | AB13: 0 | AC13: 0 | AD13: 34195.65

Sheet SPIL
A1: Jyoti Capital Limited
A2: Kamalpokhari, Kathmandu
A3: JCL Portfolio Statement
A5: 1. Shrawan | R5: Purchase | V5: Sales | Y5: Capital Gain Tax | Z5: Net Receivables | AA5: Principal Amt AP TAX (Sales Unit) | AB5: TC AP TAX | AC5: WACC AP TAX | AD5: P/L AP TAX
A6: S.No | B6: SYMBOL | C6: Bill No | D6: Txn Date | E6: Txn Type | F6: Purchase QTY | G6: PPPU | H6: Total Purchase Amount | I6: Sales Qty | J6: SPPU | K6: Sales Amt | L6: Principal Cost As per NFRS (In case of Sales) | M6: TC AP NFRS | N6: Unit Sum | O6: WACC AP NFRS | P6: P/L AP NFRS | R6: Purchase Commission | S6: DP Charges | T6: Total Commission on Purchase | U6: Total Investment Cost(Including Comission | V6: Sales Commission | W6: DP Charges | X6: Total Commission on Sales
A7: 1 | B7: SPIL | D7: 45855 | E7: Opening | F7: 0 | G7: 0 | H7: =Table242830282930[[#This Row],[PPPU]]*Table242830282930[[#This Row],[Purchase QTY]] -> 0 | K7: =Table242830282930[[#This Row],[Sales Qty]]*Table242830282930[[#This Row],[SPPU]] -> 0 | M7: =Table242830282930[[#This Row],[Total Purchase Amount]] -> 0 | N7: =IF(Table242830282930[[#This Row],[Txn Type]]="opening",Table242830282930[[#This Row],[Purchase QTY]],"Error") -> 0 | O7: =IFERROR(Table242830282930[[#This Row],[TC AP NFRS]]/Table242830282930[[#This Row],[Unit Sum]],0) -> 0 | P7: =Table242830282930[[#This Row],[Sales Amt]]-Table242830282930[[#This Row],[Principal Cost As per NFRS (In case of Sales)]] -> 0 | T7: =R7+S7 -> 0 | U7: =AB7 -> 0 | AB7: =F7*AC7 -> 0
A8: 2 | B8: SPIL | C8: B/0000509/082-83 | D8: 45500 | E8: purchase | F8: 1500 | G8: =IF(Table242830282930[[#This Row],[SPPU]]>0,0,Table242830282930[[#This Row],[Total Purchase Amount]]/Table242830282930[[#This Row],[Purchase QTY]]) -> 866.66667 | H8: 1300000 | I8: 0 | J8: 0 | K8: 0 | L8: =Table242830282930[[#This Row],[Sales Qty]]*O7 -> 0 | M8: =M7+Table242830282930[[#This Row],[Total Purchase Amount]]-Table242830282930[[#This Row],[Principal Cost As per NFRS (In case of Sales)]] -> 1300000 | N8: =N7+Table242830282930[[#This Row],[Purchase QTY]]-Table242830282930[[#This Row],[Sales Qty]] -> 1500 | O8: =IFERROR(Table242830282930[[#This Row],[TC AP NFRS]]/Table242830282930[[#This Row],[Unit Sum]],0) -> 866.66667 | P8: =Table242830282930[[#This Row],[Sales Amt]]-Table242830282930[[#This Row],[Principal Cost As per NFRS (In case of Sales)]] -> 0 | R8: =195+4177.89 -> 4372.89 | S8: 25 | T8: =R8+S8 -> 4397.89 | U8: =H8+T8 -> 1304397.9 | V8: 0 | W8: 0 | X8: =V8+W8 -> 0 | Y8: 0 | Z8: =K8-X8-Y8 -> 0 | AA8: =I8*AC7 -> 0 | AB8: =AB7+U8-AA8 -> 1304397.9 | AC8: =IFERROR(AB8/N8,0) -> 869.59859 | AD8: =Z8-AA8+Y8 -> 0
A9: =A8+1 -> 3 | G9: =Table242830282930[[#This Row],[Total Purchase Amount]]/Table242830282930[[#This Row],[Purchase QTY]] -> #DIV/0! | I9: 0 | K9: =Table242830282930[[#This Row],[Sales Qty]]*Table242830282930[[#This Row],[SPPU]] -> 0 | L9: =Table242830282930[[#This Row],[Sales Qty]]*O8 -> 0 | M9: =M8+Table242830282930[[#This Row],[Total Purchase Amount]]-Table242830282930[[#This Row],[Principal Cost As per NFRS (In case of Sales)]] -> 1300000 | N9: =N8+Table242830282930[[#This Row],[Purchase QTY]]-Table242830282930[[#This Row],[Sales Qty]] -> 1500 | O9: =Table242830282930[[#This Row],[TC AP NFRS]]/Table242830282930[[#This Row],[Unit Sum]] -> 866.66667 | P9: =Table242830282930[[#This Row],[Sales Amt]]-Table242830282930[[#This Row],[Principal Cost As per NFRS (In case of Sales)]] -> 0 | R9: 0 | T9: =R9+S9 -> 0 | U9: =H9+T9 -> 0 | V9: 0 | W9: 0 | X9: =V9+W9 -> 0 | Y9: 0 | Z9: =K9-X9-Y9 -> 0 | AA9: =I9*AC8 -> 0 | AB9: =AB8+U9-AA9 -> 1304397.9 | AC9: =IFERROR(AB9/N9,0) -> 869.59859 | AD9: =Z9-AA9+Y9 -> 0
A10: =A9+1 -> 4 | G10: =IF(Table242830282930[[#This Row],[SPPU]]>0,0,Table242830282930[[#This Row],[Total Purchase Amount]]/Table242830282930[[#This Row],[Purchase QTY]]) -> #DIV/0! | I10: 0 | K10: =Table242830282930[[#This Row],[Sales Qty]]*Table242830282930[[#This Row],[SPPU]] -> 0 | L10: =Table242830282930[[#This Row],[Sales Qty]]*O9 -> 0 | M10: =M9+Table242830282930[[#This Row],[Total Purchase Amount]]-Table242830282930[[#This Row],[Principal Cost As per NFRS (In case of Sales)]] -> 1300000 | N10: =N9+Table242830282930[[#This Row],[Purchase QTY]]-Table242830282930[[#This Row],[Sales Qty]] -> 1500 | O10: =IFERROR(Table242830282930[[#This Row],[TC AP NFRS]]/Table242830282930[[#This Row],[Unit Sum]],0) -> 866.66667 | P10: =Table242830282930[[#This Row],[Sales Amt]]-Table242830282930[[#This Row],[Principal Cost As per NFRS (In case of Sales)]] -> 0 | R10: 0 | T10: =R10+S10 -> 0 | U10: =H10+T10 -> 0 | V10: 0 | W10: 0 | X10: =V10+W10 -> 0 | Y10: 0 | Z10: =K10-X10-Y10 -> 0 | AA10: =I10*AC9 -> 0 | AB10: =AB9+U10-AA10 -> 1304397.9 | AC10: =IFERROR(AB10/N10,0) -> 869.59859 | AD10: =Z10-AA10+Y10 -> 0
A11: =A10+1 -> 5 | G11: =Table242830282930[[#This Row],[Total Purchase Amount]]/Table242830282930[[#This Row],[Purchase QTY]] -> #DIV/0! | K11: =Table242830282930[[#This Row],[Sales Qty]]*Table242830282930[[#This Row],[SPPU]] -> 0 | M11: =M10+Table242830282930[[#This Row],[Total Purchase Amount]]-Table242830282930[[#This Row],[Principal Cost As per NFRS (In case of Sales)]] -> 1300000 | N11: =N10+Table242830282930[[#This Row],[Purchase QTY]]-Table242830282930[[#This Row],[Sales Qty]] -> 1500 | O11: =Table242830282930[[#This Row],[TC AP NFRS]]/Table242830282930[[#This Row],[Unit Sum]] -> 866.66667 | P11: =Table242830282930[[#This Row],[Sales Amt]]-Table242830282930[[#This Row],[Principal Cost As per NFRS (In case of Sales)]] -> 0 | R11: 0 | T11: =R11+S11 -> 0 | U11: =H11+T11 -> 0 | V11: 0 | W11: 0 | X11: =V11+W11 -> 0 | Y11: 0 | Z11: =K11-X11-Y11 -> 0 | AA11: =I11*AC10 -> 0 | AB11: =AB10+U11-AA11 -> 1304397.9 | AC11: =IFERROR(AB11/N11,0) -> 869.59859 | AD11: =Z11-AA11+Y11 -> 0
A12: Total | F12: =SUM(INDIRECT("f4:f"&ROW()-1)) -> 1500 | G12: =Table242830282930[[#This Row],[Total Purchase Amount]]/Table242830282930[[#This Row],[Purchase QTY]] -> 866.66667 | H12: =SUM(INDIRECT("h4:h"&ROW()-1)) -> 1300000 | I12: =SUM(INDIRECT("i4:i"&ROW()-1)) -> 0 | J12: =Table242830282930[[#This Row],[Sales Amt]]/Table242830282930[[#This Row],[Sales Qty]] -> #DIV/0! | K12: =SUM(INDIRECT("k4:k"&ROW()-1)) -> 0 | M12: =Table242830282930[[#This Row],[Total Purchase Amount]]-Table242830282930[[#This Row],[Principal Cost As per NFRS (In case of Sales)]] -> 1300000 | N12: =Table242830282930[[#This Row],[Purchase QTY]]-Table242830282930[[#This Row],[Sales Qty]] -> 1500 | O12: =Table242830282930[[#This Row],[TC AP NFRS]]/Table242830282930[[#This Row],[Unit Sum]] -> 866.66667 | P12: =SUM(P7:P8) -> 0 | R12: =SUM(R7:R11) -> 4372.89 | S12: =SUM(S7:S11) -> 25 | T12: =SUM(T7:T11) -> 4397.89 | U12: =SUM(U7:U11) -> 1304397.9 | V12: =SUM(V7:V11) -> 0 | W12: =SUM(W7:W11) -> 0 | X12: =SUM(X7:X11) -> 0 | Y12: =SUM(Y7:Y11) -> 0 | ... AA12: =SUM(AA7:AA11) -> 0 | AB12: =U12-AA12 -> 1304397.9 | AC12: =IFERROR(AB12/N12,0) -> 869.59859 | AD12: =SUM(AD7:AD11) -> 0
A15: 2. Bhadra | R15: Purchase | V15: Sales | Y15: Capital Gain Tax | Z15: Net Receivables | AA15: Principal Amt AP TAX (Sales Unit) | AB15: TC AP TAX | AC15: WACC AP TAX | AD15: P/L AP TAX
A16: S.No | B16: SYMBOL | C16: Bill No | D16: Txn Date | E16: Txn Type | F16: Purchase QTY | G16: PPPU | H16: Total Purchase Amount | I16: Sales Qty | J16: SPPU | K16: Sales Amt | L16: Principal Cost As per NFRS (In case of Sales) | M16: TC AP NFRS | N16: Unit Sum | O16: WACC AP NFRS | P16: P/L AP NFRS | R16: Purchase Commission | S16: DP Charges | T16: Total Commission on Purchase | U16: Total Investment Cost(Including Comission | V16: Sales Commission | W16: DP Charges | X16: Total Commission on Sales
A17: 1 | B17: SPIL | D17: 45886 | E17: Opening | F17: 1500 | G17: 866.66667 | H17: 1300000 | M17: 1300000 | N17: 1500 | O17: 866.66667 | R17: 4372.89 | S17: 25 | T17: 4397.89 | U17: 1304397.9 | AB17: 1304397.9 | AC17: 869.59859

Sheet TAMOR
A1: 1. Bhadra | R1: Purchase | V1: Sales | Y1: Capital Gain Tax | Z1: Net Receivables | AA1: Principal Amt AP TAX (Sales Unit) | AB1: TC AP TAX | AC1: WACC AP TAX | AD1: P/L AP TAX
A2: S.No | B2: SYMBOL | C2: Bill No | D2: Txn Date | E2: Txn Type | F2: Purchase QTY | G2: PPPU | H2: Total Purchase Amount | I2: Sales Qty | J2: SPPU | K2: Sales Amt | L2: Principal Cost As per NFRS (In case of Sales) | M2: TC AP NFRS | N2: Unit Sum | O2: WACC AP NFRS | P2: P/L AP NFRS | R2: Purchase Commission | S2: DP Charges | T2: Total Commission on Purchase | U2: Total Investment Cost(Including Comission | V2: Sales Commission | W2: DP Charges | X2: Total Commission on Sales
A3: 1 | B3: TAMOR | D3: 45886 | E3: Opening | F3: 0 | G3: 0 | H3: 0 | K3: 0 | M3: 0 | N3: 0 | O3: 0 | P3: 0 | T3: =R3+S3 -> 0 | U3: =AB3 -> 0 | AB3: =F3*AC3 -> 0
A4: 2 | B4: TAMOR | C4: B/0001553/082-83 | D4: 45900 | E4: Purchase | F4: 210 | G4: =H4/F4 -> 507.8 | H4: 106638 | I4: 0 | J4: 0 | K4: 0 | L4: 0 | M4: =M3+H4-L4 -> 106638 | N4: =N3+F4-I4 -> 210 | O4: =IFERROR(M4/N4,0) -> 507.8 | P4: 0 | R4: =368.66+15.99 -> 384.65 | S4: 25 | T4: =R4+S4 -> 409.65 | U4: =H4+T4 -> 107047.65 | V4: 0 | W4: 0 | X4: =V4+W4 -> 0 | Y4: 0 | Z4: =K4-X4-Y4 -> 0 | AA4: =I4*AC2 -> 0 | AB4: =AB3+U4-AA4 -> 107047.65 | AC4: =IFERROR(AB4/N4,0) -> 509.75071 | AD4: =Z4-AA4+Y4 -> 0
A5: 3 | B5: . | C5: B/0001617/082-83 | D5: 45902 | E5: Purchase | F5: 200 | G5: =H5/F5 -> 465 | H5: 93000 | I5: 0 | J5: 0 | K5: 0 | L5: 0 | M5: =M4+H5-L5 -> 199638 | N5: =N4+F5-I5 -> 410 | O5: =IFERROR(M5/N5,0) -> 486.92195 | P5: 0 | R5: =306.9+13.95 -> 320.85 | S5: 25 | T5: =R5+S5 -> 345.85 | U5: =H5+T5 -> 93345.85 | V5: 0 | W5: 0 | X5: =V5+W5 -> 0 | Y5: 0 | Z5: =K5-X5-Y5 -> 0 | AA5: =I5*AC3 -> 0 | AB5: =AB4+U5-AA5 -> 200393.5 | AC5: =IFERROR(AB5/N5,0) -> 488.76463 | AD5: =Z5-AA5+Y5 -> 0
A6: 4 | B6: TAMOR | C6: B/0001648/082-83 | D6: 45904 | E6: Purchase | F6: 500 | G6: =H6/F6 -> 457 | H6: 228500 | I6: 0 | J6: 0 | K6: 0 | L6: 0 | M6: =M5+H6-L6 -> 428138 | N6: =N5+F6-I6 -> 910 | O6: =IFERROR(M6/N6,0) -> 470.48132 | P6: 0 | R6: =754.05+34.28 -> 788.33 | S6: 25 | T6: =R6+S6 -> 813.33 | U6: =H6+T6 -> 229313.33 | V6: 0 | W6: 0 | X6: =V6+W6 -> 0 | Y6: 0 | Z6: =K6-X6-Y6 -> 0 | AA6: =I6*AC3 -> 0 | AB6: =AB5+U6-AA6 -> 429706.83 | AC6: =IFERROR(AB6/N6,0) -> 472.20531 | AD6: =Z6-AA6+Y6 -> 0

Sheet SNLI
A1: 1. Bhadra | R1: Purchase | V1: Sales | Y1: Capital Gain Tax | Z1: Net Receivables | AA1: Principal Amt AP TAX (Sales Unit) | AB1: TC AP TAX | AC1: WACC AP TAX | AD1: P/L AP TAX
A2: S.No | B2: SYMBOL | C2: Bill No | D2: Txn Date | E2: Txn Type | F2: Purchase QTY | G2: PPPU | H2: Total Purchase Amount | I2: Sales Qty | J2: SPPU | K2: Sales Amt | L2: Principal Cost As per NFRS (In case of Sales) | M2: TC AP NFRS | N2: Unit Sum | O2: WACC AP NFRS | P2: P/L AP NFRS | R2: Purchase Commission | S2: DP Charges | T2: Total Commission on Purchase | U2: Total Investment Cost(Including Comission | V2: Sales Commission | W2: DP Charges | X2: Total Commission on Sales
A3: 1 | B3: SNLI | D3: 45886 | E3: Opening | F3: 0 | G3: 0 | H3: 0 | K3: 0 | M3: 0 | N3: 0 | O3: 0 | P3: 0 | T3: =R3+S3 -> 0 | U3: =AB3 -> 0 | AB3: =F3*AC3 -> 0
A4: 2 | B4: SNLI | C4: B/0001617/082-83 | D4: 45902 | E4: Purchase | F4: 200 | G4: =H4/F4 -> 465 | H4: 93000 | I4: 0 | J4: 0 | K4: 0 | L4: 0 | M4: =M3+H4-L4 -> 93000 | N4: =N3+F4-I4 -> 200 | O4: =IFERROR(M4/N4,0) -> 465 | P4: 0 | R4: =306.9+13.95 -> 320.85 | S4: 25 | T4: =R4+S4 -> 345.85 | U4: =H4+T4 -> 93345.85 | V4: 0 | W4: 0 | X4: =V4+W4 -> 0 | Y4: 0 | Z4: =K4-X4-Y4 -> 0 | AA4: =I4*AC3 -> 0 | AB4: =AB3+U4-AA4 -> 93345.85 | AC4: =IFERROR(AB4/N4,0) -> 466.72925 | AD4: =Z4-AA4+Y4 -> 0
A5: 3 | B5: SNLI | C5: B/0001648/082-83 | D5: 45904 | E5: Purchase | F5: 500 | G5: =H5/F5 -> 457 | H5: 228500 | I5: 0 | J5: 0 | K5: 0 | L5: 0 | M5: =M4+H5-L5 -> 321500 | N5: =N3+F5-I5 -> 500 | O5: =IFERROR(M5/N5,0) -> 643 | P5: 0 | R5: =754.05+34.28 -> 788.33 | S5: 25 | T5: =R5+S5 -> 813.33 | U5: =H5+T5 -> 229313.33 | V5: 0 | W5: 0 | X5: =V5+W5 -> 0 | Y5: 0 | Z5: =K5-X5-Y5 -> 0 | AA5: =I5*AC3 -> 0 | AB5: =AB4+U5-AA5 -> 322659.18 | AC5: =IFERROR(AB5/N5,0) -> 645.31836 | AD5: =Z5-AA5+Y5 -> 0

Sheet MANDU
A1: 1. Bhadra | R1: Purchase | V1: Sales | Y1: Capital Gain Tax | Z1: Net Receivables | AA1: Principal Amt AP TAX (Sales Unit) | AB1: TC AP TAX | AC1: WACC AP TAX | AD1: P/L AP TAX
A2: S.No | B2: SYMBOL | C2: Bill No | D2: Txn Date | E2: Txn Type | F2: Purchase QTY | G2: PPPU | H2: Total Purchase Amount | I2: Sales Qty | J2: SPPU | K2: Sales Amt | L2: Principal Cost As per NFRS (In case of Sales) | M2: TC AP NFRS | N2: Unit Sum | O2: WACC AP NFRS | P2: P/L AP NFRS | R2: Purchase Commission | S2: DP Charges | T2: Total Commission on Purchase | U2: Total Investment Cost(Including Comission | V2: Sales Commission | W2: DP Charges | X2: Total Commission on Sales
A3: 1 | B3: MANDU | D3: 45886 | E3: Opening | F3: 0 | G3: 0 | H3: 0 | K3: 0 | M3: 0 | N3: 0 | O3: 0 | P3: 0 | T3: =R3+S3 -> 0 | U3: =AB3 -> 0 | AB3: =F3*AC3 -> 0
A4: 2 | B4: MANDU | C4: B/0001405/082-83 | D4: 45895 | E4: Purchase | F4: 230 | G4: =H4/F4 -> 854.58261 | H4: 196554 | I4: 0 | J4: 0 | K4: 0 | L4: 0 | M4: =M3+H4-L4 -> 196554 | N4: =N3+F4-I4 -> 230 | O4: =IFERROR(M4/N4,0) -> 854.58261 | P4: 0 | R4: =656.28+29.5 -> 685.78 | S4: 25 | T4: =R4+S4 -> 710.78 | U4: =H4+T4 -> 197264.78 | V4: 0 | W4: 0 | X4: =V4+W4 -> 0 | Y4: 0 | Z4: =K4-X4-Y4 -> 0 | AA4: =I4*AC3 -> 0 | AB4: =AB3+U4-AA4 -> 197264.78 | AC4: =IFERROR(AB4/N4,0) -> 857.67296 | AD4: =Z4-AA4+Y4 -> 0

Sheet KMCDB
A1: Jyoti Capital Limited
A2: Kamalpokhari, Kathmandu
A3: JCL Portfolio Statement
A5: 1. Shrawan | R5: Purchase | V5: Sales | Y5: Capital Gain Tax | Z5: Net Receivables | AA5: Principal Amt AP TAX (Sales Unit) | AB5: TC AP TAX | AC5: WACC AP TAX | AD5: P/L AP TAX
A6: S.No | B6: SYMBOL | C6: Bill No | D6: Txn Date | E6: Txn Type | F6: Purchase QTY | G6: PPPU | H6: Total Purchase Amount | I6: Sales Qty | J6: SPPU | K6: Sales Amt | L6: Principal Cost As per NFRS (In case of Sales) | M6: TC AP NFRS | N6: Unit Sum | O6: WACC AP NFRS | P6: P/L AP NFRS | R6: Purchase Commission | S6: DP Charges | T6: Total Commission on Purchase | U6: Total Investment Cost(Including Comission | V6: Sales Commission | W6: DP Charges | X6: Total Commission on Sales
A7: 1 | B7: KMCDB | D7: 45855 | E7: Opening | F7: 0 | G7: 0 | H7: =Table2428302829[[#This Row],[PPPU]]*Table2428302829[[#This Row],[Purchase QTY]] -> 0 | K7: =Table2428302829[[#This Row],[Sales Qty]]*Table2428302829[[#This Row],[SPPU]] -> 0 | M7: =Table2428302829[[#This Row],[Total Purchase Amount]] -> 0 | N7: =IF(Table2428302829[[#This Row],[Txn Type]]="opening",Table2428302829[[#This Row],[Purchase QTY]],"Error") -> 0 | O7: =IFERROR(Table2428302829[[#This Row],[TC AP NFRS]]/Table2428302829[[#This Row],[Unit Sum]],0) -> 0 | P7: =Table2428302829[[#This Row],[Sales Amt]]-Table2428302829[[#This Row],[Principal Cost As per NFRS (In case of Sales)]] -> 0 | T7: =R7+S7 -> 0 | U7: =AB7 -> 0 | AB7: =F7*AC7 -> 0
A8: 2 | B8: KMCDB | C8: B/0000506/082-83 | D8: 45865 | E8: purchase | F8: 1000 | G8: =IF(Table2428302829[[#This Row],[SPPU]]>0,0,Table2428302829[[#This Row],[Total Purchase Amount]]/Table2428302829[[#This Row],[Purchase QTY]]) -> 1138.5 | H8: 1138500 | I8: 0 | J8: 0 | K8: 0 | L8: =Table2428302829[[#This Row],[Sales Qty]]*O7 -> 0 | M8: =M7+Table2428302829[[#This Row],[Total Purchase Amount]]-Table2428302829[[#This Row],[Principal Cost As per NFRS (In case of Sales)]] -> 1138500 | N8: =N7+Table2428302829[[#This Row],[Purchase QTY]]-Table2428302829[[#This Row],[Sales Qty]] -> 1000 | O8: =IFERROR(Table2428302829[[#This Row],[TC AP NFRS]]/Table2428302829[[#This Row],[Unit Sum]],0) -> 1138.5 | P8: =Table2428302829[[#This Row],[Sales Amt]]-Table2428302829[[#This Row],[Principal Cost As per NFRS (In case of Sales)]] -> 0 | R8: =170.78+3669.2 -> 3839.98 | S8: 25 | T8: =R8+S8 -> 3864.98 | U8: =H8+T8 -> 1142365 | V8: 0 | W8: 0 | X8: =V8+W8 -> 0 | Y8: 0 | Z8: =K8-X8-Y8 -> 0 | AA8: =I8*AC7 -> 0 | AB8: =AB7+U8-AA8 -> 1142365 | AC8: =IFERROR(AB8/N8,0) -> 1142.365 | AD8: =Z8-AA8+Y8 -> 0
A9: =A8+1 -> 3 | G9: =Table2428302829[[#This Row],[Total Purchase Amount]]/Table2428302829[[#This Row],[Purchase QTY]] -> #DIV/0! | I9: 0 | K9: =Table2428302829[[#This Row],[Sales Qty]]*Table2428302829[[#This Row],[SPPU]] -> 0 | L9: =Table2428302829[[#This Row],[Sales Qty]]*O8 -> 0 | M9: =M8+Table2428302829[[#This Row],[Total Purchase Amount]]-Table2428302829[[#This Row],[Principal Cost As per NFRS (In case of Sales)]] -> 1138500 | N9: =N8+Table2428302829[[#This Row],[Purchase QTY]]-Table2428302829[[#This Row],[Sales Qty]] -> 1000 | O9: =Table2428302829[[#This Row],[TC AP NFRS]]/Table2428302829[[#This Row],[Unit Sum]] -> 1138.5 | R9: 0 | T9: =R9+S9 -> 0 | U9: =H9+T9 -> 0 | V9: 0 | W9: 0 | X9: =V9+W9 -> 0 | Y9: 0 | Z9: =K9-X9-Y9 -> 0 | AA9: =I9*AC8 -> 0 | AB9: =AB8+U9-AA9 -> 1142365 | AC9: =IFERROR(AB9/N9,0) -> 1142.365 | AD9: =Z9-AA9+Y9 -> 0
A10: =A9+1 -> 4 | G10: =IF(Table2428302829[[#This Row],[SPPU]]>0,0,Table2428302829[[#This Row],[Total Purchase Amount]]/Table2428302829[[#This Row],[Purchase QTY]]) -> #DIV/0! | I10: 0 | K10: =Table2428302829[[#This Row],[Sales Qty]]*Table2428302829[[#This Row],[SPPU]] -> 0 | L10: =Table2428302829[[#This Row],[Sales Qty]]*O9 -> 0 | M10: =M9+Table2428302829[[#This Row],[Total Purchase Amount]]-Table2428302829[[#This Row],[Principal Cost As per NFRS (In case of Sales)]] -> 1138500 | N10: =N9+Table2428302829[[#This Row],[Purchase QTY]]-Table2428302829[[#This Row],[Sales Qty]] -> 1000 | O10: =IFERROR(Table2428302829[[#This Row],[TC AP NFRS]]/Table2428302829[[#This Row],[Unit Sum]],0) -> 1138.5 | P10: =Table2428302829[[#This Row],[Sales Amt]]-Table2428302829[[#This Row],[Principal Cost As per NFRS (In case of Sales)]] -> 0 | R10: 0 | T10: =R10+S10 -> 0 | U10: =H10+T10 -> 0 | V10: 0 | W10: 0 | X10: =V10+W10 -> 0 | Y10: 0 | Z10: =K10-X10-Y10 -> 0 | AA10: =I10*AC9 -> 0 | AB10: =AB9+U10-AA10 -> 1142365 | AC10: =IFERROR(AB10/N10,0) -> 1142.365 | AD10: =Z10-AA10+Y10 -> 0
A11: =A10+1 -> 5 | G11: =Table2428302829[[#This Row],[Total Purchase Amount]]/Table2428302829[[#This Row],[Purchase QTY]] -> #DIV/0! | K11: =Table2428302829[[#This Row],[Sales Qty]]*Table2428302829[[#This Row],[SPPU]] -> 0 | M11: =M10+Table2428302829[[#This Row],[Total Purchase Amount]]-Table2428302829[[#This Row],[Principal Cost As per NFRS (In case of Sales)]] -> 1138500 | N11: =N10+Table2428302829[[#This Row],[Purchase QTY]]-Table2428302829[[#This Row],[Sales Qty]] -> 1000 | O11: =Table2428302829[[#This Row],[TC AP NFRS]]/Table2428302829[[#This Row],[Unit Sum]] -> 1138.5 | R11: 0 | T11: =R11+S11 -> 0 | U11: =H11+T11 -> 0 | V11: 0 | W11: 0 | X11: =V11+W11 -> 0 | Y11: 0 | Z11: =K11-X11-Y11 -> 0 | AA11: =I11*AC10 -> 0 | AB11: =AB10+U11-AA11 -> 1142365 | AC11: =IFERROR(AB11/N11,0) -> 1142.365 | AD11: =Z11-AA11+Y11 -> 0
A12: Total | F12: =SUM(INDIRECT("f4:f"&ROW()-1)) -> 1000 | G12: =Table2428302829[[#This Row],[Total Purchase Amount]]/Table2428302829[[#This Row],[Purchase QTY]] -> 1138.5 | H12: =SUM(INDIRECT("h4:h"&ROW()-1)) -> 1138500 | I12: =SUM(INDIRECT("i4:i"&ROW()-1)) -> 0 | J12: =Table2428302829[[#This Row],[Sales Amt]]/Table2428302829[[#This Row],[Sales Qty]] -> #DIV/0! | K12: =SUM(INDIRECT("k4:k"&ROW()-1)) -> 0 | M12: =Table2428302829[[#This Row],[Total Purchase Amount]]-Table2428302829[[#This Row],[Principal Cost As per NFRS (In case of Sales)]] -> 1138500 | N12: =Table2428302829[[#This Row],[Purchase QTY]]-Table2428302829[[#This Row],[Sales Qty]] -> 1000 | O12: =Table2428302829[[#This Row],[TC AP NFRS]]/Table2428302829[[#This Row],[Unit Sum]] -> 1138.5 | P12: =SUM(P7:P8) -> 0 | R12: =SUM(R7:R11) -> 3839.98 | S12: =SUM(S7:S11) -> 25 | T12: =SUM(T7:T11) -> 3864.98 | U12: =SUM(U7:U11) -> 1142365 | V12: =SUM(V7:V11) -> 0 | W12: =SUM(W7:W11) -> 0 | X12: =SUM(X7:X11) -> 0 | Y12: =SUM(Y7:Y11) -> 0 | ... AA12: =SUM(AA7:AA11) -> 0 | AB12: =U12-AA12 -> 1142365 | AC12: =IFERROR(AB12/N12,0) -> 1142.365 | AD12: =SUM(AD7:AD11) -> 0
A16: 2. Bhadra | R16: Purchase | V16: Sales | Y16: Capital Gain Tax | Z16: Net Receivables | AA16: Principal Amt AP TAX (Sales Unit) | AB16: TC AP TAX | AC16: WACC AP TAX | AD16: P/L AP TAX
A17: S.No | B17: SYMBOL | C17: Bill No | D17: Txn Date | E17: Txn Type | F17: Purchase QTY | G17: PPPU | H17: Total Purchase Amount | I17: Sales Qty | J17: SPPU | K17: Sales Amt | L17: Principal Cost As per NFRS (In case of Sales) | M17: TC AP NFRS | N17: Unit Sum | O17: WACC AP NFRS | P17: P/L AP NFRS | R17: Purchase Commission | S17: DP Charges | T17: Total Commission on Purchase | U17: Total Investment Cost(Including Comission | V17: Sales Commission | W17: DP Charges | X17: Total Commission on Sales
A18: 1 | B18: KMCDB | D18: 45886 | E18: Opening | F18: 1000 | G18: 1138.5 | H18: 1138500 | M18: 1138500 | N18: 1000 | O18: 1138.5 | P18: 0 | R18: 3839.98 | S18: 25 | T18: 3864.98 | U18: 1142365 | V18: 0 | W18: 0 | X18: 0 | Y18: 0 | Z18: 0 | AA18: 0 | AB18: 1142365 | AC18: 1142.365 | AD18: 0

Sheet HEI
A1: Jyoti Capital Limited
A2: Kamalpokhari, Kathmandu
A3: JCL Portfolio Statement
A5: 1. Shrawan | R5: Purchase | V5: Sales | Y5: Capital Gain Tax | Z5: Net Receivables | AA5: Principal Amt AP TAX (Sales Unit) | AB5: TC AP TAX | AC5: WACC AP TAX | AD5: P/L AP TAX
A6: S.No | B6: SYMBOL | C6: Bill No | D6: Txn Date | E6: Txn Type | F6: Purchase QTY | G6: PPPU | H6: Total Purchase Amount | I6: Sales Qty | J6: SPPU | K6: Sales Amt | L6: Principal Cost As per NFRS (In case of Sales) | M6: TC AP NFRS | N6: Unit Sum | O6: WACC AP NFRS | P6: P/L AP NFRS | R6: Purchase Commission | S6: DP Charges | T6: Total Commission on Purchase | U6: Total Investment Cost(Including Comission | V6: Sales Commission | W6: DP Charges | X6: Total Commission on Sales
A7: 1 | B7: HEI | D7: 45855 | E7: Opening | F7: 0 | G7: 0 | H7: =Table24283028[[#This Row],[PPPU]]*Table24283028[[#This Row],[Purchase QTY]] -> 0 | K7: =Table24283028[[#This Row],[Sales Qty]]*Table24283028[[#This Row],[SPPU]] -> 0 | M7: =Table24283028[[#This Row],[Total Purchase Amount]] -> 0 | N7: =IF(Table24283028[[#This Row],[Txn Type]]="opening",Table24283028[[#This Row],[Purchase QTY]],"Error") -> 0 | O7: =IFERROR(Table24283028[[#This Row],[TC AP NFRS]]/Table24283028[[#This Row],[Unit Sum]],0) -> 0 | P7: =Table24283028[[#This Row],[Sales Amt]]-Table24283028[[#This Row],[Principal Cost As per NFRS (In case of Sales)]] -> 0 | T7: =R7+S7 -> 0 | U7: =AB7 -> 0 | AB7: =F7*AC7 -> 0
A8: 2 | B8: HEI | C8: B/0000507/082-83 | D8: 45500 | E8: purchase | F8: 1000 | G8: =IF(Table24283028[[#This Row],[SPPU]]>0,0,Table24283028[[#This Row],[Total Purchase Amount]]/Table24283028[[#This Row],[Purchase QTY]]) -> 635 | H8: 635000 | I8: 0 | J8: 0 | K8: 0 | L8: =Table24283028[[#This Row],[Sales Qty]]*O7 -> 0 | M8: =M7+Table24283028[[#This Row],[Total Purchase Amount]]-Table24283028[[#This Row],[Principal Cost As per NFRS (In case of Sales)]] -> 635000 | N8: =N7+Table24283028[[#This Row],[Purchase QTY]]-Table24283028[[#This Row],[Sales Qty]] -> 1000 | O8: =IFERROR(Table24283028[[#This Row],[TC AP NFRS]]/Table24283028[[#This Row],[Unit Sum]],0) -> 635 | P8: =Table24283028[[#This Row],[Sales Amt]]-Table24283028[[#This Row],[Principal Cost As per NFRS (In case of Sales)]] -> 0 | R8: =95.25+2095.5 -> 2190.75 | S8: 25 | T8: =R8+S8 -> 2215.75 | U8: =H8+T8 -> 637215.75 | V8: 0 | W8: 0 | X8: =V8+W8 -> 0 | Y8: 0 | Z8: =K8-X8-Y8 -> 0 | AA8: =I8*AC7 -> 0 | AB8: =AB7+U8-AA8 -> 637215.75 | AC8: =IFERROR(AB8/N8,0) -> 637.21575 | AD8: =Z8-AA8+Y8 -> 0
A9: =A8+1 -> 3 | B9: HEI | C9: B/0000514/082-83 | D9: 45501 | E9: purchase | F9: 381 | G9: =Table24283028[[#This Row],[Total Purchase Amount]]/Table24283028[[#This Row],[Purchase QTY]] -> 625 | H9: 238125 | I9: 0 | K9: =Table24283028[[#This Row],[Sales Qty]]*Table24283028[[#This Row],[SPPU]] -> 0 | L9: =Table24283028[[#This Row],[Sales Qty]]*O8 -> 0 | M9: =M8+Table24283028[[#This Row],[Total Purchase Amount]]-Table24283028[[#This Row],[Principal Cost As per NFRS (In case of Sales)]] -> 873125 | N9: =N8+Table24283028[[#This Row],[Purchase QTY]]-Table24283028[[#This Row],[Sales Qty]] -> 1381 | O9: =Table24283028[[#This Row],[TC AP NFRS]]/Table24283028[[#This Row],[Unit Sum]] -> 632.24113 | P9: =Table24283028[[#This Row],[Sales Amt]]-Table24283028[[#This Row],[Principal Cost As per NFRS (In case of Sales)]] -> 0 | R9: =35.72+785.82 -> 821.54 | S9: 25 | T9: =R9+S9 -> 846.54 | U9: =H9+T9 -> 238971.54 | V9: 0 | W9: 0 | X9: =V9+W9 -> 0 | Y9: 0 | Z9: =K9-X9-Y9 -> 0 | AA9: =I9*AC8 -> 0 | AB9: =AB8+U9-AA9 -> 876187.29 | AC9: =IFERROR(AB9/N9,0) -> 634.45857 | AD9: =Z9-AA9+Y9 -> 0
A10: =A9+1 -> 4 | B10: HEI | C10: B/0000595/082-83 | D10: 45502 | E10: purchase | F10: 1000 | G10: =IF(Table24283028[[#This Row],[SPPU]]>0,0,Table24283028[[#This Row],[Total Purchase Amount]]/Table24283028[[#This Row],[Purchase QTY]]) -> 632 | H10: 632000 | I10: 0 | K10: =Table24283028[[#This Row],[Sales Qty]]*Table24283028[[#This Row],[SPPU]] -> 0 | L10: =Table24283028[[#This Row],[Sales Qty]]*O9 -> 0 | M10: =M9+Table24283028[[#This Row],[Total Purchase Amount]]-Table24283028[[#This Row],[Principal Cost As per NFRS (In case of Sales)]] -> 1505125 | N10: =N9+Table24283028[[#This Row],[Purchase QTY]]-Table24283028[[#This Row],[Sales Qty]] -> 2381 | O10: =IFERROR(Table24283028[[#This Row],[TC AP NFRS]]/Table24283028[[#This Row],[Unit Sum]],0) -> 632.13986 | P10: =Table24283028[[#This Row],[Sales Amt]]-Table24283028[[#This Row],[Principal Cost As per NFRS (In case of Sales)]] -> 0 | R10: =94.8+1959.2 -> 2054 | S10: 25 | T10: =R10+S10 -> 2079 | U10: =H10+T10 -> 634079 | V10: 0 | W10: 0 | X10: =V10+W10 -> 0 | Y10: 0 | Z10: =K10-X10-Y10 -> 0 | AA10: =I10*AC9 -> 0 | AB10: =AB9+U10-AA10 -> 1510266.3 | AC10: =IFERROR(AB10/N10,0) -> 634.29916 | AD10: =Z10-AA10+Y10 -> 0
A11: =A10+1 -> 5 | G11: =Table24283028[[#This Row],[Total Purchase Amount]]/Table24283028[[#This Row],[Purchase QTY]] -> #DIV/0! | K11: =Table24283028[[#This Row],[Sales Qty]]*Table24283028[[#This Row],[SPPU]] -> 0 | M11: =M10+Table24283028[[#This Row],[Total Purchase Amount]]-Table24283028[[#This Row],[Principal Cost As per NFRS (In case of Sales)]] -> 1505125 | N11: =N10+Table24283028[[#This Row],[Purchase QTY]]-Table24283028[[#This Row],[Sales Qty]] -> 2381 | O11: =Table24283028[[#This Row],[TC AP NFRS]]/Table24283028[[#This Row],[Unit Sum]] -> 632.13986 | P11: =Table24283028[[#This Row],[Sales Amt]]-Table24283028[[#This Row],[Principal Cost As per NFRS (In case of Sales)]] -> 0 | R11: 0 | T11: =R11+S11 -> 0 | U11: =H11+T11 -> 0 | V11: 0 | W11: 0 | X11: =V11+W11 -> 0 | Y11: 0 | Z11: =K11-X11-Y11 -> 0 | AA11: =I11*AC10 -> 0 | AB11: =AB10+U11-AA11 -> 1510266.3 | AC11: =IFERROR(AB11/N11,0) -> 634.29916 | AD11: =Z11-AA11+Y11 -> 0
A12: Total | F12: =SUM(INDIRECT("f4:f"&ROW()-1)) -> 2381 | G12: =Table24283028[[#This Row],[Total Purchase Amount]]/Table24283028[[#This Row],[Purchase QTY]] -> 632.13986 | H12: =SUM(INDIRECT("h4:h"&ROW()-1)) -> 1505125 | I12: =SUM(INDIRECT("i4:i"&ROW()-1)) -> 0 | J12: =Table24283028[[#This Row],[Sales Amt]]/Table24283028[[#This Row],[Sales Qty]] -> #DIV/0! | K12: =SUM(INDIRECT("k4:k"&ROW()-1)) -> 0 | M12: =Table24283028[[#This Row],[Total Purchase Amount]]-Table24283028[[#This Row],[Sales Amt]] -> 1505125 | N12: =Table24283028[[#This Row],[Purchase QTY]]-Table24283028[[#This Row],[Sales Qty]] -> 2381 | O12: =Table24283028[[#This Row],[TC AP NFRS]]/Table24283028[[#This Row],[Unit Sum]] -> 632.13986 | P12: =SUBTOTAL(109,P7:P11) -> 0 | R12: =SUM(R7:R11) -> 5066.29 | S12: =SUM(S7:S11) -> 75 | T12: =SUM(T7:T11) -> 5141.29 | U12: =SUM(U7:U11) -> 1510266.3 | V12: =SUM(V7:V11) -> 0 | W12: =SUM(W7:W11) -> 0 | X12: =SUM(X7:X11) -> 0 | Y12: =SUM(Y7:Y11) -> 0 | ... AA12: =SUM(AA7:AA11) -> 0 | AB12: =U12-AA12 -> 1510266.3 | AC12: =IFERROR(AB12/N12,0) -> 634.29916 | AD12: =SUM(AD7:AD11) -> 0
A14: 2. Bhadra | R14: Purchase | V14: Sales | Y14: Capital Gain Tax | Z14: Net Receivables | AA14: Principal Amt AP TAX (Sales Unit) | AB14: TC AP TAX | AC14: WACC AP TAX | AD14: P/L AP TAX
A15: S.No | B15: SYMBOL | C15: Bill No | D15: Txn Date | E15: Txn Type | F15: Purchase QTY | G15: PPPU | H15: Total Purchase Amount | I15: Sales Qty | J15: SPPU | K15: Sales Amt | L15: Principal Cost As per NFRS (In case of Sales) | M15: TC AP NFRS | N15: Unit Sum | O15: WACC AP NFRS | P15: P/L AP NFRS | R15: Purchase Commission | S15: DP Charges | T15: Total Commission on Purchase | U15: Total Investment Cost(Including Comission | V15: Sales Commission | W15: DP Charges | X15: Total Commission on Sales
A16: 1 | B16: HEI | D16: 45886 | E16: Opening | F16: 2381 | G16: 632.13986 | H16: 1505125 | M16: 1505125 | N16: 2381 | O16: 632.13986 | R16: 5066.29 | S16: 75 | T16: 5141.29 | U16: 1510266.3 | AB16: 1510266.3 | AC16: 634.29916

Sheet CHDC
A1: Jyoti Capital Limited
A2: Kamalpokhari, Kathmandu
A3: JCL Portfolio Statement
A5: 1. Shrawan | R5: Purchase | V5: Sales | Y5: Capital Gain Tax | Z5: Net Receivables | AA5: Principal Amt AP TAX (Sales Unit) | AB5: TC AP TAX | AC5: WACC AP TAX | AD5: P/L AP TAX
A6: S.No | B6: SYMBOL | C6: Bill No | D6: Txn Date | E6: Txn Type | F6: Purchase QTY | G6: PPPU | H6: Total Purchase Amount | I6: Sales Qty | J6: SPPU | K6: Sales Amt | L6: Principal Cost As per NFRS (In case of Sales) | M6: TC AP NFRS | N6: Unit Sum | O6: WACC AP NFRS | P6: P/L AP NFRS | R6: Purchase Commission | S6: DP Charges | T6: Total Commission on Purchase | U6: Total Investment Cost(Including Comission | V6: Sales Commission | W6: DP Charges | X6: Total Commission on Sales
A7: 1 | B7: CHDC | D7: 45855 | E7: Opening | F7: 0 | G7: 0 | H7: =Table2428302227[[#This Row],[PPPU]]*Table2428302227[[#This Row],[Purchase QTY]] -> 0 | K7: =Table2428302227[[#This Row],[Sales Qty]]*Table2428302227[[#This Row],[SPPU]] -> 0 | M7: =Table2428302227[[#This Row],[Total Purchase Amount]] -> 0 | N7: =IF(Table2428302227[[#This Row],[Txn Type]]="opening",Table2428302227[[#This Row],[Purchase QTY]],"Error") -> 0 | O7: =IFERROR(Table2428302227[[#This Row],[TC AP NFRS]]/Table2428302227[[#This Row],[Unit Sum]],0) -> 0 | P7: =Table2428302227[[#This Row],[Sales Amt]]-Table2428302227[[#This Row],[Principal Cost As per NFRS (In case of Sales)]] -> 0 | T7: =R7+S7 -> 0 | U7: =AB7 -> 0 | AB7: =F7*AC7 -> 0
A8: 2 | B8: CHDC | C8: B/000506/082-083 | D8: 45865 | E8: purchase | F8: 135 | G8: =IF(Table2428302227[[#This Row],[SPPU]]>0,0,Table2428302227[[#This Row],[Total Purchase Amount]]/Table2428302227[[#This Row],[Purchase QTY]]) -> 2862.2 | H8: 386397 | I8: 0 | J8: 0 | K8: =Table2428302227[[#This Row],[Sales Qty]]*Table2428302227[[#This Row],[SPPU]] -> 0 | L8: =Table2428302227[[#This Row],[Sales Qty]]*O7 -> 0 | M8: =M7+Table2428302227[[#This Row],[Total Purchase Amount]]-Table2428302227[[#This Row],[Principal Cost As per NFRS (In case of Sales)]] -> 386397 | N8: =N7+Table2428302227[[#This Row],[Purchase QTY]]-Table2428302227[[#This Row],[Sales Qty]] -> 135 | O8: =IFERROR(Table2428302227[[#This Row],[TC AP NFRS]]/Table2428302227[[#This Row],[Unit Sum]],0) -> 2862.2 | P8: =Table2428302227[[#This Row],[Sales Amt]]-Table2428302227[[#This Row],[Principal Cost As per NFRS (In case of Sales)]] -> 0 | R8: =57.96+1275.11 -> 1333.07 | S8: 25 | T8: =R8+S8 -> 1358.07 | U8: =H8+T8 -> 387755.07 | V8: 0 | W8: 0 | X8: =V8+W8 -> 0 | Y8: 0 | Z8: =K8-X8-Y8 -> 0 | AA8: =I8*AC7 -> 0 | AB8: =AB7+U8-AA8 -> 387755.07 | AC8: =IFERROR(AB8/N8,0) -> 2872.2598 | AD8: =Z8-AA8+Y8 -> 0
A9: =A8+1 -> 3 | B9: CHDC | C9: B/000513/082-083 | D9: 45866 | E9: purchase | F9: 399 | G9: =Table2428302227[[#This Row],[Total Purchase Amount]]/Table2428302227[[#This Row],[Purchase QTY]] -> 2855 | H9: 1139145 | I9: 0 | K9: =Table2428302227[[#This Row],[Sales Qty]]*Table2428302227[[#This Row],[SPPU]] -> 0 | M9: =M8+Table2428302227[[#This Row],[Total Purchase Amount]]-Table2428302227[[#This Row],[Principal Cost As per NFRS (In case of Sales)]] -> 1525542 | N9: =N8+Table2428302227[[#This Row],[Purchase QTY]]-Table2428302227[[#This Row],[Sales Qty]] -> 534 | O9: =Table2428302227[[#This Row],[TC AP NFRS]]/Table2428302227[[#This Row],[Unit Sum]] -> 2856.8202 | P9: =Table2428302227[[#This Row],[Sales Amt]]-Table2428302227[[#This Row],[Principal Cost As per NFRS (In case of Sales)]] -> 0 | R9: =170.88+3651.26 -> 3822.14 | S9: 25 | T9: =R9+S9 -> 3847.14 | U9: =H9+T9 -> 1142992.1 | V9: 0 | W9: 0 | X9: =V9+W9 -> 0 | Y9: 0 | Z9: =K9-X9-Y9 -> 0 | AA9: =I9*AC8 -> 0 | AB9: =AB8+U9-AA9 -> 1530747.2 | AC9: =IFERROR(AB9/N9,0) -> 2866.5678 | AD9: =Z9-AA9+Y9 -> 0
A10: =A9+1 -> 4 | B10: CHDC | C10: B/000594/082-083 | D10: 45867 | E10: purchase | F10: 10 | G10: =Table2428302227[[#This Row],[Total Purchase Amount]]/Table2428302227[[#This Row],[Purchase QTY]] -> 2846.5 | H10: 28465 | K10: =Table2428302227[[#This Row],[Sales Qty]]*Table2428302227[[#This Row],[SPPU]] -> 0 | M10: =M9+Table2428302227[[#This Row],[Total Purchase Amount]]-Table2428302227[[#This Row],[Principal Cost As per NFRS (In case of Sales)]] -> 1554007 | N10: =N9+Table2428302227[[#This Row],[Purchase QTY]]-Table2428302227[[#This Row],[Sales Qty]] -> 544 | O10: =Table2428302227[[#This Row],[TC AP NFRS]]/Table2428302227[[#This Row],[Unit Sum]] -> 2856.6305 | P10: =Table2428302227[[#This Row],[Sales Amt]]-Table2428302227[[#This Row],[Principal Cost As per NFRS (In case of Sales)]] -> 0 | R10: =4.27+102.47 -> 106.74 | S10: 25 | T10: =R10+S10 -> 131.74 | U10: =H10+T10 -> 28596.74 | V10: 0 | W10: 0 | X10: =V10+W10 -> 0 | Y10: 0 | Z10: =K10-X10-Y10 -> 0 | AA10: =I10*AC9 -> 0 | AB10: =AB9+U10-AA10 -> 1559343.9 | AC10: =IFERROR(AB10/N10,0) -> 2866.4411 | AD10: =Z10-AA10+Y10 -> 0
A11: Total | F11: =SUM(INDIRECT("f4:f"&ROW()-1)) -> 544 | H11: =SUM(INDIRECT("h4:h"&ROW()-1)) -> 1554007 | I11: =SUM(INDIRECT("i4:i"&ROW()-1)) -> 0 | K11: =SUM(INDIRECT("k4:k"&ROW()-1)) -> 0 | M11: =Table2428302227[[#This Row],[Total Purchase Amount]]-Table2428302227[[#This Row],[Principal Cost As per NFRS (In case of Sales)]] -> 1554007 | N11: =Table2428302227[[#This Row],[Purchase QTY]]-Table2428302227[[#This Row],[Sales Qty]] -> 544 | O11: =Table2428302227[[#This Row],[TC AP NFRS]]/Table2428302227[[#This Row],[Unit Sum]] -> 2856.6305 | P11: =SUM(P7:P8) -> 0 | R11: =SUM(R7:R10) -> 5261.95 | S11: =SUM(S7:S10) -> 75 | T11: =SUM(T7:T10) -> 5336.95 | U11: =SUM(U7:U10) -> 1559343.9 | V11: =SUM(V7:V10) -> 0 | W11: =SUM(W7:W10) -> 0 | X11: =SUM(X7:X10) -> 0 | Y11: =SUM(Y7:Y10) -> 0 | ... AA11: =SUM(AA7:AA10) -> 0 | AB11: =U11-AA11 -> 1559343.9 | AC11: =AB11/Table2428302227[[#This Row],[Unit Sum]] -> 2866.4411 | AD11: =SUM(AD7:AD10) -> 0
A14: 2. Bhadra | R14: Purchase | V14: Sales | Y14: Capital Gain Tax | Z14: Net Receivables | AA14: Principal Amt AP TAX (Sales Unit) | AB14: TC AP TAX | AC14: WACC AP TAX | AD14: P/L AP TAX
A15: S.No | B15: SYMBOL | C15: Bill No | D15: Txn Date | E15: Txn Type | F15: Purchase QTY | G15: PPPU | H15: Total Purchase Amount | I15: Sales Qty | J15: SPPU | K15: Sales Amt | L15: Principal Cost As per NFRS (In case of Sales) | M15: TC AP NFRS | N15: Unit Sum | O15: WACC AP NFRS | P15: P/L AP NFRS | R15: Purchase Commission | S15: DP Charges | T15: Total Commission on Purchase | U15: Total Investment Cost(Including Comission | V15: Sales Commission | W15: DP Charges | X15: Total Commission on Sales
A16: 1 | B16: CHDC | D16: 45886 | E16: Opening | F16: 544 | H16: 1554007 | I16: 0 | K16: 0 | M16: 1554007 | N16: 544 | O16: 2856.6305 | P16: 0 | R16: 5261.95 | S16: 75 | T16: 5336.95 | U16: 1559343.9 | V16: 0 | W16: 0 | X16: 0 | Y16: 0 | Z16: 0 | AA16: 0 | AB16: 1559343.9 | AC16: 2866.4411 | AD16: 0
A17: 2 | B17: CHDC | C17: B/001551/082-083 | D17: 45900 | E17: Purchase | F17: 300 | G17: =H17/F17 -> 2515.0133 | H17: 754504 | M17: =M16+H17-L17 -> 2308511 | N17: =N16+F17-I17 -> 844 | O17: =M17/N17 -> 2735.2026 | R17: =2498.93+113.19 -> 2612.12 | S17: 25 | T17: =R17+S17 -> 2637.12 | U17: =H17+T17 -> 757141.12 | V17: 0 | W17: 0 | X17: =V17+W17 -> 0 | Y17: 0 | Z17: =K17-X17-Y17 -> 0 | AA17: =I17*AC16 -> 0 | AB17: =AB16+U17-AA17 -> 2316485.1 | AC17: =IFERROR(AB17/N17,0) -> 2744.6506 | AD17: =Z17-AA17+Y17 -> 0

Sheet TRH
A1: 1. Bhadra | R1: Purchase | V1: Sales | Y1: Capital Gain Tax | Z1: Net Receivables | AA1: Principal Amt AP TAX (Sales Unit) | AB1: TC AP TAX | AC1: WACC AP TAX | AD1: P/L AP TAX
A2: S.No | B2: SYMBOL | C2: Bill No | D2: Txn Date | E2: Txn Type | F2: Purchase QTY | G2: PPPU | H2: Total Purchase Amount | I2: Sales Qty | J2: SPPU | K2: Sales Amt | L2: Principal Cost As per NFRS (In case of Sales) | M2: TC AP NFRS | N2: Unit Sum | O2: WACC AP NFRS | P2: P/L AP NFRS | R2: Purchase Commission | S2: DP Charges | T2: Total Commission on Purchase | U2: Total Investment Cost(Including Comission | V2: Sales Commission | W2: DP Charges | X2: Total Commission on Sales
A3: 1 | B3: TRH | D3: 45886 | E3: Opening | F3: 0 | G3: 0 | H3: 0 | K3: 0 | M3: 0 | N3: 0 | O3: 0 | P3: 0 | T3: =R3+S3 -> 0 | U3: =AB3 -> 0 | AB3: =F3*AC3 -> 0
A4: 2 | B4: TRH | C4: B/0001555/082-83 | D4: 45900 | E4: Purchase | F4: 600 | G4: =H4/F4 -> 950.1 | H4: 570060 | I4: 0 | J4: 0 | K4: 0 | L4: 0 | M4: =M3+H4-L4 -> 570060 | N4: =N3+F4-I4 -> 600 | O4: =IFERROR(M4/N4,0) -> 950.1 | P4: 0 | R4: =1901.27+85.51 -> 1986.78 | S4: 25 | T4: =R4+S4 -> 2011.78 | U4: =H4+T4 -> 572071.78 | V4: 0 | W4: 0 | X4: =V4+W4 -> 0 | Y4: 0 | Z4: =K4-X4-Y4 -> 0 | AA4: =I4*AC3 -> 0 | AB4: =AB3+U4-AA4 -> 572071.78 | AC4: =IFERROR(AB4/N4,0) -> 953.45297 | AD4: =Z4-AA4+Y4 -> 0

Sheet RSDC
A1: 1. Bhadra | R1: Purchase | V1: Sales | Y1: Capital Gain Tax | Z1: Net Receivables | AA1: Principal Amt AP TAX (Sales Unit) | AB1: TC AP TAX | AC1: WACC AP TAX | AD1: P/L AP TAX
A2: S.No | B2: SYMBOL | C2: Bill No | D2: Txn Date | E2: Txn Type | F2: Purchase QTY | G2: PPPU | H2: Total Purchase Amount | I2: Sales Qty | J2: SPPU | K2: Sales Amt | L2: Principal Cost As per NFRS (In case of Sales) | M2: TC AP NFRS | N2: Unit Sum | O2: WACC AP NFRS | P2: P/L AP NFRS | R2: Purchase Commission | S2: DP Charges | T2: Total Commission on Purchase | U2: Total Investment Cost(Including Comission | V2: Sales Commission | W2: DP Charges | X2: Total Commission on Sales
A3: 1 | B3: RSDC | D3: 45886 | E3: Opening | F3: 0 | G3: 0 | H3: 0 | K3: 0 | M3: 0 | N3: 0 | O3: 0 | P3: 0 | T3: =R3+S3 -> 0 | U3: =AB3 -> 0 | AB3: =F3*AC3 -> 0
A4: 2 | B4: RSDC | C4: B/0001554/082-83 | D4: 45893 | E4: Purchase | F4: 100 | G4: =H4/F4 -> 681 | H4: 68100 | I4: 0 | J4: 0 | K4: 0 | L4: 0 | M4: =M3+H4-L4 -> 68100 | N4: =N3+F4-I4 -> 100 | O4: =IFERROR(M4/N4,0) -> 681 | P4: 0 | R4: =224.73+10.22 -> 234.95 | S4: 25 | T4: =R4+S4 -> 259.95 | U4: =H4+T4 -> 68359.95 | V4: 0 | W4: 0 | X4: =V4+W4 -> 0 | Y4: 0 | Z4: =K4-X4-Y4 -> 0 | AA4: =I4*AC3 -> 0 | AB4: =AB3+U4-AA4 -> 68359.95 | AC4: =IFERROR(AB4/N4,0) -> 683.5995 | AD4: =Z4-AA4+Y4 -> 0

Sheet ILI
A1: Jyoti Capital Limited
A2: Kamalpokhari, Kathmandu
A3: JCL Portfolio Statement
A5: 1. Shrawan | R5: Purchase | V5: Sales | Y5: Capital Gain Tax | Z5: Net Receivables | AA5: Principal Amt AP TAX (Sales Unit) | AB5: TC AP TAX | AC5: WACC AP TAX | AD5: P/L AP TAX
A6: S.No | B6: SYMBOL | C6: Bill No | D6: Txn Date | E6: Txn Type | F6: Purchase QTY | G6: PPPU | H6: Total Purchase Amount | I6: Sales Qty | J6: SPPU | K6: Sales Amt | L6: Principal Cost As per NFRS (In case of Sales) | M6: TC AP NFRS | N6: Unit Sum | O6: WACC AP NFRS | P6: P/L AP NFRS | R6: Purchase Commission | S6: DP Charges | T6: Total Commission on Purchase | U6: Total Investment Cost(Including Comission | V6: Sales Commission | W6: DP Charges | X6: Total Commission on Sales
A7: 1 | B7: ILI | D7: 45855 | E7: Opening | F7: 10450 | G7: 462.02 | H7: =Table242830891013141516171819[[#This Row],[Purchase QTY]]*Table242830891013141516171819[[#This Row],[PPPU]] -> 4828109 | M7: =Table242830891013141516171819[[#This Row],[Total Purchase Amount]] -> 4828109 | N7: =IF(Table242830891013141516171819[[#This Row],[Txn Type]]="opening",Table242830891013141516171819[[#This Row],[Purchase QTY]],"Error") -> 10450 | O7: =IFERROR(Table242830891013141516171819[[#This Row],[TC AP NFRS]]/Table242830891013141516171819[[#This Row],[Unit Sum]],0) -> 462.02 | P7: =Table242830891013141516171819[[#This Row],[Sales Amt]]-Table242830891013141516171819[[#This Row],[Principal Cost As per NFRS (In case of Sales)]] -> 0 | T7: =R7+S7 -> 0 | U7: =AB7 -> 5386975 | AB7: =F7*AC7 -> 5386975 | AC7: 515.5
A8: =A7+1 -> 2 | B8: ILI | C8: B/0000121/082-83 | D8: 45858 | E8: purchase | F8: 1000 | G8: =Table242830891013141516171819[[#This Row],[Total Purchase Amount]]/Table242830891013141516171819[[#This Row],[Purchase QTY]] -> 478 | H8: 478000 | I8: 0 | J8: =Table242830891013141516171819[[#This Row],[Sales Amt]]/Table242830891013141516171819[[#This Row],[Sales Qty]] -> #DIV/0! | K8: 0 | L8: =Table242830891013141516171819[[#This Row],[Sales Qty]]*O7 -> 0 | M8: =M7+Table242830891013141516171819[[#This Row],[Total Purchase Amount]]-Table242830891013141516171819[[#This Row],[Principal Cost As per NFRS (In case of Sales)]] -> 5306109 | N8: =N7+Table242830891013141516171819[[#This Row],[Purchase QTY]]-Table242830891013141516171819[[#This Row],[Sales Qty]] -> 11450 | O8: =IFERROR(Table242830891013141516171819[[#This Row],[TC AP NFRS]]/Table242830891013141516171819[[#This Row],[Unit Sum]],0) -> 463.41563 | P8: =Table242830891013141516171819[[#This Row],[Sales Amt]]-Table242830891013141516171819[[#This Row],[Principal Cost As per NFRS (In case of Sales)]] -> 0 | R8: =71.7+1596.76 -> 1668.46 | S8: 25 | T8: =R8+S8 -> 1693.46 | U8: =H8+T8 -> 479693.46 | V8: 0 | W8: 0 | X8: =V8+W8 -> 0 | Y8: 0 | Z8: =K8-X8-Y8 -> 0 | AA8: =I8*AC7 -> 0 | AB8: =AB7+U8-AA8 -> 5866668.5 | AC8: =IFERROR(AB8/N8,0) -> 512.37279 | AD8: =Z8-AA8+Y8 -> 0
A9: =A8+1 -> 3 | B9: ILI | C9: B/0000597/082-83 | D9: 45867 | E9: purchase | F9: 996 | G9: =IF(Table242830891013141516171819[[#This Row],[SPPU]]>0,0,Table242830891013141516171819[[#This Row],[Total Purchase Amount]]/Table242830891013141516171819[[#This Row],[Purchase QTY]]) -> 485 | H9: 483060 | I9: 0 | J9: =IFERROR(Table242830891013141516171819[[#This Row],[Sales Amt]]/Table242830891013141516171819[[#This Row],[Sales Qty]],0) -> 0 | K9: 0 | L9: =Table242830891013141516171819[[#This Row],[Sales Qty]]*O8 -> 0 | M9: =M8+Table242830891013141516171819[[#This Row],[Total Purchase Amount]]-Table242830891013141516171819[[#This Row],[Principal Cost As per NFRS (In case of Sales)]] -> 5789169 | N9: =N8+Table242830891013141516171819[[#This Row],[Purchase QTY]]-Table242830891013141516171819[[#This Row],[Sales Qty]] -> 12446 | O9: =IFERROR(Table242830891013141516171819[[#This Row],[TC AP NFRS]]/Table242830891013141516171819[[#This Row],[Unit Sum]],0) -> 465.14294 | P9: =Table242830891013141516171819[[#This Row],[Sales Amt]]-Table242830891013141516171819[[#This Row],[Principal Cost As per NFRS (In case of Sales)]] -> 0 | R9: =72.41+1635.68 -> 1708.09 | S9: 25 | T9: =R9+S9 -> 1733.09 | U9: =H9+T9 -> 484793.09 | V9: 0 | W9: 0 | X9: =V9+W9 -> 0 | Y9: 0 | Z9: =K9-X9-Y9 -> 0 | AA9: =I9*AC8 -> 0 | AB9: =AB8+U9-AA9 -> 6351461.5 | AC9: =IFERROR(AB9/N9,0) -> 510.32151 | AD9: =Z9-AA9+Y9 -> 0
A10: =A9+1 -> 4 | G10: =IF(Table242830891013141516171819[[#This Row],[SPPU]]>=0,0,Table242830891013141516171819[[#This Row],[Total Purchase Amount]]/Table242830891013141516171819[[#This Row],[Purchase QTY]]) -> 0 | I10: 0 | J10: 0 | K10: =Table242830891013141516171819[[#This Row],[Sales Qty]]*Table242830891013141516171819[[#This Row],[SPPU]] -> 0 | L10: =Table242830891013141516171819[[#This Row],[Sales Qty]]*O9 -> 0 | M10: =M9+Table242830891013141516171819[[#This Row],[Total Purchase Amount]]-Table242830891013141516171819[[#This Row],[Principal Cost As per NFRS (In case of Sales)]] -> 5789169 | N10: =N9+Table242830891013141516171819[[#This Row],[Purchase QTY]]-Table242830891013141516171819[[#This Row],[Sales Qty]] -> 12446 | O10: =IFERROR(Table242830891013141516171819[[#This Row],[TC AP NFRS]]/Table242830891013141516171819[[#This Row],[Unit Sum]],0) -> 465.14294 | P10: =Table242830891013141516171819[[#This Row],[Sales Amt]]-Table242830891013141516171819[[#This Row],[Principal Cost As per NFRS (In case of Sales)]] -> 0 | R10: 0 | T10: =R10+S10 -> 0 | U10: =H10+T10 -> 0 | V10: 0 | W10: 0 | X10: =V10+W10 -> 0 | Y10: 0 | Z10: =K10-X10-Y10 -> 0 | AA10: =I10*AC9 -> 0 | AB10: =AB9+U10-AA10 -> 6351461.5 | AC10: =IFERROR(AB10/N10,0) -> 510.32151 | AD10: =Z10-AA10+Y10 -> 0
A11: =A10+1 -> 5 | G11: =IF(Table242830891013141516171819[[#This Row],[SPPU]]>=0,0,Table242830891013141516171819[[#This Row],[Total Purchase Amount]]/Table242830891013141516171819[[#This Row],[Purchase QTY]]) -> #DIV/0! | I11: 0 | J11: =Table242830891013141516171819[[#This Row],[Sales Amt]]/Table242830891013141516171819[[#This Row],[Sales Qty]] -> #DIV/0! | K11: 0 | L11: =Table242830891013141516171819[[#This Row],[Sales Qty]]*O10 -> 0 | M11: =M10+Table242830891013141516171819[[#This Row],[Total Purchase Amount]]-Table242830891013141516171819[[#This Row],[Principal Cost As per NFRS (In case of Sales)]] -> 5789169 | N11: =N10+Table242830891013141516171819[[#This Row],[Purchase QTY]]-Table242830891013141516171819[[#This Row],[Sales Qty]] -> 12446 | O11: =IFERROR(Table242830891013141516171819[[#This Row],[TC AP NFRS]]/Table242830891013141516171819[[#This Row],[Unit Sum]],0) -> 465.14294 | P11: =Table242830891013141516171819[[#This Row],[Sales Amt]]-Table242830891013141516171819[[#This Row],[Principal Cost As per NFRS (In case of Sales)]] -> 0 | R11: 0 | T11: =R11+S11 -> 0 | U11: =H11+T11 -> 0 | V11: 0 | W11: 0 | X11: =V11+W11 -> 0 | Y11: 0 | Z11: =K11-X11-Y11 -> 0 | AA11: =I11*AC10 -> 0 | AB11: =AB10+U11-AA11 -> 6351461.5 | AC11: =IFERROR(AB11/N11,0) -> 510.32151 | AD11: =Z11-AA11+Y11 -> 0
A12: =A11+1 -> 6 | F12: 0 | G12: =Table242830891013141516171819[[#This Row],[Total Purchase Amount]]/Table242830891013141516171819[[#This Row],[Purchase QTY]] -> #DIV/0! | H12: 0 | I12: 0 | J12: =IFERROR(Table242830891013141516171819[[#This Row],[Sales Amt]]/Table242830891013141516171819[[#This Row],[Sales Qty]],0) -> 0 | K12: =Table242830891013141516171819[[#This Row],[Sales Qty]]*Table242830891013141516171819[[#This Row],[SPPU]] -> 0 | L12: =Table242830891013141516171819[[#This Row],[Sales Qty]]*O11 -> 0 | M12: =M11+Table242830891013141516171819[[#This Row],[Total Purchase Amount]]-Table242830891013141516171819[[#This Row],[Principal Cost As per NFRS (In case of Sales)]] -> 5789169 | N12: =N11+Table242830891013141516171819[[#This Row],[Purchase QTY]]-Table242830891013141516171819[[#This Row],[Sales Qty]] -> 12446 | O12: =IFERROR(Table242830891013141516171819[[#This Row],[TC AP NFRS]]/Table242830891013141516171819[[#This Row],[Unit Sum]],0) -> 465.14294 | P12: =Table242830891013141516171819[[#This Row],[Sales Amt]]-Table242830891013141516171819[[#This Row],[Principal Cost As per NFRS (In case of Sales)]] -> 0 | R12: 0 | T12: =R12+S12 -> 0 | U12: =H12+T12 -> 0 | V12: 0 | W12: 0 | X12: =V12+W12 -> 0 | Y12: 0 | Z12: =K12-X12-Y12 -> 0 | AA12: =I12*AC11 -> 0 | AB12: =AB11+U12-AA12 -> 6351461.5 | AC12: =IFERROR(AB12/N12,0) -> 510.32151 | AD12: =Z12-AA12+Y12 -> 0
A13: =A12+1 -> 7 | F13: 0 | G13: =Table242830891013141516171819[[#This Row],[Total Purchase Amount]]/Table242830891013141516171819[[#This Row],[Purchase QTY]] -> #DIV/0! | H13: 0 | I13: 0 | J13: =IFERROR(Table242830891013141516171819[[#This Row],[Sales Amt]]/Table242830891013141516171819[[#This Row],[Sales Qty]],0) -> 0 | K13: =Table242830891013141516171819[[#This Row],[Sales Qty]]*Table242830891013141516171819[[#This Row],[SPPU]] -> 0 | L13: =Table242830891013141516171819[[#This Row],[Sales Qty]]*O12 -> 0 | M13: =M12+Table242830891013141516171819[[#This Row],[Total Purchase Amount]]-Table242830891013141516171819[[#This Row],[Principal Cost As per NFRS (In case of Sales)]] -> 5789169 | N13: =N12+Table242830891013141516171819[[#This Row],[Purchase QTY]]-Table242830891013141516171819[[#This Row],[Sales Qty]] -> 12446 | O13: =IFERROR(Table242830891013141516171819[[#This Row],[TC AP NFRS]]/Table242830891013141516171819[[#This Row],[Unit Sum]],0) -> 465.14294 | P13: =Table242830891013141516171819[[#This Row],[Sales Amt]]-Table242830891013141516171819[[#This Row],[Principal Cost As per NFRS (In case of Sales)]] -> 0 | R13: 0 | T13: =R13+S13 -> 0 | U13: =H13+T13 -> 0 | V13: 0 | W13: 0 | X13: =V13+W13 -> 0 | Y13: 0 | Z13: =K13-X13-Y13 -> 0 | AA13: =I13*AC12 -> 0 | AB13: =AB12+U13-AA13 -> 6351461.5 | AC13: =IFERROR(AB13/N13,0) -> 510.32151 | AD13: =Z13-AA13+Y13 -> 0
A14: =A13+1 -> 8 | G14: =IF(Table242830891013141516171819[[#This Row],[SPPU]]>=0,0,Table242830891013141516171819[[#This Row],[Total Purchase Amount]]/Table242830891013141516171819[[#This Row],[Purchase QTY]]) -> 0 | I14: 0 | J14: =IFERROR(Table242830891013141516171819[[#This Row],[Sales Amt]]/Table242830891013141516171819[[#This Row],[Sales Qty]],0) -> 0 | K14: 0 | L14: =Table242830891013141516171819[[#This Row],[Sales Qty]]*O12 -> 0 | M14: =M13+Table242830891013141516171819[[#This Row],[Total Purchase Amount]]-Table242830891013141516171819[[#This Row],[Principal Cost As per NFRS (In case of Sales)]] -> 5789169 | N14: =N13+Table242830891013141516171819[[#This Row],[Purchase QTY]]-Table242830891013141516171819[[#This Row],[Sales Qty]] -> 12446 | O14: =IFERROR(Table242830891013141516171819[[#This Row],[TC AP NFRS]]/Table242830891013141516171819[[#This Row],[Unit Sum]],0) -> 465.14294 | P14: =Table242830891013141516171819[[#This Row],[Sales Amt]]-Table242830891013141516171819[[#This Row],[Principal Cost As per NFRS (In case of Sales)]] -> 0 | R14: 0 | T14: =R14+S14 -> 0 | U14: =H14+T14 -> 0 | V14: 0 | W14: 0 | X14: =V14+W14 -> 0 | Y14: 0 | Z14: =K14-X14-Y14 -> 0 | AA14: =I14*AC13 -> 0 | AB14: =AB13+U14-AA14 -> 6351461.5 | AC14: =IFERROR(AB14/N14,0) -> 510.32151 | AD14: =Z14-AA14+Y14 -> 0
A15: =A14+1 -> 9 | G15: =IF(Table242830891013141516171819[[#This Row],[SPPU]]>=0,0,Table242830891013141516171819[[#This Row],[Total Purchase Amount]]/Table242830891013141516171819[[#This Row],[Purchase QTY]]) -> 0 | I15: 0 | J15: 0 | K15: 0 | L15: =Table242830891013141516171819[[#This Row],[Sales Qty]]*O14 -> 0 | M15: =M14+Table242830891013141516171819[[#This Row],[Total Purchase Amount]]-Table242830891013141516171819[[#This Row],[Principal Cost As per NFRS (In case of Sales)]] -> 5789169 | N15: =N14+Table242830891013141516171819[[#This Row],[Purchase QTY]]-Table242830891013141516171819[[#This Row],[Sales Qty]] -> 12446 | O15: =IFERROR(Table242830891013141516171819[[#This Row],[TC AP NFRS]]/Table242830891013141516171819[[#This Row],[Unit Sum]],0) -> 465.14294 | P15: =Table242830891013141516171819[[#This Row],[Sales Amt]]-Table242830891013141516171819[[#This Row],[Principal Cost As per NFRS (In case of Sales)]] -> 0 | R15: 0 | T15: =R15+S15 -> 0 | U15: =H15+T15 -> 0 | V15: 0 | W15: 0 | X15: =V15+W15 -> 0 | Y15: 0 | Z15: =K15-X15-Y15 -> 0 | AA15: =I15*AC14 -> 0 | AB15: =AB14+U15-AA15 -> 6351461.5 | AC15: =IFERROR(AB15/N15,0) -> 510.32151 | AD15: =Z15-AA15+Y15 -> 0
A16: =A15+1 -> 10 | G16: =IF(Table242830891013141516171819[[#This Row],[SPPU]]>=0,0,Table242830891013141516171819[[#This Row],[Total Purchase Amount]]/Table242830891013141516171819[[#This Row],[Purchase QTY]]) -> #DIV/0! | I16: 0 | J16: =Table242830891013141516171819[[#This Row],[Sales Amt]]/Table242830891013141516171819[[#This Row],[Sales Qty]] -> #DIV/0! | K16: 0 | L16: =Table242830891013141516171819[[#This Row],[Sales Qty]]*O15 -> 0 | M16: =M15+Table242830891013141516171819[[#This Row],[Total Purchase Amount]]-Table242830891013141516171819[[#This Row],[Principal Cost As per NFRS (In case of Sales)]] -> 5789169 | N16: =N15+Table242830891013141516171819[[#This Row],[Purchase QTY]]-Table242830891013141516171819[[#This Row],[Sales Qty]] -> 12446 | O16: =IFERROR(Table242830891013141516171819[[#This Row],[TC AP NFRS]]/Table242830891013141516171819[[#This Row],[Unit Sum]],0) -> 465.14294 | P16: =Table242830891013141516171819[[#This Row],[Sales Amt]]-Table242830891013141516171819[[#This Row],[Principal Cost As per NFRS (In case of Sales)]] -> 0 | R16: 0 | T16: =R16+S16 -> 0 | U16: =H16+T16 -> 0 | V16: 0 | W16: 0 | X16: =V16+W16 -> 0 | Y16: 0 | Z16: =K16-X16-Y16 -> 0 | AA16: =I16*AC15 -> 0 | AB16: =AB15+U16-AA16 -> 6351461.5 | AC16: =IFERROR(AB16/N16,0) -> 510.32151 | AD16: =Z16-AA16+Y16 -> 0
A17: Total | F17: =SUM(INDIRECT("f4:f"&ROW()-1)) -> 12446 | H17: =SUM(INDIRECT("h4:h"&ROW()-1)) -> 5789169 | I17: =SUM(INDIRECT("i4:i"&ROW()-1)) -> 0 | J17: =Table242830891013141516171819[[#This Row],[Sales Amt]]/Table242830891013141516171819[[#This Row],[Sales Qty]] -> #DIV/0! | K17: =SUM(K7:K10) -> 0 | M17: =Table242830891013141516171819[[#This Row],[Total Purchase Amount]]-Table242830891013141516171819[[#This Row],[Principal Cost As per NFRS (In case of Sales)]] -> 5789169 | N17: =Table242830891013141516171819[[#This Row],[Purchase QTY]]-Table242830891013141516171819[[#This Row],[Sales Qty]] -> 12446 | O17: =Table242830891013141516171819[[#This Row],[TC AP NFRS]]/Table242830891013141516171819[[#This Row],[Unit Sum]] -> 465.14294 | R17: =SUM(R7:R16) -> 3376.55 | S17: =SUM(S7:S16) -> 50 | T17: =SUM(T7:T16) -> 3426.55 | U17: =SUM(U7:U16) -> 6351461.5 | V17: =SUM(V7:V16) -> 0 | W17: =SUM(W7:W16) -> 0 | X17: =SUM(X7:X16) -> 0 | Y17: =SUM(Y7:Y16) -> 0 | ... AA17: =SUM(AA7:AA16) -> 0 | AB17: =U17-AA17 -> 6351461.5 | AC17: =IFERROR(AB17/N17,0) -> 510.32151 | AD17: =SUM(AD7:AD16) -> 0
A19: 2. Bhadra | R19: Purchase | V19: Sales | Y19: Capital Gain Tax | Z19: Net Receivables | AA19: Principal Amt AP TAX (Sales Unit) | AB19: TC AP TAX | AC19: WACC AP TAX | AD19: P/L AP TAX
A20: S.No | B20: SYMBOL | C20: Bill No | D20: Txn Date | E20: Txn Type | F20: Purchase QTY | G20: PPPU | H20: Total Purchase Amount | I20: Sales Qty | J20: SPPU | K20: Sales Amt | L20: Principal Cost As per NFRS (In case of Sales) | M20: TC AP NFRS | N20: Unit Sum | O20: WACC AP NFRS | P20: P/L AP NFRS | R20: Purchase Commission | S20: DP Charges | T20: Total Commission on Purchase | U20: Total Investment Cost(Including Comission | V20: Sales Commission | W20: DP Charges | X20: Total Commission on Sales
A21: 1 | B21: ILI | D21: 45886 | E21: Opening | F21: 12446 | H21: 5789169 | M21: 5789169 | N21: 12446 | O21: 465.14294 | R21: 3376.55 | S21: 50 | T21: 3426.55 | U21: 6351461.5 | AB21: 6351461.5 | AC21: 510.32151

Sheet UAIL
A1: Jyoti Capital Limited
A2: Kamalpokhari, Kathmandu
A3: JCL Portfolio Statement
A5: 1. Shrawan | R5: Purchase | V5: Sales | Y5: Capital Gain Tax | Z5: Net Receivables | AA5: Principal Amt AP TAX (Sales Unit) | AB5: TC AP TAX | AC5: WACC AP TAX | AD5: P/L AP TAX
A6: S.No | B6: SYMBOL | C6: Bill No | D6: Txn Date | E6: Txn Type | F6: Purchase QTY | G6: PPPU | H6: Total Purchase Amount | I6: Sales Qty | J6: SPPU | K6: Sales Amt | L6: Principal Cost As per NFRS (In case of Sales) | M6: TC AP NFRS | N6: Unit Sum | O6: WACC AP NFRS | P6: P/L AP NFRS | R6: Purchase Commission | S6: DP Charges | T6: Total Commission on Purchase | U6: Total Investment Cost(Including Comission | V6: Sales Commission | W6: DP Charges | X6: Total Commission on Sales
A7: 1 | B7: UAIL | D7: 45855 | E7: Opening | F7: 6013 | G7: 571.56 | H7: =Table2428308910131415161718[[#This Row],[Purchase QTY]]*Table2428308910131415161718[[#This Row],[PPPU]] -> 3436790.3 | M7: =Table2428308910131415161718[[#This Row],[Total Purchase Amount]] -> 3436790.3 | N7: =IF(Table2428308910131415161718[[#This Row],[Txn Type]]="opening",Table2428308910131415161718[[#This Row],[Purchase QTY]],"Error") -> 6013 | O7: =IFERROR(Table2428308910131415161718[[#This Row],[TC AP NFRS]]/Table2428308910131415161718[[#This Row],[Unit Sum]],0) -> 571.56 | P7: =Table2428308910131415161718[[#This Row],[Sales Amt]]-Table2428308910131415161718[[#This Row],[Principal Cost As per NFRS (In case of Sales)]] -> 0 | T7: =R7+S7 -> 0 | U7: =AB7 -> 3859776.5 | AB7: =F7*AC7 -> 3859776.5 | AC7: 641.90528
A8: =A7+1 -> 2 | B8: UAIL | C8: B/0000049/082-83 | D8: 45855 | E8: purchase | F8: 500 | G8: =Table2428308910131415161718[[#This Row],[Total Purchase Amount]]/Table2428308910131415161718[[#This Row],[Purchase QTY]] -> 595 | H8: 297500 | I8: 0 | J8: =IFERROR(Table2428308910131415161718[[#This Row],[Sales Amt]]/Table2428308910131415161718[[#This Row],[Sales Qty]],0) -> 0 | K8: 0 | L8: =Table2428308910131415161718[[#This Row],[Sales Qty]]*O7 -> 0 | M8: =M7+Table2428308910131415161718[[#This Row],[Total Purchase Amount]]-Table2428308910131415161718[[#This Row],[Principal Cost As per NFRS (In case of Sales)]] -> 3734290.3 | N8: =N7+Table2428308910131415161718[[#This Row],[Purchase QTY]]-Table2428308910131415161718[[#This Row],[Sales Qty]] -> 6513 | O8: =IFERROR(Table2428308910131415161718[[#This Row],[TC AP NFRS]]/Table2428308910131415161718[[#This Row],[Unit Sum]],0) -> 573.35948 | P8: =Table2428308910131415161718[[#This Row],[Sales Amt]]-Table2428308910131415161718[[#This Row],[Principal Cost As per NFRS (In case of Sales)]] -> 0 | R8: =44.63+981.75 -> 1026.38 | S8: 25 | T8: =R8+S8 -> 1051.38 | U8: =H8+T8 -> 298551.38 | V8: 0 | W8: 0 | X8: =V8+W8 -> 0 | Y8: 0 | Z8: =K8-X8-Y8 -> 0 | AA8: =I8*AC7 -> 0 | AB8: =AB7+U8-AA8 -> 4158327.9 | AC8: =IFERROR(AB8/N8,0) -> 638.46582 | AD8: =Z8-AA8+Y8 -> 0
A9: =A8+1 -> 3 | B9: UAIL | C9: S/0004076/082-83 | D9: 45872 | E9: sale | F9: 0 | G9: =IF(Table2428308910131415161718[[#This Row],[SPPU]]>=0,0,Table2428308910131415161718[[#This Row],[Total Purchase Amount]]/Table2428308910131415161718[[#This Row],[Purchase QTY]]) -> 0 | H9: 0 | I9: 1500 | J9: =IFERROR(Table2428308910131415161718[[#This Row],[Sales Amt]]/Table2428308910131415161718[[#This Row],[Sales Qty]],0) -> 577.7268 | K9: 866590.2 | L9: =Table2428308910131415161718[[#This Row],[Sales Qty]]*O8 -> 860039.22 | M9: =M8+Table2428308910131415161718[[#This Row],[Total Purchase Amount]]-Table2428308910131415161718[[#This Row],[Principal Cost As per NFRS (In case of Sales)]] -> 2874251.1 | N9: =N8+Table2428308910131415161718[[#This Row],[Purchase QTY]]-Table2428308910131415161718[[#This Row],[Sales Qty]] -> 5013 | O9: =IFERROR(Table2428308910131415161718[[#This Row],[TC AP NFRS]]/Table2428308910131415161718[[#This Row],[Unit Sum]],0) -> 573.35948 | P9: =Table2428308910131415161718[[#This Row],[Sales Amt]]-Table2428308910131415161718[[#This Row],[Principal Cost As per NFRS (In case of Sales)]] -> 6550.983 | R9: 0 | S9: 0 | T9: 0 | U9: =H9+T9 -> 0 | V9: =129.99+2904.83 -> 3034.82 | W9: 25 | X9: =V9+W9 -> 3059.82 | Y9: 0 | Z9: =K9-X9-Y9 -> 863530.38 | AA9: =I9*AC8 -> 957698.72 | AB9: =AB8+U9-AA9 -> 3200629.1 | AC9: =IFERROR(AB9/N9,0) -> 638.46582 | AD9: =Z9-AA9+Y9 -> -94168.344
A10: =A9+1 -> 4 | B10: UAIL | C10: S/0004465/082-83 | D10: 45873 | E10: sale | G10: =IF(Table2428308910131415161718[[#This Row],[SPPU]]>=0,0,Table2428308910131415161718[[#This Row],[Total Purchase Amount]]/Table2428308910131415161718[[#This Row],[Purchase QTY]]) -> 0 | I10: 700 | J10: =IFERROR(Table2428308910131415161718[[#This Row],[Sales Amt]]/Table2428308910131415161718[[#This Row],[Sales Qty]],0) -> 579.71429 | K10: 405800 | L10: =Table2428308910131415161718[[#This Row],[Sales Qty]]*O9 -> 401351.63 | M10: =M9+Table2428308910131415161718[[#This Row],[Total Purchase Amount]]-Table2428308910131415161718[[#This Row],[Principal Cost As per NFRS (In case of Sales)]] -> 2472899.4 | N10: =N9+Table2428308910131415161718[[#This Row],[Purchase QTY]]-Table2428308910131415161718[[#This Row],[Sales Qty]] -> 4313 | O10: =IFERROR(Table2428308910131415161718[[#This Row],[TC AP NFRS]]/Table2428308910131415161718[[#This Row],[Unit Sum]],0) -> 573.35948 | P10: =Table2428308910131415161718[[#This Row],[Sales Amt]]-Table2428308910131415161718[[#This Row],[Principal Cost As per NFRS (In case of Sales)]] -> 4448.3654 | R10: 0 | T10: =R10+S10 -> 0 | U10: =H10+T10 -> 0 | V10: =60.88+1366.34 -> 1427.22 | W10: 25 | X10: =V10+W10 -> 1452.22 | Y10: 0 | Z10: =K10-X10-Y10 -> 404347.78 | AA10: =I10*AC9 -> 446926.07 | AB10: =AB9+U10-AA10 -> 2753703.1 | AC10: =IFERROR(AB10/N10,0) -> 638.46582 | AD10: =Z10-AA10+Y10 -> -42578.291
A11: =A10+1 -> 5 | B11: UAIL | C11: S/0004654/082-83 | D11: 45874 | E11: sale | G11: =IF(Table2428308910131415161718[[#This Row],[SPPU]]>=0,0,Table2428308910131415161718[[#This Row],[Total Purchase Amount]]/Table2428308910131415161718[[#This Row],[Purchase QTY]]) -> 0 | I11: 92 | J11: =Table2428308910131415161718[[#This Row],[Sales Amt]]/Table2428308910131415161718[[#This Row],[Sales Qty]] -> 577.9 | K11: 53166.8 | L11: =Table2428308910131415161718[[#This Row],[Sales Qty]]*O10 -> 52749.072 | M11: =M10+Table2428308910131415161718[[#This Row],[Total Purchase Amount]]-Table2428308910131415161718[[#This Row],[Principal Cost As per NFRS (In case of Sales)]] -> 2420150.4 | N11: =N10+Table2428308910131415161718[[#This Row],[Purchase QTY]]-Table2428308910131415161718[[#This Row],[Sales Qty]] -> 4221 | O11: =IFERROR(Table2428308910131415161718[[#This Row],[TC AP NFRS]]/Table2428308910131415161718[[#This Row],[Unit Sum]],0) -> 573.35948 | P11: =Table2428308910131415161718[[#This Row],[Sales Amt]]-Table2428308910131415161718[[#This Row],[Principal Cost As per NFRS (In case of Sales)]] -> 417.72803 | R11: 0 | T11: =R11+S11 -> 0 | U11: =H11+T11 -> 0 | V11: =7.98+175.45 -> 183.43 | W11: 25 | X11: =V11+W11 -> 208.43 | Y11: 0 | Z11: =K11-X11-Y11 -> 52958.37 | AA11: =I11*AC10 -> 58738.855 | AB11: =AB10+U11-AA11 -> 2694964.2 | AC11: 721.95 | AD11: =Z11-AA11+Y11 -> -5780.4851
